{"id":"ekstep.content.find","ver":"3.0","ts":"2018-11-08T15:28:47ZZ","params":{"resmsgid":"cf657c77-ab31-450e-a338-c142437a3b51","msgid":null,"err":null,"status":"successful","errmsg":null},"responseCode":"OK","result":{"content":{"identifier":"do_21258891296725401611444","body":"{\"theme\":{\"id\":\"theme\",\"version\":\"1.0\",\"startStage\":\"1dc7a2e2-be16-4e1d-a148-650e2cceaced\",\"stage\":[{\"x\":0,\"y\":0,\"w\":100,\"h\":100,\"id\":\"1dc7a2e2-be16-4e1d-a148-650e2cceaced\",\"rotate\":null,\"config\":{\"__cdata\":\"{\\\"opacity\\\":100,\\\"strokeWidth\\\":1,\\\"stroke\\\":\\\"rgba(255, 255, 255, 0)\\\",\\\"autoplay\\\":false,\\\"visible\\\":true,\\\"color\\\":\\\"#FFFFFF\\\",\\\"genieControls\\\":false,\\\"instructions\\\":\\\"\\\"}\"},\"manifest\":{\"media\":[{\"assetId\":\"QuizImage\"},{\"assetId\":\"audioIcon\"},{\"assetId\":\"zoomIcon\"},{\"assetId\":\"org.ekstep.keyboard.eras_icon\"},{\"assetId\":\"org.ekstep.keyboard.language_icon\"},{\"assetId\":\"org.ekstep.keyboard.hide_keyboard\"}]},\"org.ekstep.questionset\":[{\"x\":9,\"y\":6,\"w\":80,\"h\":85,\"rotate\":0,\"z-index\":0,\"id\":\"7c9713d1-c918-4d64-88cd-5542110e47e3\",\"data\":{\"__cdata\":\"[{\\\"code\\\":\\\"NA\\\",\\\"isShuffleOption\\\":false,\\\"body\\\":\\\"{\\\\\\\"data\\\\\\\":{\\\\\\\"plugin\\\\\\\":{\\\\\\\"id\\\\\\\":\\\\\\\"org.ekstep.questionunit.ftb\\\\\\\",\\\\\\\"version\\\\\\\":\\\\\\\"1.0\\\\\\\",\\\\\\\"templateId\\\\\\\":\\\\\\\"ftbtemplate\\\\\\\"},\\\\\\\"data\\\\\\\":{\\\\\\\"question\\\\\\\":{\\\\\\\"text\\\\\\\":\\\\\\\"FTB [[test]]\\\\\\\\n\\\\\\\",\\\\\\\"image\\\\\\\":\\\\\\\"\\\\\\\",\\\\\\\"audio\\\\\\\":\\\\\\\"\\\\\\\",\\\\\\\"audioName\\\\\\\":\\\\\\\"\\\\\\\",\\\\\\\"keyboardConfig\\\\\\\":{\\\\\\\"keyboardType\\\\\\\":\\\\\\\"Device\\\\\\\",\\\\\\\"customKeys\\\\\\\":[]}},\\\\\\\"answer\\\\\\\":[\\\\\\\"test\\\\\\\"],\\\\\\\"media\\\\\\\":[{\\\\\\\"id\\\\\\\":\\\\\\\"org.ekstep.keyboard.eras_icon\\\\\\\",\\\\\\\"src\\\\\\\":\\\\\\\"/content-plugins/org.ekstep.keyboard-1.0/renderer/assets/eras_icon.png\\\\\\\",\\\\\\\"assetId\\\\\\\":\\\\\\\"org.ekstep.keyboard.eras_icon\\\\\\\",\\\\\\\"type\\\\\\\":\\\\\\\"image\\\\\\\",\\\\\\\"preload\\\\\\\":true},{\\\\\\\"id\\\\\\\":\\\\\\\"org.ekstep.keyboard.language_icon\\\\\\\",\\\\\\\"src\\\\\\\":\\\\\\\"/content-plugins/org.ekstep.keyboard-1.0/renderer/assets/language_icon.png\\\\\\\",\\\\\\\"assetId\\\\\\\":\\\\\\\"org.ekstep.keyboard.language_icon\\\\\\\",\\\\\\\"type\\\\\\\":\\\\\\\"image\\\\\\\",\\\\\\\"preload\\\\\\\":true},{\\\\\\\"id\\\\\\\":\\\\\\\"org.ekstep.keyboard.hide_keyboard\\\\\\\",\\\\\\\"src\\\\\\\":\\\\\\\"/content-plugins/org.ekstep.keyboard-1.0/renderer/assets/keyboard.svg\\\\\\\",\\\\\\\"assetId\\\\\\\":\\\\\\\"org.ekstep.keyboard.hide_keyboard\\\\\\\",\\\\\\\"type\\\\\\\":\\\\\\\"image\\\\\\\",\\\\\\\"preload\\\\\\\":true}]},\\\\\\\"config\\\\\\\":{\\\\\\\"metadata\\\\\\\":{\\\\\\\"questionMaxScore\\\\\\\":1,\\\\\\\"isShuffleOption\\\\\\\":false,\\\\\\\"isPartialScore\\\\\\\":true,\\\\\\\"templateType\\\\\\\":\\\\\\\"Horizontal\\\\\\\",\\\\\\\"name\\\\\\\":\\\\\\\"FTB ____\\\\\\\\n\\\\\\\",\\\\\\\"title\\\\\\\":\\\\\\\"FTB ____\\\\\\\\n\\\\\\\",\\\\\\\"board\\\\\\\":\\\\\\\"State (Rajasthan)\\\\\\\",\\\\\\\"topic\\\\\\\":[],\\\\\\\"medium\\\\\\\":\\\\\\\"Hindi\\\\\\\",\\\\\\\"gradeLevel\\\\\\\":[\\\\\\\"Class 9\\\\\\\"],\\\\\\\"subject\\\\\\\":\\\\\\\"Mathematics\\\\\\\",\\\\\\\"max_score\\\\\\\":2,\\\\\\\"qlevel\\\\\\\":\\\\\\\"EASY\\\\\\\",\\\\\\\"category\\\\\\\":\\\\\\\"FTB\\\\\\\"},\\\\\\\"max_time\\\\\\\":0,\\\\\\\"max_score\\\\\\\":2,\\\\\\\"partial_scoring\\\\\\\":true,\\\\\\\"layout\\\\\\\":\\\\\\\"Horizontal\\\\\\\",\\\\\\\"isShuffleOption\\\\\\\":false,\\\\\\\"questionCount\\\\\\\":1},\\\\\\\"media\\\\\\\":[{\\\\\\\"id\\\\\\\":\\\\\\\"org.ekstep.keyboard.eras_icon\\\\\\\",\\\\\\\"src\\\\\\\":\\\\\\\"/content-plugins/org.ekstep.keyboard-1.0/renderer/assets/eras_icon.png\\\\\\\",\\\\\\\"assetId\\\\\\\":\\\\\\\"org.ekstep.keyboard.eras_icon\\\\\\\",\\\\\\\"type\\\\\\\":\\\\\\\"image\\\\\\\",\\\\\\\"preload\\\\\\\":true},{\\\\\\\"id\\\\\\\":\\\\\\\"org.ekstep.keyboard.language_icon\\\\\\\",\\\\\\\"src\\\\\\\":\\\\\\\"/content-plugins/org.ekstep.keyboard-1.0/renderer/assets/language_icon.png\\\\\\\",\\\\\\\"assetId\\\\\\\":\\\\\\\"org.ekstep.keyboard.language_icon\\\\\\\",\\\\\\\"type\\\\\\\":\\\\\\\"image\\\\\\\",\\\\\\\"preload\\\\\\\":true},{\\\\\\\"id\\\\\\\":\\\\\\\"org.ekstep.keyboard.hide_keyboard\\\\\\\",\\\\\\\"src\\\\\\\":\\\\\\\"/content-plugins/org.ekstep.keyboard-1.0/renderer/assets/keyboard.svg\\\\\\\",\\\\\\\"assetId\\\\\\\":\\\\\\\"org.ekstep.keyboard.hide_keyboard\\\\\\\",\\\\\\\"type\\\\\\\":\\\\\\\"image\\\\\\\",\\\\\\\"preload\\\\\\\":true}]}}\\\",\\\"itemType\\\":\\\"UNIT\\\",\\\"version\\\":2,\\\"category\\\":\\\"FTB\\\",\\\"createdBy\\\":\\\"9e607f86-21a8-445b-9854-42bbcf9f5a69\\\",\\\"channel\\\":\\\"0124758418460180480\\\",\\\"type\\\":\\\"ftb\\\",\\\"template\\\":\\\"NA\\\",\\\"template_id\\\":\\\"NA\\\",\\\"framework\\\":\\\"rj_k-12_2\\\",\\\"questionMaxScore\\\":1,\\\"isPartialScore\\\":true,\\\"templateType\\\":\\\"Horizontal\\\",\\\"name\\\":\\\"FTB ____\\\\n\\\",\\\"title\\\":\\\"FTB ____\\\\n\\\",\\\"board\\\":\\\"State (Rajasthan)\\\",\\\"topic\\\":[],\\\"medium\\\":\\\"Hindi\\\",\\\"gradeLevel\\\":[\\\"Class 9\\\"],\\\"subject\\\":\\\"Mathematics\\\",\\\"max_score\\\":2,\\\"qlevel\\\":\\\"EASY\\\",\\\"answer\\\":[{\\\"answer\\\":true,\\\"value\\\":{\\\"type\\\":\\\"text\\\",\\\"asset\\\":\\\"1\\\"}}],\\\"identifier\\\":\\\"do_21258891367797555211446\\\",\\\"isSelected\\\":true,\\\"$$hashKey\\\":\\\"object:1265\\\"},{\\\"code\\\":\\\"NA\\\",\\\"isShuffleOption\\\":false,\\\"body\\\":\\\"{\\\\\\\"data\\\\\\\":{\\\\\\\"plugin\\\\\\\":{\\\\\\\"id\\\\\\\":\\\\\\\"org.ekstep.questionunit.mcq\\\\\\\",\\\\\\\"version\\\\\\\":\\\\\\\"1.1\\\\\\\",\\\\\\\"templateId\\\\\\\":\\\\\\\"horizontalMCQ\\\\\\\"},\\\\\\\"data\\\\\\\":{\\\\\\\"question\\\\\\\":{\\\\\\\"text\\\\\\\":\\\\\\\"<p>MCQ&nbsp;</p>\\\\\\\\n\\\\\\\",\\\\\\\"image\\\\\\\":\\\\\\\"\\\\\\\",\\\\\\\"audio\\\\\\\":\\\\\\\"\\\\\\\",\\\\\\\"audioName\\\\\\\":\\\\\\\"\\\\\\\",\\\\\\\"hint\\\\\\\":\\\\\\\"\\\\\\\"},\\\\\\\"options\\\\\\\":[{\\\\\\\"text\\\\\\\":\\\\\\\"1\\\\\\\",\\\\\\\"image\\\\\\\":\\\\\\\"\\\\\\\",\\\\\\\"audio\\\\\\\":\\\\\\\"\\\\\\\",\\\\\\\"audioName\\\\\\\":\\\\\\\"\\\\\\\",\\\\\\\"hint\\\\\\\":\\\\\\\"\\\\\\\",\\\\\\\"isCorrect\\\\\\\":true,\\\\\\\"$$hashKey\\\\\\\":\\\\\\\"object:1000\\\\\\\"},{\\\\\\\"text\\\\\\\":\\\\\\\"2\\\\\\\",\\\\\\\"image\\\\\\\":\\\\\\\"\\\\\\\",\\\\\\\"audio\\\\\\\":\\\\\\\"\\\\\\\",\\\\\\\"audioName\\\\\\\":\\\\\\\"\\\\\\\",\\\\\\\"hint\\\\\\\":\\\\\\\"\\\\\\\",\\\\\\\"isCorrect\\\\\\\":false,\\\\\\\"$$hashKey\\\\\\\":\\\\\\\"object:1001\\\\\\\"}],\\\\\\\"questionCount\\\\\\\":0,\\\\\\\"media\\\\\\\":[]},\\\\\\\"config\\\\\\\":{\\\\\\\"metadata\\\\\\\":{\\\\\\\"questionMaxScore\\\\\\\":1,\\\\\\\"isShuffleOption\\\\\\\":false,\\\\\\\"isPartialScore\\\\\\\":true,\\\\\\\"templateType\\\\\\\":\\\\\\\"Horizontal\\\\\\\",\\\\\\\"name\\\\\\\":\\\\\\\"MCQ \\\\\\\\n\\\\\\\",\\\\\\\"title\\\\\\\":\\\\\\\"MCQ \\\\\\\\n\\\\\\\",\\\\\\\"board\\\\\\\":\\\\\\\"State (Rajasthan)\\\\\\\",\\\\\\\"topic\\\\\\\":[],\\\\\\\"medium\\\\\\\":\\\\\\\"Hindi\\\\\\\",\\\\\\\"gradeLevel\\\\\\\":[\\\\\\\"Class 10\\\\\\\"],\\\\\\\"subject\\\\\\\":\\\\\\\"Mathematics\\\\\\\",\\\\\\\"max_score\\\\\\\":2,\\\\\\\"qlevel\\\\\\\":\\\\\\\"EASY\\\\\\\",\\\\\\\"category\\\\\\\":\\\\\\\"MCQ\\\\\\\"},\\\\\\\"max_time\\\\\\\":0,\\\\\\\"max_score\\\\\\\":2,\\\\\\\"partial_scoring\\\\\\\":true,\\\\\\\"layout\\\\\\\":\\\\\\\"Horizontal\\\\\\\",\\\\\\\"isShuffleOption\\\\\\\":false,\\\\\\\"questionCount\\\\\\\":1},\\\\\\\"media\\\\\\\":[]}}\\\",\\\"itemType\\\":\\\"UNIT\\\",\\\"version\\\":2,\\\"category\\\":\\\"MCQ\\\",\\\"createdBy\\\":\\\"9e607f86-21a8-445b-9854-42bbcf9f5a69\\\",\\\"channel\\\":\\\"0124758418460180480\\\",\\\"type\\\":\\\"mcq\\\",\\\"template\\\":\\\"NA\\\",\\\"template_id\\\":\\\"NA\\\",\\\"framework\\\":\\\"rj_k-12_2\\\",\\\"questionMaxScore\\\":1,\\\"isPartialScore\\\":true,\\\"templateType\\\":\\\"Horizontal\\\",\\\"name\\\":\\\"MCQ \\\\n\\\",\\\"title\\\":\\\"MCQ \\\\n\\\",\\\"board\\\":\\\"State (Rajasthan)\\\",\\\"topic\\\":[],\\\"medium\\\":\\\"Hindi\\\",\\\"gradeLevel\\\":[\\\"Class 10\\\"],\\\"subject\\\":\\\"Mathematics\\\",\\\"max_score\\\":2,\\\"qlevel\\\":\\\"EASY\\\",\\\"options\\\":[{\\\"answer\\\":true,\\\"value\\\":{\\\"type\\\":\\\"text\\\",\\\"asset\\\":\\\"1\\\"}}],\\\"identifier\\\":\\\"do_21258891331019571211445\\\",\\\"isSelected\\\":true,\\\"$$hashKey\\\":\\\"object:1119\\\"}]\"},\"config\":{\"__cdata\":\"{\\\"title\\\":\\\"test\\\",\\\"max_score\\\":4,\\\"allow_skip\\\":true,\\\"show_feedback\\\":true,\\\"shuffle_questions\\\":false,\\\"shuffle_options\\\":false,\\\"total_items\\\":2,\\\"btn_edit\\\":\\\"Edit\\\"}\"},\"org.ekstep.question\":[{\"id\":\"83d849a3-c989-4c8a-ac8d-2879a35553c7\",\"type\":\"ftb\",\"pluginId\":\"org.ekstep.questionunit.ftb\",\"pluginVer\":\"1.0\",\"templateId\":\"ftbtemplate\",\"data\":{\"__cdata\":\"{\\\"question\\\":{\\\"text\\\":\\\"FTB [[test]]\\\\n\\\",\\\"image\\\":\\\"\\\",\\\"audio\\\":\\\"\\\",\\\"audioName\\\":\\\"\\\",\\\"keyboardConfig\\\":{\\\"keyboardType\\\":\\\"Device\\\",\\\"customKeys\\\":[]}},\\\"answer\\\":[\\\"test\\\"],\\\"media\\\":[{\\\"id\\\":\\\"org.ekstep.keyboard.eras_icon\\\",\\\"src\\\":\\\"/content-plugins/org.ekstep.keyboard-1.0/renderer/assets/eras_icon.png\\\",\\\"assetId\\\":\\\"org.ekstep.keyboard.eras_icon\\\",\\\"type\\\":\\\"image\\\",\\\"preload\\\":true},{\\\"id\\\":\\\"org.ekstep.keyboard.language_icon\\\",\\\"src\\\":\\\"/content-plugins/org.ekstep.keyboard-1.0/renderer/assets/language_icon.png\\\",\\\"assetId\\\":\\\"org.ekstep.keyboard.language_icon\\\",\\\"type\\\":\\\"image\\\",\\\"preload\\\":true},{\\\"id\\\":\\\"org.ekstep.keyboard.hide_keyboard\\\",\\\"src\\\":\\\"/content-plugins/org.ekstep.keyboard-1.0/renderer/assets/keyboard.svg\\\",\\\"assetId\\\":\\\"org.ekstep.keyboard.hide_keyboard\\\",\\\"type\\\":\\\"image\\\",\\\"preload\\\":true}]}\"},\"config\":{\"__cdata\":\"{\\\"metadata\\\":{\\\"questionMaxScore\\\":1,\\\"isShuffleOption\\\":false,\\\"isPartialScore\\\":true,\\\"templateType\\\":\\\"Horizontal\\\",\\\"name\\\":\\\"FTB ____\\\\n\\\",\\\"title\\\":\\\"FTB ____\\\\n\\\",\\\"board\\\":\\\"State (Rajasthan)\\\",\\\"topic\\\":[],\\\"medium\\\":\\\"Hindi\\\",\\\"gradeLevel\\\":[\\\"Class 9\\\"],\\\"subject\\\":\\\"Mathematics\\\",\\\"max_score\\\":2,\\\"qlevel\\\":\\\"EASY\\\",\\\"category\\\":\\\"FTB\\\"},\\\"max_time\\\":0,\\\"max_score\\\":2,\\\"partial_scoring\\\":true,\\\"layout\\\":\\\"Horizontal\\\",\\\"isShuffleOption\\\":false,\\\"questionCount\\\":1}\"},\"w\":80,\"h\":85,\"x\":9,\"y\":6},{\"id\":\"a83b60cc-000b-4455-9290-d2108004056a\",\"type\":\"mcq\",\"pluginId\":\"org.ekstep.questionunit.mcq\",\"pluginVer\":\"1.1\",\"templateId\":\"horizontalMCQ\",\"data\":{\"__cdata\":\"{\\\"question\\\":{\\\"text\\\":\\\"<p>MCQ&nbsp;</p>\\\\n\\\",\\\"image\\\":\\\"\\\",\\\"audio\\\":\\\"\\\",\\\"audioName\\\":\\\"\\\",\\\"hint\\\":\\\"\\\"},\\\"options\\\":[{\\\"text\\\":\\\"1\\\",\\\"image\\\":\\\"\\\",\\\"audio\\\":\\\"\\\",\\\"audioName\\\":\\\"\\\",\\\"hint\\\":\\\"\\\",\\\"isCorrect\\\":true,\\\"$$hashKey\\\":\\\"object:1000\\\"},{\\\"text\\\":\\\"2\\\",\\\"image\\\":\\\"\\\",\\\"audio\\\":\\\"\\\",\\\"audioName\\\":\\\"\\\",\\\"hint\\\":\\\"\\\",\\\"isCorrect\\\":false,\\\"$$hashKey\\\":\\\"object:1001\\\"}],\\\"questionCount\\\":0,\\\"media\\\":[]}\"},\"config\":{\"__cdata\":\"{\\\"metadata\\\":{\\\"questionMaxScore\\\":1,\\\"isShuffleOption\\\":false,\\\"isPartialScore\\\":true,\\\"templateType\\\":\\\"Horizontal\\\",\\\"name\\\":\\\"MCQ \\\\n\\\",\\\"title\\\":\\\"MCQ \\\\n\\\",\\\"board\\\":\\\"State (Rajasthan)\\\",\\\"topic\\\":[],\\\"medium\\\":\\\"Hindi\\\",\\\"gradeLevel\\\":[\\\"Class 10\\\"],\\\"subject\\\":\\\"Mathematics\\\",\\\"max_score\\\":2,\\\"qlevel\\\":\\\"EASY\\\",\\\"category\\\":\\\"MCQ\\\"},\\\"max_time\\\":0,\\\"max_score\\\":2,\\\"partial_scoring\\\":true,\\\"layout\\\":\\\"Horizontal\\\",\\\"isShuffleOption\\\":false,\\\"questionCount\\\":1}\"},\"w\":80,\"h\":85,\"x\":9,\"y\":6}]}]}],\"manifest\":{\"media\":[{\"id\":\"10d38870-17ca-407b-ae79-47a01947369b\",\"plugin\":\"org.ekstep.navigation\",\"ver\":\"1.0\",\"src\":\"/content-plugins/org.ekstep.navigation-1.0/renderer/controller/navigation_ctrl.js\",\"type\":\"js\"},{\"id\":\"ca0b9265-03a8-4760-bb0a-4b3561346d0a\",\"plugin\":\"org.ekstep.navigation\",\"ver\":\"1.0\",\"src\":\"/content-plugins/org.ekstep.navigation-1.0/renderer/templates/navigation.html\",\"type\":\"js\"},{\"id\":\"org.ekstep.navigation\",\"plugin\":\"org.ekstep.navigation\",\"ver\":\"1.0\",\"src\":\"/content-plugins/org.ekstep.navigation-1.0/renderer/plugin.js\",\"type\":\"plugin\"},{\"id\":\"org.ekstep.navigation_manifest\",\"plugin\":\"org.ekstep.navigation\",\"ver\":\"1.0\",\"src\":\"/content-plugins/org.ekstep.navigation-1.0/manifest.json\",\"type\":\"json\"},{\"id\":\"648b0829-6d1e-4815-b034-bd24be6298c0\",\"plugin\":\"org.ekstep.questionunit\",\"ver\":\"1.0\",\"src\":\"/content-plugins/org.ekstep.questionunit-1.0/renderer/components/js/components.js\",\"type\":\"js\"},{\"id\":\"ebab2e01-2c4e-4449-8b9a-d2e038c2c402\",\"plugin\":\"org.ekstep.questionunit\",\"ver\":\"1.0\",\"src\":\"/content-plugins/org.ekstep.questionunit-1.0/renderer/components/css/components.css\",\"type\":\"css\"},{\"id\":\"9b3a9ed2-3067-4d11-8053-276180b82523\",\"plugin\":\"org.ekstep.questionunit\",\"ver\":\"1.0\",\"src\":\"/content-plugins/org.ekstep.questionunit-1.0/renderer/libs/katex/katex.min.js\",\"type\":\"js\"},{\"id\":\"22dbb9a1-d244-414e-8dd8-bdbd42851e3a\",\"plugin\":\"org.ekstep.questionunit\",\"ver\":\"1.0\",\"src\":\"/content-plugins/org.ekstep.questionunit-1.0/renderer/libs/katex/katex.min.css\",\"type\":\"css\"},{\"id\":\"b18a6216-9812-4a56-9c4d-18c78a667318\",\"plugin\":\"org.ekstep.questionunit\",\"ver\":\"1.0\",\"src\":\"/content-plugins/org.ekstep.questionunit-1.0/renderer/libs/katex/fonts/katex_main-bold.ttf\",\"type\":\"js\"},{\"id\":\"3c618237-b093-4a64-b72c-d731cd3e27bc\",\"plugin\":\"org.ekstep.questionunit\",\"ver\":\"1.0\",\"src\":\"/content-plugins/org.ekstep.questionunit-1.0/renderer/libs/katex/fonts/katex_main-bolditalic.ttf\",\"type\":\"js\"},{\"id\":\"a371c9c2-5400-40e4-85c4-23aa127e9558\",\"plugin\":\"org.ekstep.questionunit\",\"ver\":\"1.0\",\"src\":\"/content-plugins/org.ekstep.questionunit-1.0/renderer/libs/katex/fonts/katex_main-italic.ttf\",\"type\":\"js\"},{\"id\":\"77eed293-2278-4599-aebc-506066891e68\",\"plugin\":\"org.ekstep.questionunit\",\"ver\":\"1.0\",\"src\":\"/content-plugins/org.ekstep.questionunit-1.0/renderer/libs/katex/fonts/katex_main-regular.ttf\",\"type\":\"js\"},{\"id\":\"49c414c3-62ac-4961-a886-b739c1d1427b\",\"plugin\":\"org.ekstep.questionunit\",\"ver\":\"1.0\",\"src\":\"/content-plugins/org.ekstep.questionunit-1.0/renderer/libs/katex/fonts/katex_math-bolditalic.ttf\",\"type\":\"js\"},{\"id\":\"5971c906-90d2-4491-82e7-726b68615705\",\"plugin\":\"org.ekstep.questionunit\",\"ver\":\"1.0\",\"src\":\"/content-plugins/org.ekstep.questionunit-1.0/renderer/libs/katex/fonts/katex_math-italic.ttf\",\"type\":\"js\"},{\"id\":\"a03e7e32-3372-4b0c-be95-c1966eee1489\",\"plugin\":\"org.ekstep.questionunit\",\"ver\":\"1.0\",\"src\":\"/content-plugins/org.ekstep.questionunit-1.0/renderer/libs/katex/fonts/katex_math-regular.ttf\",\"type\":\"js\"},{\"id\":\"47895d52-9b59-4b95-a026-1ed196344ea2\",\"plugin\":\"org.ekstep.questionunit\",\"ver\":\"1.0\",\"src\":\"/content-plugins/org.ekstep.questionunit-1.0/renderer/libs/katex/fonts/katex_size1-regular.ttf\",\"type\":\"js\"},{\"id\":\"1b858751-463c-4370-8a2a-2ab6cb5144d9\",\"plugin\":\"org.ekstep.questionunit\",\"ver\":\"1.0\",\"src\":\"/content-plugins/org.ekstep.questionunit-1.0/renderer/libs/katex/fonts/katex_size2-regular.ttf\",\"type\":\"js\"},{\"id\":\"5a43a0c7-c70c-4171-817a-618163989c6c\",\"plugin\":\"org.ekstep.questionunit\",\"ver\":\"1.0\",\"src\":\"/content-plugins/org.ekstep.questionunit-1.0/renderer/libs/katex/fonts/katex_size3-regular.ttf\",\"type\":\"js\"},{\"id\":\"4d319956-1ca2-4190-a44e-119decded87a\",\"plugin\":\"org.ekstep.questionunit\",\"ver\":\"1.0\",\"src\":\"/content-plugins/org.ekstep.questionunit-1.0/renderer/libs/katex/fonts/katex_size4-regular.ttf\",\"type\":\"js\"},{\"id\":\"org.ekstep.questionunit\",\"plugin\":\"org.ekstep.questionunit\",\"ver\":\"1.0\",\"src\":\"/content-plugins/org.ekstep.questionunit-1.0/renderer/plugin.js\",\"type\":\"plugin\"},{\"id\":\"org.ekstep.questionunit_manifest\",\"plugin\":\"org.ekstep.questionunit\",\"ver\":\"1.0\",\"src\":\"/content-plugins/org.ekstep.questionunit-1.0/manifest.json\",\"type\":\"json\"},{\"id\":\"045c6037-cdb9-4edd-86ce-573382e2467b\",\"plugin\":\"org.ekstep.questionunit.mcq\",\"ver\":\"1.1\",\"src\":\"/content-plugins/org.ekstep.questionunit.mcq-1.1/renderer/styles/style.css\",\"type\":\"css\"},{\"id\":\"1cbecbd2-9100-4121-819c-dca53a45ccc1\",\"plugin\":\"org.ekstep.questionunit.mcq\",\"ver\":\"1.1\",\"src\":\"/content-plugins/org.ekstep.questionunit.mcq-1.1/renderer/styles/horizontal_and_vertical.css\",\"type\":\"css\"},{\"id\":\"5c404c80-9663-4199-9813-396718696be0\",\"plugin\":\"org.ekstep.questionunit.mcq\",\"ver\":\"1.1\",\"src\":\"/content-plugins/org.ekstep.questionunit.mcq-1.1/renderer/template/mcq-layouts.js\",\"type\":\"js\"},{\"id\":\"38325ad7-3ed8-4429-820c-181556dea753\",\"plugin\":\"org.ekstep.questionunit.mcq\",\"ver\":\"1.1\",\"src\":\"/content-plugins/org.ekstep.questionunit.mcq-1.1/renderer/template/template_controller.js\",\"type\":\"js\"},{\"id\":\"org.ekstep.questionunit.mcq\",\"plugin\":\"org.ekstep.questionunit.mcq\",\"ver\":\"1.1\",\"src\":\"/content-plugins/org.ekstep.questionunit.mcq-1.1/renderer/plugin.js\",\"type\":\"plugin\"},{\"id\":\"org.ekstep.questionunit.mcq_manifest\",\"plugin\":\"org.ekstep.questionunit.mcq\",\"ver\":\"1.1\",\"src\":\"/content-plugins/org.ekstep.questionunit.mcq-1.1/manifest.json\",\"type\":\"json\"},{\"id\":\"4874698a-760c-41c4-a906-8896a27b6314\",\"plugin\":\"org.ekstep.keyboard\",\"ver\":\"1.0\",\"src\":\"/content-plugins/org.ekstep.keyboard-1.0/renderer/keyboard.js\",\"type\":\"js\"},{\"id\":\"b1e2b47b-156c-40c8-916c-b90be6311e0a\",\"plugin\":\"org.ekstep.keyboard\",\"ver\":\"1.0\",\"src\":\"/content-plugins/org.ekstep.keyboard-1.0/renderer/style/style.css\",\"type\":\"css\"},{\"id\":\"org.ekstep.keyboard\",\"plugin\":\"org.ekstep.keyboard\",\"ver\":\"1.0\",\"src\":\"/content-plugins/org.ekstep.keyboard-1.0/renderer/plugin.js\",\"type\":\"plugin\"},{\"id\":\"org.ekstep.keyboard_manifest\",\"plugin\":\"org.ekstep.keyboard\",\"ver\":\"1.0\",\"src\":\"/content-plugins/org.ekstep.keyboard-1.0/manifest.json\",\"type\":\"json\"},{\"id\":\"86404d80-90a8-42a0-a880-ca17e13caddd\",\"plugin\":\"org.ekstep.questionunit.ftb\",\"ver\":\"1.0\",\"src\":\"/content-plugins/org.ekstep.questionunit.ftb-1.0/renderer/styles/style.css\",\"type\":\"css\"},{\"id\":\"dad5a09e-6207-4803-b051-76b334d456e7\",\"plugin\":\"org.ekstep.questionunit.ftb\",\"ver\":\"1.0\",\"src\":\"/content-plugins/org.ekstep.questionunit.ftb-1.0/renderer/ftbcontroller.js\",\"type\":\"js\"},{\"id\":\"org.ekstep.questionunit.ftb\",\"plugin\":\"org.ekstep.questionunit.ftb\",\"ver\":\"1.0\",\"src\":\"/content-plugins/org.ekstep.questionunit.ftb-1.0/renderer/plugin.js\",\"type\":\"plugin\"},{\"id\":\"org.ekstep.questionunit.ftb_manifest\",\"plugin\":\"org.ekstep.questionunit.ftb\",\"ver\":\"1.0\",\"src\":\"/content-plugins/org.ekstep.questionunit.ftb-1.0/manifest.json\",\"type\":\"json\"},{\"id\":\"org.ekstep.questionset.quiz\",\"plugin\":\"org.ekstep.questionset.quiz\",\"ver\":\"1.0\",\"src\":\"/content-plugins/org.ekstep.questionset.quiz-1.0/renderer/plugin.js\",\"type\":\"plugin\"},{\"id\":\"org.ekstep.questionset.quiz_manifest\",\"plugin\":\"org.ekstep.questionset.quiz\",\"ver\":\"1.0\",\"src\":\"/content-plugins/org.ekstep.questionset.quiz-1.0/manifest.json\",\"type\":\"json\"},{\"id\":\"org.ekstep.iterator\",\"plugin\":\"org.ekstep.iterator\",\"ver\":\"1.0\",\"src\":\"/content-plugins/org.ekstep.iterator-1.0/renderer/plugin.js\",\"type\":\"plugin\"},{\"id\":\"org.ekstep.iterator_manifest\",\"plugin\":\"org.ekstep.iterator\",\"ver\":\"1.0\",\"src\":\"/content-plugins/org.ekstep.iterator-1.0/manifest.json\",\"type\":\"json\"},{\"id\":\"ba456c6b-d835-41d2-a08e-da01366e48d7\",\"plugin\":\"org.ekstep.questionset\",\"ver\":\"1.0\",\"src\":\"/content-plugins/org.ekstep.questionset-1.0/renderer/utils/telemetry_logger.js\",\"type\":\"js\"},{\"id\":\"0c58e6a3-8dcc-48c2-8a18-0a1e1c35a910\",\"plugin\":\"org.ekstep.questionset\",\"ver\":\"1.0\",\"src\":\"/content-plugins/org.ekstep.questionset-1.0/renderer/utils/html_audio_plugin.js\",\"type\":\"js\"},{\"id\":\"7caada3b-5c18-49a8-a204-c23cd55d975c\",\"plugin\":\"org.ekstep.questionset\",\"ver\":\"1.0\",\"src\":\"/content-plugins/org.ekstep.questionset-1.0/renderer/utils/qs_feedback_popup.js\",\"type\":\"js\"},{\"id\":\"org.ekstep.questionset\",\"plugin\":\"org.ekstep.questionset\",\"ver\":\"1.0\",\"src\":\"/content-plugins/org.ekstep.questionset-1.0/renderer/plugin.js\",\"type\":\"plugin\"},{\"id\":\"org.ekstep.questionset_manifest\",\"plugin\":\"org.ekstep.questionset\",\"ver\":\"1.0\",\"src\":\"/content-plugins/org.ekstep.questionset-1.0/manifest.json\",\"type\":\"json\"},{\"id\":\"QuizImage\",\"src\":\"/content-plugins/org.ekstep.questionset-1.0/editor/assets/quizimage.png\",\"assetId\":\"QuizImage\",\"type\":\"image\",\"preload\":true},{\"id\":\"audioIcon\",\"src\":\"/content-plugins/org.ekstep.questionunit.mcq-1.0/renderer/assets/audio-icon.png\",\"assetId\":\"audioIcon\",\"type\":\"image\",\"preload\":true},{\"id\":\"zoomIcon\",\"src\":\"/content-plugins/org.ekstep.questionunit.mcq-1.0/renderer/assets/expand-icon.png\",\"assetId\":\"zoomIcon\",\"type\":\"image\",\"preload\":true},{\"id\":\"org.ekstep.keyboard.eras_icon\",\"src\":\"/content-plugins/org.ekstep.keyboard-1.0/renderer/assets/eras_icon.png\",\"assetId\":\"org.ekstep.keyboard.eras_icon\",\"type\":\"image\",\"preload\":true},{\"id\":\"org.ekstep.keyboard.language_icon\",\"src\":\"/content-plugins/org.ekstep.keyboard-1.0/renderer/assets/language_icon.png\",\"assetId\":\"org.ekstep.keyboard.language_icon\",\"type\":\"image\",\"preload\":true},{\"id\":\"org.ekstep.keyboard.hide_keyboard\",\"src\":\"/content-plugins/org.ekstep.keyboard-1.0/renderer/assets/keyboard.svg\",\"assetId\":\"org.ekstep.keyboard.hide_keyboard\",\"type\":\"image\",\"preload\":true}]},\"plugin-manifest\":{\"plugin\":[{\"id\":\"org.ekstep.navigation\",\"ver\":\"1.0\",\"type\":\"plugin\",\"depends\":\"\"},{\"id\":\"org.ekstep.questionunit\",\"ver\":\"1.0\",\"type\":\"plugin\",\"depends\":\"\"},{\"id\":\"org.ekstep.questionunit.mcq\",\"ver\":\"1.1\",\"type\":\"plugin\",\"depends\":\"org.ekstep.questionunit\"},{\"id\":\"org.ekstep.keyboard\",\"ver\":\"1.0\",\"type\":\"plugin\",\"depends\":\"\"},{\"id\":\"org.ekstep.questionunit.ftb\",\"ver\":\"1.0\",\"type\":\"plugin\",\"depends\":\"org.ekstep.questionunit,org.ekstep.keyboard\"},{\"id\":\"org.ekstep.questionset.quiz\",\"ver\":\"1.0\",\"type\":\"plugin\",\"depends\":\"\"},{\"id\":\"org.ekstep.iterator\",\"ver\":\"1.0\",\"type\":\"plugin\",\"depends\":\"\"},{\"id\":\"org.ekstep.questionset\",\"ver\":\"1.0\",\"type\":\"plugin\",\"depends\":\"org.ekstep.questionset.quiz,org.ekstep.iterator\"}]},\"compatibilityVersion\":2}}","languageCode":"en"}}}