{"id":"ekstep.content.find","ver":"3.0","ts":"2018-11-08T15:20:20ZZ","params":{"resmsgid":"56bf26ce-0948-4085-b250-269673d5797b","msgid":null,"err":null,"status":"successful","errmsg":null},"responseCode":"OK","result":{"content":{"identifier":"do_21257271319615078418446","body":"{\"theme\":{\"id\":\"theme\",\"version\":\"1.0\",\"startStage\":\"3d778123-8603-4d11-9510-0c72ba23b0aa\",\"stage\":[{\"x\":0,\"y\":0,\"w\":100,\"h\":100,\"id\":\"3d778123-8603-4d11-9510-0c72ba23b0aa\",\"rotate\":null,\"config\":{\"__cdata\":\"{\\\"opacity\\\":100,\\\"strokeWidth\\\":1,\\\"stroke\\\":\\\"rgba(255, 255, 255, 0)\\\",\\\"autoplay\\\":false,\\\"visible\\\":true,\\\"color\\\":\\\"#FFFFFF\\\",\\\"genieControls\\\":true,\\\"instructions\\\":\\\"\\\"}\"},\"param\":[{\"name\":\"next\",\"value\":\"1ba9ec83-d3bc-44c0-9c88-3c44407574b0\"}],\"manifest\":{\"media\":[]},\"org.ekstep.funtoot.multiplicationhorizontal\":[{\"w\":100,\"h\":100,\"x\":0,\"y\":0,\"rotate\":null,\"id\":\"dd4c7cea-26a2-45bc-88d1-7e0706b6b7ae\",\"data\":{\"__cdata\":\"{\\\"total_items\\\":3,\\\"item_sets\\\":[{\\\"id\\\":\\\"set1\\\",\\\"count\\\":3}],\\\"items\\\":{\\\"set1\\\":[{\\\"langid\\\":\\\"en\\\",\\\"identifier\\\":\\\"org.ekstep.funtoot.multiplicationhorizontal-g1-l0-sl1-q0-rand8689789438698514\\\",\\\"language\\\":[\\\"English\\\"],\\\"qid\\\":\\\"org.ekstep.funtoot.multiplicationhorizontal-g1-l0-sl1\\\",\\\"subject\\\":\\\"LMA\\\",\\\"grade\\\":\\\"1\\\",\\\"gradeLevel\\\":[\\\"Grade 1\\\"],\\\"bloomsTaxonomyLevel\\\":\\\"R\\\",\\\"level\\\":0,\\\"sublevel\\\":1,\\\"qindex\\\":\\\"\\\",\\\"qlevel\\\":\\\"EASY\\\",\\\"type\\\":\\\"ftb\\\",\\\"template_id\\\":\\\"\\\",\\\"template\\\":\\\"multiplicationhorizontal\\\",\\\"title\\\":\\\"Multiplication\\\",\\\"question_audio\\\":\\\"\\\",\\\"question_image\\\":\\\"\\\",\\\"model\\\":{\\\"numbers\\\":\\\"$nums\\\",\\\"numericLangId\\\":\\\"en\\\",\\\"langId\\\":\\\"en\\\",\\\"numberType\\\":\\\"\\\",\\\"hintMsg\\\":\\\"HINT_1\\\",\\\"question\\\":\\\"QTEXT\\\",\\\"variables\\\":{\\\"$x\\\":\\\"random(1 , 20)\\\",\\\"$y\\\":\\\"1\\\",\\\"$nums\\\":\\\"[toNumber($x) , toNumber($y)]\\\"}},\\\"concepts\\\":{\\\"identifier\\\":\\\"C6\\\",\\\"name\\\":\\\"Counting\\\"}},{\\\"langid\\\":\\\"en\\\",\\\"identifier\\\":\\\"org.ekstep.funtoot.multiplicationhorizontal-g1-l0-sl1-q1-rand7119315896500833\\\",\\\"language\\\":[\\\"English\\\"],\\\"qid\\\":\\\"org.ekstep.funtoot.multiplicationhorizontal-g1-l0-sl1\\\",\\\"subject\\\":\\\"LMA\\\",\\\"grade\\\":\\\"1\\\",\\\"gradeLevel\\\":[\\\"Grade 1\\\"],\\\"bloomsTaxonomyLevel\\\":\\\"R\\\",\\\"level\\\":0,\\\"sublevel\\\":1,\\\"qindex\\\":\\\"\\\",\\\"qlevel\\\":\\\"EASY\\\",\\\"type\\\":\\\"ftb\\\",\\\"template_id\\\":\\\"\\\",\\\"template\\\":\\\"multiplicationhorizontal\\\",\\\"title\\\":\\\"Multiplication\\\",\\\"question_audio\\\":\\\"\\\",\\\"question_image\\\":\\\"\\\",\\\"model\\\":{\\\"numbers\\\":\\\"$nums\\\",\\\"numericLangId\\\":\\\"en\\\",\\\"langId\\\":\\\"en\\\",\\\"numberType\\\":\\\"\\\",\\\"hintMsg\\\":\\\"HINT_1\\\",\\\"question\\\":\\\"QTEXT\\\",\\\"variables\\\":{\\\"$x\\\":\\\"random(1 , 20)\\\",\\\"$y\\\":\\\"1\\\",\\\"$nums\\\":\\\"[toNumber($x) , toNumber($y)]\\\"}},\\\"concepts\\\":{\\\"identifier\\\":\\\"C6\\\",\\\"name\\\":\\\"Counting\\\"}},{\\\"langid\\\":\\\"en\\\",\\\"identifier\\\":\\\"org.ekstep.funtoot.multiplicationhorizontal-g1-l0-sl1-q2-rand7780337230541963\\\",\\\"language\\\":[\\\"English\\\"],\\\"qid\\\":\\\"org.ekstep.funtoot.multiplicationhorizontal-g1-l0-sl1\\\",\\\"subject\\\":\\\"LMA\\\",\\\"grade\\\":\\\"1\\\",\\\"gradeLevel\\\":[\\\"Grade 1\\\"],\\\"bloomsTaxonomyLevel\\\":\\\"R\\\",\\\"level\\\":0,\\\"sublevel\\\":1,\\\"qindex\\\":\\\"\\\",\\\"qlevel\\\":\\\"EASY\\\",\\\"type\\\":\\\"ftb\\\",\\\"template_id\\\":\\\"\\\",\\\"template\\\":\\\"multiplicationhorizontal\\\",\\\"title\\\":\\\"Multiplication\\\",\\\"question_audio\\\":\\\"\\\",\\\"question_image\\\":\\\"\\\",\\\"model\\\":{\\\"numbers\\\":\\\"$nums\\\",\\\"numericLangId\\\":\\\"en\\\",\\\"langId\\\":\\\"en\\\",\\\"numberType\\\":\\\"\\\",\\\"hintMsg\\\":\\\"HINT_1\\\",\\\"question\\\":\\\"QTEXT\\\",\\\"variables\\\":{\\\"$x\\\":\\\"random(1 , 20)\\\",\\\"$y\\\":\\\"1\\\",\\\"$nums\\\":\\\"[toNumber($x) , toNumber($y)]\\\"}},\\\"concepts\\\":{\\\"identifier\\\":\\\"C6\\\",\\\"name\\\":\\\"Counting\\\"}}]},\\\"i18n\\\":{\\\"en\\\":{\\\"HINT\\\":\\\"Hint\\\",\\\"MICROHINT\\\":\\\"Micro Hint\\\",\\\"SOLUTION\\\":\\\"Solution\\\",\\\"HELP\\\":\\\"Help\\\",\\\"REDUCE_FRACTION\\\":\\\"Check the solution again. Remove the common factors in the fraction and reduce it to its lowest term.\\\",\\\"MIXED_FRACTION\\\":\\\"Convert the mixed fraction to an improper fraction.\\\",\\\"IMPROPER_FRACTION\\\":\\\"Convert the improper fraction to an mixed fraction.\\\",\\\"LIKEFRACTIONADDITION_NUMERATOR\\\":\\\"Add the numerator of the given fractions correctly.\\\",\\\"LIKEFRACTIONADDITION_DENOMINATOR\\\":\\\"For addition of like fractions the denominator remains the same.\\\",\\\"LIKEFRACTIONADDITION_FULL\\\":\\\"Check the addition of the numerator. The denominator remains the same.\\\",\\\"UNLIKEFRACTIONADDITION_NUMERATOR\\\":\\\"First convert the unlike fractions to like fractions. Then add the numerator of the like fractions.\\\",\\\"UNLIKEFRACTIONADDITION_DENOMINATOR\\\":\\\"First find the least common factor and convert the unlike fractions to like fractions. The denominator of the solution is the denominator of the like fractions.\\\",\\\"UNLIKEFRACTIONADDITION_FULL\\\":\\\"Convert the given fractions to like fractions and then carefully do the addition.\\\",\\\"LIKEFRACTIONSUBTRACTION_NUMERATOR\\\":\\\"Subtract the numerator of the given fractions correctly.\\\",\\\"LIKEFRACTIONSUBTRACTION_DENOMINATOR\\\":\\\"For subtraction of like fractions the denominator remains the same as that of the question.\\\",\\\"LIKEFRACTIONSUBTRACTION_FULL\\\":\\\"Subtract the numerator of the fractions. Denominator remains the same.\\\",\\\"UNLIKEFRACTIONSUBTRACTION_NUMERATOR\\\":\\\"First convert the unlike fractions to like fractions. Then subtract the numerator of the like fractions.\\\",\\\"UNLIKEFRACTIONSUBTRACTION_DENOMINATOR\\\":\\\"First find the least common factor and convert the unlike fractions to like fractions. The denominator of the solution is the denominator of the like fractions.\\\",\\\"UNLIKEFRACTIONSUBTRACTION_FULL\\\":\\\"Convert the given fractions to like fractions and then carefully do the subtraction.\\\",\\\"LIKEMIXEDFRACTIONADDITION_WHOLE\\\":\\\"Add the whole number part of both the fractions carefully. Check for the conversion of the improper fraction to proper fractions in the solution.\\\",\\\"LIKEMIXEDFRACTIONADDITION_NUMERATOR\\\":\\\"Add the numerator of the like fractions. If the fractional part is an improper fraction, then convert it to a proper fraction.\\\",\\\"LIKEMIXEDFRACTIONADDITION_DENOMINATOR\\\":\\\"The denominator of the solution fraction does not change for like fractions.\\\",\\\"LIKEMIXEDFRACTIONADDITION_FULL\\\":\\\"Convert the mixed fractions to improper fractions and then add them. The final solution should again be as a mixed fraction.\\\",\\\"LIKEMIXEDFRACTIONSUBTRACTION_WHOLE\\\":\\\"Subtract the whole number part of both the fractions carefully.\\\",\\\"LIKEMIXEDFRACTIONSUBTRACTION_NUMERATOR\\\":\\\"Subtract the numerator of the like fractions.\\\",\\\"LIKEMIXEDFRACTIONSUBTRACTION_DENOMINATOR\\\":\\\"The denominator of the solution fraction does not change for like fractions.\\\",\\\"LIKEMIXEDFRACTIONSUBTRACTION_FULL\\\":\\\"Convert the mixed fractions to improper fractions and then subtract them. The final solution should again be as a mixed fraction.\\\",\\\"WHOLEANDPROPERFRACTIONADDITION_WHOLE\\\":\\\"The integer added becomes the whole number part of the mixed fraction.\\\",\\\"WHOLEANDPROPERFRACTIONADDITION_NUMERATOR\\\":\\\"The numerator of the solution fraction remains the same.\\\",\\\"WHOLEANDPROPERFRACTIONADDITION_DENOMINATOR\\\":\\\"The denominator of the solution fraction remains the same as given in the problem.\\\",\\\"WHOLEANDPROPERFRACTIONADDITION_FULL\\\":\\\"The integer and the proper fraction when added becomes the mixed fraction.\\\",\\\"WHOLEANDPROPERFRACTIONSUBTRACTION_WHOLE\\\":\\\"Convert the whole number to an equivalent fraction. Then find the difference between the like fractions.\\\",\\\"WHOLEANDPROPERFRACTIONSUBTRACTION_NUMERATOR\\\":\\\"First find the least common factor and convert them to difference between like fractions. Then subtract the numerators carefully.\\\",\\\"WHOLEANDPROPERFRACTIONSUBTRACTION_DENOMINATOR\\\":\\\"The denominator of the solution fraction remains the same as given in the problem.\\\",\\\"WHOLEANDPROPERFRACTIONSUBTRACTION_FULL\\\":\\\"When the proper fraction is subtracted from the integer becomes the mixed fraction.\\\",\\\"WHOLEANDFRACTIONMULTIPLICATION_NUMERATOR\\\":\\\"Multiply the numerator and the whole number carefully.\\\",\\\"WHOLEANDFRACTIONMULTIPLICATION_DENOMINATOR\\\":\\\"Multiply the denominators of the fractions carefully.\\\",\\\"WHOLEANDFRACTIONMULTIPLICATION_FULL\\\":\\\"Multiply the integer with the fraction.\\\",\\\"FRACTIONMULTIPLICATION_NUMERATOR\\\":\\\"Multiply the numerators of the fractions carefully.\\\",\\\"FRACTIONMULTIPLICATION_DENOMINATOR\\\":\\\"Multiply the denominators of the fractions carefully.\\\",\\\"FRACTIONMULTIPLICATION_FULL\\\":\\\"Multiply the numerators and denominators of the fractions.\\\",\\\"FRACTIONDIVISION\\\":\\\"First find the reciprocal of the divisor. Then multiply the fraction with the reciprocal of the divisor to get the solution.\\\",\\\"QTEXT\\\":\\\"Multiply the given numbers.\\\",\\\"MH_SINGLEDIGIT\\\":\\\"Check the numbers to be multiplied and recall skip counting and carefully try again.\\\",\\\"MH_SAME\\\":\\\"Please understand that product of two equal numbers is calculated exactly like product of any numbers. Try again.\\\",\\\"MH_10\\\":\\\"When multiplying with 10 or powers of 10, carefully check the number of zeroes in the product and try again.\\\",\\\"MH_SUM\\\":\\\"Please identify the symbol carefully and find the product of the given numbers.\\\",\\\"NO_HINT\\\":\\\"There is no hint for this question\\\",\\\"QUESTION_TITLE\\\":\\\"Multiplication\\\",\\\"MH_END0\\\":\\\"Please do not leave the zeros  in the product while multiplying with powers of 10.\\\",\\\"MH_MISPLACE\\\":\\\"Please go through the process of multiplication and identify the exact position where numbers must be placed after multiplying each digit.\\\",\\\"MH_0\\\":\\\"Do not ignore the zero in the given numbers. Carefully do the multiplication.\\\",\\\"MH_1\\\":\\\"When we multiply by 1, we get the number itself. This is the special property of 1.\\\",\\\"NO_ANSWER\\\":\\\"Please answer\\\",\\\"MH_POWERSOF10\\\":\\\"Multiply the given numbers and add as many zeroes as needed. Place the decimal point correctly.\\\",\\\"HINT_4\\\":\\\"Carefully find the product of the numbers by recalling the skip counting sequences.\\\",\\\"HINT_5\\\":\\\"Carefully multiply by each term and calculate the product without missing the addition of carryover digits.\\\",\\\"MH_DEFAULT\\\":\\\"Please recall the process of multiplication. When multiplying with successive digits, we need to identify the correct place value to put the next set of multiplied numbers.\\\",\\\"HINT_6DECIMAL\\\":\\\"The decimal point moves one place to the right after multiplication.\\\",\\\"HINT_1\\\":\\\"Product of a number with 1 gives the number itself.\\\",\\\"HINT_2\\\":\\\"Carefully remember counting in 2's and try again.\\\",\\\"HINT_3\\\":\\\"Carefully remember counting in 3's and try again.\\\",\\\"MH_MISSED0\\\":\\\"The product with zero must be calculated to find the final answer. Please do not leave multiplying with zero.\\\",\\\"MH_DECIMAL\\\":\\\"Multiply the given numbers. Now place the decimal point in such a way that it will have as many decimal places as the original operands combined.\\\"}},\\\"selectedConfig\\\":{\\\"enableNextButton\\\":true,\\\"Grade\\\":\\\"1\\\",\\\"Level\\\":{\\\"Level\\\":0,\\\"LevelDesc\\\":\\\"Multiplication with single digit numbers\\\",\\\"$$hashKey\\\":\\\"object:3151\\\"},\\\"SubLevel\\\":{\\\"SubLevel\\\":1,\\\"SubLevelDesc\\\":\\\"Multiply by 1\\\",\\\"$$hashKey\\\":\\\"object:3152\\\"},\\\"itemData\\\":{\\\"Type\\\":\\\"Multiplication\\\",\\\"Grade\\\":1,\\\"Level\\\":0,\\\"LevelDesc\\\":\\\"Multiplication with single digit numbers\\\",\\\"SubLevel\\\":1,\\\"SubLevelDesc\\\":\\\"Multiply by 1\\\",\\\"Expression\\\":\\\"$x = random(1 , 20)\\\\n$y = 1\\\\n$nums = [toNumber($x) , toNumber($y)]\\\",\\\"BTLO\\\":\\\"R\\\",\\\"DifficultyLevel\\\":2,\\\"Description\\\":\\\"Tests the multiplication of numbers by 1.\\\",\\\"SubLevelDesc1\\\":\\\"Give numbers between 1 and 20 to be multiplied by 1.\\\",\\\"HintID\\\":\\\"HINT_1\\\",\\\"QuestionText\\\":\\\"QTEXT\\\",\\\"QID\\\":\\\"\\\",\\\"Subject\\\":\\\"LMA\\\",\\\"ConceptCode\\\":\\\"C271, C548\\\",\\\"ESDifficultyLevel\\\":\\\"Easy\\\"},\\\"QCount\\\":3,\\\"showImmediateFeedback\\\":true,\\\"areVariablesStatic\\\":false,\\\"areMicrohintsEnabled\\\":true,\\\"enableFeedback\\\":true,\\\"enableSolution\\\":true,\\\"enableHint\\\":true,\\\"retainAnswers\\\":true,\\\"maxNoOfAtt\\\":2,\\\"contentLocale\\\":\\\"en\\\",\\\"numeralLocale\\\":\\\"en\\\"}}\"},\"config\":{\"__cdata\":\"{\\\"title\\\":\\\"Multiplication\\\",\\\"count\\\":3,\\\"locales\\\":{\\\"contentLocale\\\":\\\"en\\\",\\\"numeralLocale\\\":\\\"en\\\"},\\\"selectedConfig\\\":{\\\"enableNextButton\\\":true,\\\"Grade\\\":\\\"1\\\",\\\"Level\\\":{\\\"Level\\\":0,\\\"LevelDesc\\\":\\\"Multiplication with single digit numbers\\\",\\\"$$hashKey\\\":\\\"object:3151\\\"},\\\"SubLevel\\\":{\\\"SubLevel\\\":1,\\\"SubLevelDesc\\\":\\\"Multiply by 1\\\",\\\"$$hashKey\\\":\\\"object:3152\\\"},\\\"itemData\\\":{\\\"Type\\\":\\\"Multiplication\\\",\\\"Grade\\\":1,\\\"Level\\\":0,\\\"LevelDesc\\\":\\\"Multiplication with single digit numbers\\\",\\\"SubLevel\\\":1,\\\"SubLevelDesc\\\":\\\"Multiply by 1\\\",\\\"Expression\\\":\\\"$x = random(1 , 20)\\\\n$y = 1\\\\n$nums = [toNumber($x) , toNumber($y)]\\\",\\\"BTLO\\\":\\\"R\\\",\\\"DifficultyLevel\\\":2,\\\"Description\\\":\\\"Tests the multiplication of numbers by 1.\\\",\\\"SubLevelDesc1\\\":\\\"Give numbers between 1 and 20 to be multiplied by 1.\\\",\\\"HintID\\\":\\\"HINT_1\\\",\\\"QuestionText\\\":\\\"QTEXT\\\",\\\"QID\\\":\\\"\\\",\\\"Subject\\\":\\\"LMA\\\",\\\"ConceptCode\\\":\\\"C271, C548\\\",\\\"ESDifficultyLevel\\\":\\\"Easy\\\"},\\\"QCount\\\":3,\\\"showImmediateFeedback\\\":true,\\\"areVariablesStatic\\\":false,\\\"areMicrohintsEnabled\\\":true,\\\"enableFeedback\\\":true,\\\"enableSolution\\\":true,\\\"enableHint\\\":true,\\\"retainAnswers\\\":true,\\\"maxNoOfAtt\\\":2,\\\"contentLocale\\\":\\\"en\\\",\\\"numeralLocale\\\":\\\"en\\\"},\\\"type\\\":\\\"items\\\",\\\"var\\\":\\\"item\\\"}\"}}]},{\"x\":0,\"y\":0,\"w\":100,\"h\":100,\"id\":\"1ba9ec83-d3bc-44c0-9c88-3c44407574b0\",\"rotate\":null,\"config\":{\"__cdata\":\"{\\\"opacity\\\":100,\\\"strokeWidth\\\":1,\\\"stroke\\\":\\\"rgba(255, 255, 255, 0)\\\",\\\"autoplay\\\":false,\\\"visible\\\":true,\\\"color\\\":\\\"#FFFFFF\\\",\\\"genieControls\\\":true,\\\"instructions\\\":\\\"\\\"}\"},\"param\":[{\"name\":\"previous\",\"value\":\"3d778123-8603-4d11-9510-0c72ba23b0aa\"},{\"name\":\"next\",\"value\":\"b15cc820-d453-4dad-b5dd-b9bc80ed9360\"}],\"manifest\":{\"media\":[]},\"org.ekstep.funtoot.multiplicationhorizontal\":[{\"w\":100,\"h\":100,\"x\":0,\"y\":0,\"rotate\":null,\"id\":\"2b839bb6-b40c-4d05-876e-06d875b626a5\",\"data\":{\"__cdata\":\"{\\\"total_items\\\":3,\\\"item_sets\\\":[{\\\"id\\\":\\\"set2\\\",\\\"count\\\":3}],\\\"items\\\":{\\\"set2\\\":[{\\\"langid\\\":\\\"en\\\",\\\"identifier\\\":\\\"org.ekstep.funtoot.multiplicationhorizontal-g1-l0-sl1-q0-rand6700558689010339\\\",\\\"language\\\":[\\\"English\\\"],\\\"qid\\\":\\\"org.ekstep.funtoot.multiplicationhorizontal-g1-l0-sl1\\\",\\\"subject\\\":\\\"LMA\\\",\\\"grade\\\":\\\"1\\\",\\\"gradeLevel\\\":[\\\"Grade 1\\\"],\\\"bloomsTaxonomyLevel\\\":\\\"R\\\",\\\"level\\\":0,\\\"sublevel\\\":1,\\\"qindex\\\":\\\"\\\",\\\"qlevel\\\":\\\"EASY\\\",\\\"type\\\":\\\"ftb\\\",\\\"template_id\\\":\\\"\\\",\\\"template\\\":\\\"multiplicationhorizontal\\\",\\\"title\\\":\\\"Multiplication\\\",\\\"question_audio\\\":\\\"\\\",\\\"question_image\\\":\\\"\\\",\\\"model\\\":{\\\"numbers\\\":\\\"$nums\\\",\\\"numericLangId\\\":\\\"en\\\",\\\"langId\\\":\\\"en\\\",\\\"numberType\\\":\\\"\\\",\\\"hintMsg\\\":\\\"HINT_1\\\",\\\"question\\\":\\\"QTEXT\\\",\\\"variables\\\":{\\\"$x\\\":\\\"random(1 , 20)\\\",\\\"$y\\\":\\\"1\\\",\\\"$nums\\\":\\\"[toNumber($x) , toNumber($y)]\\\"}},\\\"concepts\\\":{\\\"identifier\\\":\\\"C6\\\",\\\"name\\\":\\\"Counting\\\"}},{\\\"langid\\\":\\\"en\\\",\\\"identifier\\\":\\\"org.ekstep.funtoot.multiplicationhorizontal-g1-l0-sl1-q1-rand9294790586579171\\\",\\\"language\\\":[\\\"English\\\"],\\\"qid\\\":\\\"org.ekstep.funtoot.multiplicationhorizontal-g1-l0-sl1\\\",\\\"subject\\\":\\\"LMA\\\",\\\"grade\\\":\\\"1\\\",\\\"gradeLevel\\\":[\\\"Grade 1\\\"],\\\"bloomsTaxonomyLevel\\\":\\\"R\\\",\\\"level\\\":0,\\\"sublevel\\\":1,\\\"qindex\\\":\\\"\\\",\\\"qlevel\\\":\\\"EASY\\\",\\\"type\\\":\\\"ftb\\\",\\\"template_id\\\":\\\"\\\",\\\"template\\\":\\\"multiplicationhorizontal\\\",\\\"title\\\":\\\"Multiplication\\\",\\\"question_audio\\\":\\\"\\\",\\\"question_image\\\":\\\"\\\",\\\"model\\\":{\\\"numbers\\\":\\\"$nums\\\",\\\"numericLangId\\\":\\\"en\\\",\\\"langId\\\":\\\"en\\\",\\\"numberType\\\":\\\"\\\",\\\"hintMsg\\\":\\\"HINT_1\\\",\\\"question\\\":\\\"QTEXT\\\",\\\"variables\\\":{\\\"$x\\\":\\\"random(1 , 20)\\\",\\\"$y\\\":\\\"1\\\",\\\"$nums\\\":\\\"[toNumber($x) , toNumber($y)]\\\"}},\\\"concepts\\\":{\\\"identifier\\\":\\\"C6\\\",\\\"name\\\":\\\"Counting\\\"}},{\\\"langid\\\":\\\"en\\\",\\\"identifier\\\":\\\"org.ekstep.funtoot.multiplicationhorizontal-g1-l0-sl1-q2-rand9282795994164494\\\",\\\"language\\\":[\\\"English\\\"],\\\"qid\\\":\\\"org.ekstep.funtoot.multiplicationhorizontal-g1-l0-sl1\\\",\\\"subject\\\":\\\"LMA\\\",\\\"grade\\\":\\\"1\\\",\\\"gradeLevel\\\":[\\\"Grade 1\\\"],\\\"bloomsTaxonomyLevel\\\":\\\"R\\\",\\\"level\\\":0,\\\"sublevel\\\":1,\\\"qindex\\\":\\\"\\\",\\\"qlevel\\\":\\\"EASY\\\",\\\"type\\\":\\\"ftb\\\",\\\"template_id\\\":\\\"\\\",\\\"template\\\":\\\"multiplicationhorizontal\\\",\\\"title\\\":\\\"Multiplication\\\",\\\"question_audio\\\":\\\"\\\",\\\"question_image\\\":\\\"\\\",\\\"model\\\":{\\\"numbers\\\":\\\"$nums\\\",\\\"numericLangId\\\":\\\"en\\\",\\\"langId\\\":\\\"en\\\",\\\"numberType\\\":\\\"\\\",\\\"hintMsg\\\":\\\"HINT_1\\\",\\\"question\\\":\\\"QTEXT\\\",\\\"variables\\\":{\\\"$x\\\":\\\"random(1 , 20)\\\",\\\"$y\\\":\\\"1\\\",\\\"$nums\\\":\\\"[toNumber($x) , toNumber($y)]\\\"}},\\\"concepts\\\":{\\\"identifier\\\":\\\"C6\\\",\\\"name\\\":\\\"Counting\\\"}}]},\\\"i18n\\\":{\\\"en\\\":{\\\"HINT\\\":\\\"Hint\\\",\\\"MICROHINT\\\":\\\"Micro Hint\\\",\\\"SOLUTION\\\":\\\"Solution\\\",\\\"HELP\\\":\\\"Help\\\",\\\"REDUCE_FRACTION\\\":\\\"Check the solution again. Remove the common factors in the fraction and reduce it to its lowest term.\\\",\\\"MIXED_FRACTION\\\":\\\"Convert the mixed fraction to an improper fraction.\\\",\\\"IMPROPER_FRACTION\\\":\\\"Convert the improper fraction to an mixed fraction.\\\",\\\"LIKEFRACTIONADDITION_NUMERATOR\\\":\\\"Add the numerator of the given fractions correctly.\\\",\\\"LIKEFRACTIONADDITION_DENOMINATOR\\\":\\\"For addition of like fractions the denominator remains the same.\\\",\\\"LIKEFRACTIONADDITION_FULL\\\":\\\"Check the addition of the numerator. The denominator remains the same.\\\",\\\"UNLIKEFRACTIONADDITION_NUMERATOR\\\":\\\"First convert the unlike fractions to like fractions. Then add the numerator of the like fractions.\\\",\\\"UNLIKEFRACTIONADDITION_DENOMINATOR\\\":\\\"First find the least common factor and convert the unlike fractions to like fractions. The denominator of the solution is the denominator of the like fractions.\\\",\\\"UNLIKEFRACTIONADDITION_FULL\\\":\\\"Convert the given fractions to like fractions and then carefully do the addition.\\\",\\\"LIKEFRACTIONSUBTRACTION_NUMERATOR\\\":\\\"Subtract the numerator of the given fractions correctly.\\\",\\\"LIKEFRACTIONSUBTRACTION_DENOMINATOR\\\":\\\"For subtraction of like fractions the denominator remains the same as that of the question.\\\",\\\"LIKEFRACTIONSUBTRACTION_FULL\\\":\\\"Subtract the numerator of the fractions. Denominator remains the same.\\\",\\\"UNLIKEFRACTIONSUBTRACTION_NUMERATOR\\\":\\\"First convert the unlike fractions to like fractions. Then subtract the numerator of the like fractions.\\\",\\\"UNLIKEFRACTIONSUBTRACTION_DENOMINATOR\\\":\\\"First find the least common factor and convert the unlike fractions to like fractions. The denominator of the solution is the denominator of the like fractions.\\\",\\\"UNLIKEFRACTIONSUBTRACTION_FULL\\\":\\\"Convert the given fractions to like fractions and then carefully do the subtraction.\\\",\\\"LIKEMIXEDFRACTIONADDITION_WHOLE\\\":\\\"Add the whole number part of both the fractions carefully. Check for the conversion of the improper fraction to proper fractions in the solution.\\\",\\\"LIKEMIXEDFRACTIONADDITION_NUMERATOR\\\":\\\"Add the numerator of the like fractions. If the fractional part is an improper fraction, then convert it to a proper fraction.\\\",\\\"LIKEMIXEDFRACTIONADDITION_DENOMINATOR\\\":\\\"The denominator of the solution fraction does not change for like fractions.\\\",\\\"LIKEMIXEDFRACTIONADDITION_FULL\\\":\\\"Convert the mixed fractions to improper fractions and then add them. The final solution should again be as a mixed fraction.\\\",\\\"LIKEMIXEDFRACTIONSUBTRACTION_WHOLE\\\":\\\"Subtract the whole number part of both the fractions carefully.\\\",\\\"LIKEMIXEDFRACTIONSUBTRACTION_NUMERATOR\\\":\\\"Subtract the numerator of the like fractions.\\\",\\\"LIKEMIXEDFRACTIONSUBTRACTION_DENOMINATOR\\\":\\\"The denominator of the solution fraction does not change for like fractions.\\\",\\\"LIKEMIXEDFRACTIONSUBTRACTION_FULL\\\":\\\"Convert the mixed fractions to improper fractions and then subtract them. The final solution should again be as a mixed fraction.\\\",\\\"WHOLEANDPROPERFRACTIONADDITION_WHOLE\\\":\\\"The integer added becomes the whole number part of the mixed fraction.\\\",\\\"WHOLEANDPROPERFRACTIONADDITION_NUMERATOR\\\":\\\"The numerator of the solution fraction remains the same.\\\",\\\"WHOLEANDPROPERFRACTIONADDITION_DENOMINATOR\\\":\\\"The denominator of the solution fraction remains the same as given in the problem.\\\",\\\"WHOLEANDPROPERFRACTIONADDITION_FULL\\\":\\\"The integer and the proper fraction when added becomes the mixed fraction.\\\",\\\"WHOLEANDPROPERFRACTIONSUBTRACTION_WHOLE\\\":\\\"Convert the whole number to an equivalent fraction. Then find the difference between the like fractions.\\\",\\\"WHOLEANDPROPERFRACTIONSUBTRACTION_NUMERATOR\\\":\\\"First find the least common factor and convert them to difference between like fractions. Then subtract the numerators carefully.\\\",\\\"WHOLEANDPROPERFRACTIONSUBTRACTION_DENOMINATOR\\\":\\\"The denominator of the solution fraction remains the same as given in the problem.\\\",\\\"WHOLEANDPROPERFRACTIONSUBTRACTION_FULL\\\":\\\"When the proper fraction is subtracted from the integer becomes the mixed fraction.\\\",\\\"WHOLEANDFRACTIONMULTIPLICATION_NUMERATOR\\\":\\\"Multiply the numerator and the whole number carefully.\\\",\\\"WHOLEANDFRACTIONMULTIPLICATION_DENOMINATOR\\\":\\\"Multiply the denominators of the fractions carefully.\\\",\\\"WHOLEANDFRACTIONMULTIPLICATION_FULL\\\":\\\"Multiply the integer with the fraction.\\\",\\\"FRACTIONMULTIPLICATION_NUMERATOR\\\":\\\"Multiply the numerators of the fractions carefully.\\\",\\\"FRACTIONMULTIPLICATION_DENOMINATOR\\\":\\\"Multiply the denominators of the fractions carefully.\\\",\\\"FRACTIONMULTIPLICATION_FULL\\\":\\\"Multiply the numerators and denominators of the fractions.\\\",\\\"FRACTIONDIVISION\\\":\\\"First find the reciprocal of the divisor. Then multiply the fraction with the reciprocal of the divisor to get the solution.\\\",\\\"QTEXT\\\":\\\"Multiply the given numbers.\\\",\\\"MH_SINGLEDIGIT\\\":\\\"Check the numbers to be multiplied and recall skip counting and carefully try again.\\\",\\\"MH_SAME\\\":\\\"Please understand that product of two equal numbers is calculated exactly like product of any numbers. Try again.\\\",\\\"MH_10\\\":\\\"When multiplying with 10 or powers of 10, carefully check the number of zeroes in the product and try again.\\\",\\\"MH_SUM\\\":\\\"Please identify the symbol carefully and find the product of the given numbers.\\\",\\\"NO_HINT\\\":\\\"There is no hint for this question\\\",\\\"QUESTION_TITLE\\\":\\\"Multiplication\\\",\\\"MH_END0\\\":\\\"Please do not leave the zeros  in the product while multiplying with powers of 10.\\\",\\\"MH_MISPLACE\\\":\\\"Please go through the process of multiplication and identify the exact position where numbers must be placed after multiplying each digit.\\\",\\\"MH_0\\\":\\\"Do not ignore the zero in the given numbers. Carefully do the multiplication.\\\",\\\"MH_1\\\":\\\"When we multiply by 1, we get the number itself. This is the special property of 1.\\\",\\\"NO_ANSWER\\\":\\\"Please answer\\\",\\\"MH_POWERSOF10\\\":\\\"Multiply the given numbers and add as many zeroes as needed. Place the decimal point correctly.\\\",\\\"HINT_4\\\":\\\"Carefully find the product of the numbers by recalling the skip counting sequences.\\\",\\\"HINT_5\\\":\\\"Carefully multiply by each term and calculate the product without missing the addition of carryover digits.\\\",\\\"MH_DEFAULT\\\":\\\"Please recall the process of multiplication. When multiplying with successive digits, we need to identify the correct place value to put the next set of multiplied numbers.\\\",\\\"HINT_6DECIMAL\\\":\\\"The decimal point moves one place to the right after multiplication.\\\",\\\"HINT_1\\\":\\\"Product of a number with 1 gives the number itself.\\\",\\\"HINT_2\\\":\\\"Carefully remember counting in 2's and try again.\\\",\\\"HINT_3\\\":\\\"Carefully remember counting in 3's and try again.\\\",\\\"MH_MISSED0\\\":\\\"The product with zero must be calculated to find the final answer. Please do not leave multiplying with zero.\\\",\\\"MH_DECIMAL\\\":\\\"Multiply the given numbers. Now place the decimal point in such a way that it will have as many decimal places as the original operands combined.\\\"}},\\\"selectedConfig\\\":{\\\"enableNextButton\\\":true,\\\"Grade\\\":\\\"1\\\",\\\"Level\\\":{\\\"Level\\\":0,\\\"LevelDesc\\\":\\\"Multiplication with single digit numbers\\\",\\\"$$hashKey\\\":\\\"object:9262\\\"},\\\"SubLevel\\\":{\\\"SubLevel\\\":1,\\\"SubLevelDesc\\\":\\\"Multiply by 1\\\",\\\"$$hashKey\\\":\\\"object:9263\\\"},\\\"itemData\\\":{\\\"Type\\\":\\\"Multiplication\\\",\\\"Grade\\\":1,\\\"Level\\\":0,\\\"LevelDesc\\\":\\\"Multiplication with single digit numbers\\\",\\\"SubLevel\\\":1,\\\"SubLevelDesc\\\":\\\"Multiply by 1\\\",\\\"Expression\\\":\\\"$x = random(1 , 20)\\\\n$y = 1\\\\n$nums = [toNumber($x) , toNumber($y)]\\\",\\\"BTLO\\\":\\\"R\\\",\\\"DifficultyLevel\\\":2,\\\"Description\\\":\\\"Tests the multiplication of numbers by 1.\\\",\\\"SubLevelDesc1\\\":\\\"Give numbers between 1 and 20 to be multiplied by 1.\\\",\\\"HintID\\\":\\\"HINT_1\\\",\\\"QuestionText\\\":\\\"QTEXT\\\",\\\"QID\\\":\\\"\\\",\\\"Subject\\\":\\\"LMA\\\",\\\"ConceptCode\\\":\\\"C271, C548\\\",\\\"ESDifficultyLevel\\\":\\\"Easy\\\"},\\\"QCount\\\":3,\\\"showImmediateFeedback\\\":true,\\\"areVariablesStatic\\\":false,\\\"areMicrohintsEnabled\\\":true,\\\"enableFeedback\\\":true,\\\"enableSolution\\\":true,\\\"enableHint\\\":true,\\\"retainAnswers\\\":true,\\\"maxNoOfAtt\\\":2,\\\"contentLocale\\\":\\\"en\\\",\\\"numeralLocale\\\":\\\"en\\\"}}\"},\"config\":{\"__cdata\":\"{\\\"title\\\":\\\"Multiplication\\\",\\\"count\\\":3,\\\"locales\\\":{\\\"contentLocale\\\":\\\"en\\\",\\\"numeralLocale\\\":\\\"en\\\"},\\\"selectedConfig\\\":{\\\"enableNextButton\\\":true,\\\"Grade\\\":\\\"1\\\",\\\"Level\\\":{\\\"Level\\\":0,\\\"LevelDesc\\\":\\\"Multiplication with single digit numbers\\\",\\\"$$hashKey\\\":\\\"object:9262\\\"},\\\"SubLevel\\\":{\\\"SubLevel\\\":1,\\\"SubLevelDesc\\\":\\\"Multiply by 1\\\",\\\"$$hashKey\\\":\\\"object:9263\\\"},\\\"itemData\\\":{\\\"Type\\\":\\\"Multiplication\\\",\\\"Grade\\\":1,\\\"Level\\\":0,\\\"LevelDesc\\\":\\\"Multiplication with single digit numbers\\\",\\\"SubLevel\\\":1,\\\"SubLevelDesc\\\":\\\"Multiply by 1\\\",\\\"Expression\\\":\\\"$x = random(1 , 20)\\\\n$y = 1\\\\n$nums = [toNumber($x) , toNumber($y)]\\\",\\\"BTLO\\\":\\\"R\\\",\\\"DifficultyLevel\\\":2,\\\"Description\\\":\\\"Tests the multiplication of numbers by 1.\\\",\\\"SubLevelDesc1\\\":\\\"Give numbers between 1 and 20 to be multiplied by 1.\\\",\\\"HintID\\\":\\\"HINT_1\\\",\\\"QuestionText\\\":\\\"QTEXT\\\",\\\"QID\\\":\\\"\\\",\\\"Subject\\\":\\\"LMA\\\",\\\"ConceptCode\\\":\\\"C271, C548\\\",\\\"ESDifficultyLevel\\\":\\\"Easy\\\"},\\\"QCount\\\":3,\\\"showImmediateFeedback\\\":true,\\\"areVariablesStatic\\\":false,\\\"areMicrohintsEnabled\\\":true,\\\"enableFeedback\\\":true,\\\"enableSolution\\\":true,\\\"enableHint\\\":true,\\\"retainAnswers\\\":true,\\\"maxNoOfAtt\\\":2,\\\"contentLocale\\\":\\\"en\\\",\\\"numeralLocale\\\":\\\"en\\\"},\\\"type\\\":\\\"items\\\",\\\"var\\\":\\\"item\\\"}\"}}]},{\"x\":0,\"y\":0,\"w\":100,\"h\":100,\"id\":\"b15cc820-d453-4dad-b5dd-b9bc80ed9360\",\"rotate\":null,\"config\":{\"__cdata\":\"{\\\"opacity\\\":100,\\\"strokeWidth\\\":1,\\\"stroke\\\":\\\"rgba(255, 255, 255, 0)\\\",\\\"autoplay\\\":false,\\\"visible\\\":true,\\\"color\\\":\\\"#FFFFFF\\\",\\\"genieControls\\\":true,\\\"instructions\\\":\\\"\\\"}\"},\"param\":[{\"name\":\"previous\",\"value\":\"1ba9ec83-d3bc-44c0-9c88-3c44407574b0\"}],\"manifest\":{\"media\":[]},\"org.ekstep.funtoot.multiplicationhorizontal\":[{\"w\":100,\"h\":100,\"x\":0,\"y\":0,\"rotate\":null,\"id\":\"594dea57-ab23-4908-9711-e97781a66d38\",\"data\":{\"__cdata\":\"{\\\"total_items\\\":10,\\\"item_sets\\\":[{\\\"id\\\":\\\"set2\\\",\\\"count\\\":\\\"10\\\"}],\\\"items\\\":{\\\"set2\\\":[{\\\"langid\\\":\\\"en\\\",\\\"identifier\\\":\\\"org.ekstep.funtoot.multiplicationhorizontal-g1-l0-sl1-q0-rand1942089287796145\\\",\\\"language\\\":[\\\"English\\\"],\\\"qid\\\":\\\"org.ekstep.funtoot.multiplicationhorizontal-g1-l0-sl1\\\",\\\"subject\\\":\\\"LMA\\\",\\\"grade\\\":\\\"1\\\",\\\"gradeLevel\\\":[\\\"Grade 1\\\"],\\\"bloomsTaxonomyLevel\\\":\\\"R\\\",\\\"level\\\":0,\\\"sublevel\\\":1,\\\"qindex\\\":\\\"\\\",\\\"qlevel\\\":\\\"EASY\\\",\\\"type\\\":\\\"ftb\\\",\\\"template_id\\\":\\\"\\\",\\\"template\\\":\\\"multiplicationhorizontal\\\",\\\"title\\\":\\\"Multiplication\\\",\\\"question_audio\\\":\\\"\\\",\\\"question_image\\\":\\\"\\\",\\\"model\\\":{\\\"numbers\\\":\\\"$nums\\\",\\\"numericLangId\\\":\\\"en\\\",\\\"langId\\\":\\\"en\\\",\\\"numberType\\\":\\\"\\\",\\\"hintMsg\\\":\\\"HINT_1\\\",\\\"question\\\":\\\"QTEXT\\\",\\\"variables\\\":{\\\"$x\\\":\\\"random(1 , 20)\\\",\\\"$y\\\":\\\"1\\\",\\\"$nums\\\":\\\"[toNumber($x) , toNumber($y)]\\\"}},\\\"concepts\\\":{\\\"identifier\\\":\\\"C6\\\",\\\"name\\\":\\\"Counting\\\"}},{\\\"langid\\\":\\\"en\\\",\\\"identifier\\\":\\\"org.ekstep.funtoot.multiplicationhorizontal-g1-l0-sl1-q1-rand6209572814318511\\\",\\\"language\\\":[\\\"English\\\"],\\\"qid\\\":\\\"org.ekstep.funtoot.multiplicationhorizontal-g1-l0-sl1\\\",\\\"subject\\\":\\\"LMA\\\",\\\"grade\\\":\\\"1\\\",\\\"gradeLevel\\\":[\\\"Grade 1\\\"],\\\"bloomsTaxonomyLevel\\\":\\\"R\\\",\\\"level\\\":0,\\\"sublevel\\\":1,\\\"qindex\\\":\\\"\\\",\\\"qlevel\\\":\\\"EASY\\\",\\\"type\\\":\\\"ftb\\\",\\\"template_id\\\":\\\"\\\",\\\"template\\\":\\\"multiplicationhorizontal\\\",\\\"title\\\":\\\"Multiplication\\\",\\\"question_audio\\\":\\\"\\\",\\\"question_image\\\":\\\"\\\",\\\"model\\\":{\\\"numbers\\\":\\\"$nums\\\",\\\"numericLangId\\\":\\\"en\\\",\\\"langId\\\":\\\"en\\\",\\\"numberType\\\":\\\"\\\",\\\"hintMsg\\\":\\\"HINT_1\\\",\\\"question\\\":\\\"QTEXT\\\",\\\"variables\\\":{\\\"$x\\\":\\\"random(1 , 20)\\\",\\\"$y\\\":\\\"1\\\",\\\"$nums\\\":\\\"[toNumber($x) , toNumber($y)]\\\"}},\\\"concepts\\\":{\\\"identifier\\\":\\\"C6\\\",\\\"name\\\":\\\"Counting\\\"}},{\\\"langid\\\":\\\"en\\\",\\\"identifier\\\":\\\"org.ekstep.funtoot.multiplicationhorizontal-g1-l0-sl1-q2-rand917835412018039\\\",\\\"language\\\":[\\\"English\\\"],\\\"qid\\\":\\\"org.ekstep.funtoot.multiplicationhorizontal-g1-l0-sl1\\\",\\\"subject\\\":\\\"LMA\\\",\\\"grade\\\":\\\"1\\\",\\\"gradeLevel\\\":[\\\"Grade 1\\\"],\\\"bloomsTaxonomyLevel\\\":\\\"R\\\",\\\"level\\\":0,\\\"sublevel\\\":1,\\\"qindex\\\":\\\"\\\",\\\"qlevel\\\":\\\"EASY\\\",\\\"type\\\":\\\"ftb\\\",\\\"template_id\\\":\\\"\\\",\\\"template\\\":\\\"multiplicationhorizontal\\\",\\\"title\\\":\\\"Multiplication\\\",\\\"question_audio\\\":\\\"\\\",\\\"question_image\\\":\\\"\\\",\\\"model\\\":{\\\"numbers\\\":\\\"$nums\\\",\\\"numericLangId\\\":\\\"en\\\",\\\"langId\\\":\\\"en\\\",\\\"numberType\\\":\\\"\\\",\\\"hintMsg\\\":\\\"HINT_1\\\",\\\"question\\\":\\\"QTEXT\\\",\\\"variables\\\":{\\\"$x\\\":\\\"random(1 , 20)\\\",\\\"$y\\\":\\\"1\\\",\\\"$nums\\\":\\\"[toNumber($x) , toNumber($y)]\\\"}},\\\"concepts\\\":{\\\"identifier\\\":\\\"C6\\\",\\\"name\\\":\\\"Counting\\\"}},{\\\"langid\\\":\\\"en\\\",\\\"identifier\\\":\\\"org.ekstep.funtoot.multiplicationhorizontal-g1-l0-sl1-q3-rand23206733578100813\\\",\\\"language\\\":[\\\"English\\\"],\\\"qid\\\":\\\"org.ekstep.funtoot.multiplicationhorizontal-g1-l0-sl1\\\",\\\"subject\\\":\\\"LMA\\\",\\\"grade\\\":\\\"1\\\",\\\"gradeLevel\\\":[\\\"Grade 1\\\"],\\\"bloomsTaxonomyLevel\\\":\\\"R\\\",\\\"level\\\":0,\\\"sublevel\\\":1,\\\"qindex\\\":\\\"\\\",\\\"qlevel\\\":\\\"EASY\\\",\\\"type\\\":\\\"ftb\\\",\\\"template_id\\\":\\\"\\\",\\\"template\\\":\\\"multiplicationhorizontal\\\",\\\"title\\\":\\\"Multiplication\\\",\\\"question_audio\\\":\\\"\\\",\\\"question_image\\\":\\\"\\\",\\\"model\\\":{\\\"numbers\\\":\\\"$nums\\\",\\\"numericLangId\\\":\\\"en\\\",\\\"langId\\\":\\\"en\\\",\\\"numberType\\\":\\\"\\\",\\\"hintMsg\\\":\\\"HINT_1\\\",\\\"question\\\":\\\"QTEXT\\\",\\\"variables\\\":{\\\"$x\\\":\\\"random(1 , 20)\\\",\\\"$y\\\":\\\"1\\\",\\\"$nums\\\":\\\"[toNumber($x) , toNumber($y)]\\\"}},\\\"concepts\\\":{\\\"identifier\\\":\\\"C6\\\",\\\"name\\\":\\\"Counting\\\"}},{\\\"langid\\\":\\\"en\\\",\\\"identifier\\\":\\\"org.ekstep.funtoot.multiplicationhorizontal-g1-l0-sl1-q4-rand32618225043562643\\\",\\\"language\\\":[\\\"English\\\"],\\\"qid\\\":\\\"org.ekstep.funtoot.multiplicationhorizontal-g1-l0-sl1\\\",\\\"subject\\\":\\\"LMA\\\",\\\"grade\\\":\\\"1\\\",\\\"gradeLevel\\\":[\\\"Grade 1\\\"],\\\"bloomsTaxonomyLevel\\\":\\\"R\\\",\\\"level\\\":0,\\\"sublevel\\\":1,\\\"qindex\\\":\\\"\\\",\\\"qlevel\\\":\\\"EASY\\\",\\\"type\\\":\\\"ftb\\\",\\\"template_id\\\":\\\"\\\",\\\"template\\\":\\\"multiplicationhorizontal\\\",\\\"title\\\":\\\"Multiplication\\\",\\\"question_audio\\\":\\\"\\\",\\\"question_image\\\":\\\"\\\",\\\"model\\\":{\\\"numbers\\\":\\\"$nums\\\",\\\"numericLangId\\\":\\\"en\\\",\\\"langId\\\":\\\"en\\\",\\\"numberType\\\":\\\"\\\",\\\"hintMsg\\\":\\\"HINT_1\\\",\\\"question\\\":\\\"QTEXT\\\",\\\"variables\\\":{\\\"$x\\\":\\\"random(1 , 20)\\\",\\\"$y\\\":\\\"1\\\",\\\"$nums\\\":\\\"[toNumber($x) , toNumber($y)]\\\"}},\\\"concepts\\\":{\\\"identifier\\\":\\\"C6\\\",\\\"name\\\":\\\"Counting\\\"}},{\\\"langid\\\":\\\"en\\\",\\\"identifier\\\":\\\"org.ekstep.funtoot.multiplicationhorizontal-g1-l0-sl1-q5-rand9131360459518736\\\",\\\"language\\\":[\\\"English\\\"],\\\"qid\\\":\\\"org.ekstep.funtoot.multiplicationhorizontal-g1-l0-sl1\\\",\\\"subject\\\":\\\"LMA\\\",\\\"grade\\\":\\\"1\\\",\\\"gradeLevel\\\":[\\\"Grade 1\\\"],\\\"bloomsTaxonomyLevel\\\":\\\"R\\\",\\\"level\\\":0,\\\"sublevel\\\":1,\\\"qindex\\\":\\\"\\\",\\\"qlevel\\\":\\\"EASY\\\",\\\"type\\\":\\\"ftb\\\",\\\"template_id\\\":\\\"\\\",\\\"template\\\":\\\"multiplicationhorizontal\\\",\\\"title\\\":\\\"Multiplication\\\",\\\"question_audio\\\":\\\"\\\",\\\"question_image\\\":\\\"\\\",\\\"model\\\":{\\\"numbers\\\":\\\"$nums\\\",\\\"numericLangId\\\":\\\"en\\\",\\\"langId\\\":\\\"en\\\",\\\"numberType\\\":\\\"\\\",\\\"hintMsg\\\":\\\"HINT_1\\\",\\\"question\\\":\\\"QTEXT\\\",\\\"variables\\\":{\\\"$x\\\":\\\"random(1 , 20)\\\",\\\"$y\\\":\\\"1\\\",\\\"$nums\\\":\\\"[toNumber($x) , toNumber($y)]\\\"}},\\\"concepts\\\":{\\\"identifier\\\":\\\"C6\\\",\\\"name\\\":\\\"Counting\\\"}},{\\\"langid\\\":\\\"en\\\",\\\"identifier\\\":\\\"org.ekstep.funtoot.multiplicationhorizontal-g1-l0-sl1-q6-rand8028343590062477\\\",\\\"language\\\":[\\\"English\\\"],\\\"qid\\\":\\\"org.ekstep.funtoot.multiplicationhorizontal-g1-l0-sl1\\\",\\\"subject\\\":\\\"LMA\\\",\\\"grade\\\":\\\"1\\\",\\\"gradeLevel\\\":[\\\"Grade 1\\\"],\\\"bloomsTaxonomyLevel\\\":\\\"R\\\",\\\"level\\\":0,\\\"sublevel\\\":1,\\\"qindex\\\":\\\"\\\",\\\"qlevel\\\":\\\"EASY\\\",\\\"type\\\":\\\"ftb\\\",\\\"template_id\\\":\\\"\\\",\\\"template\\\":\\\"multiplicationhorizontal\\\",\\\"title\\\":\\\"Multiplication\\\",\\\"question_audio\\\":\\\"\\\",\\\"question_image\\\":\\\"\\\",\\\"model\\\":{\\\"numbers\\\":\\\"$nums\\\",\\\"numericLangId\\\":\\\"en\\\",\\\"langId\\\":\\\"en\\\",\\\"numberType\\\":\\\"\\\",\\\"hintMsg\\\":\\\"HINT_1\\\",\\\"question\\\":\\\"QTEXT\\\",\\\"variables\\\":{\\\"$x\\\":\\\"random(1 , 20)\\\",\\\"$y\\\":\\\"1\\\",\\\"$nums\\\":\\\"[toNumber($x) , toNumber($y)]\\\"}},\\\"concepts\\\":{\\\"identifier\\\":\\\"C6\\\",\\\"name\\\":\\\"Counting\\\"}},{\\\"langid\\\":\\\"en\\\",\\\"identifier\\\":\\\"org.ekstep.funtoot.multiplicationhorizontal-g1-l0-sl1-q7-rand6207816773538728\\\",\\\"language\\\":[\\\"English\\\"],\\\"qid\\\":\\\"org.ekstep.funtoot.multiplicationhorizontal-g1-l0-sl1\\\",\\\"subject\\\":\\\"LMA\\\",\\\"grade\\\":\\\"1\\\",\\\"gradeLevel\\\":[\\\"Grade 1\\\"],\\\"bloomsTaxonomyLevel\\\":\\\"R\\\",\\\"level\\\":0,\\\"sublevel\\\":1,\\\"qindex\\\":\\\"\\\",\\\"qlevel\\\":\\\"EASY\\\",\\\"type\\\":\\\"ftb\\\",\\\"template_id\\\":\\\"\\\",\\\"template\\\":\\\"multiplicationhorizontal\\\",\\\"title\\\":\\\"Multiplication\\\",\\\"question_audio\\\":\\\"\\\",\\\"question_image\\\":\\\"\\\",\\\"model\\\":{\\\"numbers\\\":\\\"$nums\\\",\\\"numericLangId\\\":\\\"en\\\",\\\"langId\\\":\\\"en\\\",\\\"numberType\\\":\\\"\\\",\\\"hintMsg\\\":\\\"HINT_1\\\",\\\"question\\\":\\\"QTEXT\\\",\\\"variables\\\":{\\\"$x\\\":\\\"random(1 , 20)\\\",\\\"$y\\\":\\\"1\\\",\\\"$nums\\\":\\\"[toNumber($x) , toNumber($y)]\\\"}},\\\"concepts\\\":{\\\"identifier\\\":\\\"C6\\\",\\\"name\\\":\\\"Counting\\\"}},{\\\"langid\\\":\\\"en\\\",\\\"identifier\\\":\\\"org.ekstep.funtoot.multiplicationhorizontal-g1-l0-sl1-q8-rand10865788722978564\\\",\\\"language\\\":[\\\"English\\\"],\\\"qid\\\":\\\"org.ekstep.funtoot.multiplicationhorizontal-g1-l0-sl1\\\",\\\"subject\\\":\\\"LMA\\\",\\\"grade\\\":\\\"1\\\",\\\"gradeLevel\\\":[\\\"Grade 1\\\"],\\\"bloomsTaxonomyLevel\\\":\\\"R\\\",\\\"level\\\":0,\\\"sublevel\\\":1,\\\"qindex\\\":\\\"\\\",\\\"qlevel\\\":\\\"EASY\\\",\\\"type\\\":\\\"ftb\\\",\\\"template_id\\\":\\\"\\\",\\\"template\\\":\\\"multiplicationhorizontal\\\",\\\"title\\\":\\\"Multiplication\\\",\\\"question_audio\\\":\\\"\\\",\\\"question_image\\\":\\\"\\\",\\\"model\\\":{\\\"numbers\\\":\\\"$nums\\\",\\\"numericLangId\\\":\\\"en\\\",\\\"langId\\\":\\\"en\\\",\\\"numberType\\\":\\\"\\\",\\\"hintMsg\\\":\\\"HINT_1\\\",\\\"question\\\":\\\"QTEXT\\\",\\\"variables\\\":{\\\"$x\\\":\\\"random(1 , 20)\\\",\\\"$y\\\":\\\"1\\\",\\\"$nums\\\":\\\"[toNumber($x) , toNumber($y)]\\\"}},\\\"concepts\\\":{\\\"identifier\\\":\\\"C6\\\",\\\"name\\\":\\\"Counting\\\"}},{\\\"langid\\\":\\\"en\\\",\\\"identifier\\\":\\\"org.ekstep.funtoot.multiplicationhorizontal-g1-l0-sl1-q9-rand9986962679208529\\\",\\\"language\\\":[\\\"English\\\"],\\\"qid\\\":\\\"org.ekstep.funtoot.multiplicationhorizontal-g1-l0-sl1\\\",\\\"subject\\\":\\\"LMA\\\",\\\"grade\\\":\\\"1\\\",\\\"gradeLevel\\\":[\\\"Grade 1\\\"],\\\"bloomsTaxonomyLevel\\\":\\\"R\\\",\\\"level\\\":0,\\\"sublevel\\\":1,\\\"qindex\\\":\\\"\\\",\\\"qlevel\\\":\\\"EASY\\\",\\\"type\\\":\\\"ftb\\\",\\\"template_id\\\":\\\"\\\",\\\"template\\\":\\\"multiplicationhorizontal\\\",\\\"title\\\":\\\"Multiplication\\\",\\\"question_audio\\\":\\\"\\\",\\\"question_image\\\":\\\"\\\",\\\"model\\\":{\\\"numbers\\\":\\\"$nums\\\",\\\"numericLangId\\\":\\\"en\\\",\\\"langId\\\":\\\"en\\\",\\\"numberType\\\":\\\"\\\",\\\"hintMsg\\\":\\\"HINT_1\\\",\\\"question\\\":\\\"QTEXT\\\",\\\"variables\\\":{\\\"$x\\\":\\\"random(1 , 20)\\\",\\\"$y\\\":\\\"1\\\",\\\"$nums\\\":\\\"[toNumber($x) , toNumber($y)]\\\"}},\\\"concepts\\\":{\\\"identifier\\\":\\\"C6\\\",\\\"name\\\":\\\"Counting\\\"}}]},\\\"i18n\\\":{\\\"en\\\":{\\\"HINT\\\":\\\"Hint\\\",\\\"MICROHINT\\\":\\\"Micro Hint\\\",\\\"SOLUTION\\\":\\\"Solution\\\",\\\"HELP\\\":\\\"Help\\\",\\\"REDUCE_FRACTION\\\":\\\"Check the solution again. Remove the common factors in the fraction and reduce it to its lowest term.\\\",\\\"MIXED_FRACTION\\\":\\\"Convert the mixed fraction to an improper fraction.\\\",\\\"IMPROPER_FRACTION\\\":\\\"Convert the improper fraction to an mixed fraction.\\\",\\\"LIKEFRACTIONADDITION_NUMERATOR\\\":\\\"Add the numerator of the given fractions correctly.\\\",\\\"LIKEFRACTIONADDITION_DENOMINATOR\\\":\\\"For addition of like fractions the denominator remains the same.\\\",\\\"LIKEFRACTIONADDITION_FULL\\\":\\\"Check the addition of the numerator. The denominator remains the same.\\\",\\\"UNLIKEFRACTIONADDITION_NUMERATOR\\\":\\\"First convert the unlike fractions to like fractions. Then add the numerator of the like fractions.\\\",\\\"UNLIKEFRACTIONADDITION_DENOMINATOR\\\":\\\"First find the least common factor and convert the unlike fractions to like fractions. The denominator of the solution is the denominator of the like fractions.\\\",\\\"UNLIKEFRACTIONADDITION_FULL\\\":\\\"Convert the given fractions to like fractions and then carefully do the addition.\\\",\\\"LIKEFRACTIONSUBTRACTION_NUMERATOR\\\":\\\"Subtract the numerator of the given fractions correctly.\\\",\\\"LIKEFRACTIONSUBTRACTION_DENOMINATOR\\\":\\\"For subtraction of like fractions the denominator remains the same as that of the question.\\\",\\\"LIKEFRACTIONSUBTRACTION_FULL\\\":\\\"Subtract the numerator of the fractions. Denominator remains the same.\\\",\\\"UNLIKEFRACTIONSUBTRACTION_NUMERATOR\\\":\\\"First convert the unlike fractions to like fractions. Then subtract the numerator of the like fractions.\\\",\\\"UNLIKEFRACTIONSUBTRACTION_DENOMINATOR\\\":\\\"First find the least common factor and convert the unlike fractions to like fractions. The denominator of the solution is the denominator of the like fractions.\\\",\\\"UNLIKEFRACTIONSUBTRACTION_FULL\\\":\\\"Convert the given fractions to like fractions and then carefully do the subtraction.\\\",\\\"LIKEMIXEDFRACTIONADDITION_WHOLE\\\":\\\"Add the whole number part of both the fractions carefully. Check for the conversion of the improper fraction to proper fractions in the solution.\\\",\\\"LIKEMIXEDFRACTIONADDITION_NUMERATOR\\\":\\\"Add the numerator of the like fractions. If the fractional part is an improper fraction, then convert it to a proper fraction.\\\",\\\"LIKEMIXEDFRACTIONADDITION_DENOMINATOR\\\":\\\"The denominator of the solution fraction does not change for like fractions.\\\",\\\"LIKEMIXEDFRACTIONADDITION_FULL\\\":\\\"Convert the mixed fractions to improper fractions and then add them. The final solution should again be as a mixed fraction.\\\",\\\"LIKEMIXEDFRACTIONSUBTRACTION_WHOLE\\\":\\\"Subtract the whole number part of both the fractions carefully.\\\",\\\"LIKEMIXEDFRACTIONSUBTRACTION_NUMERATOR\\\":\\\"Subtract the numerator of the like fractions.\\\",\\\"LIKEMIXEDFRACTIONSUBTRACTION_DENOMINATOR\\\":\\\"The denominator of the solution fraction does not change for like fractions.\\\",\\\"LIKEMIXEDFRACTIONSUBTRACTION_FULL\\\":\\\"Convert the mixed fractions to improper fractions and then subtract them. The final solution should again be as a mixed fraction.\\\",\\\"WHOLEANDPROPERFRACTIONADDITION_WHOLE\\\":\\\"The integer added becomes the whole number part of the mixed fraction.\\\",\\\"WHOLEANDPROPERFRACTIONADDITION_NUMERATOR\\\":\\\"The numerator of the solution fraction remains the same.\\\",\\\"WHOLEANDPROPERFRACTIONADDITION_DENOMINATOR\\\":\\\"The denominator of the solution fraction remains the same as given in the problem.\\\",\\\"WHOLEANDPROPERFRACTIONADDITION_FULL\\\":\\\"The integer and the proper fraction when added becomes the mixed fraction.\\\",\\\"WHOLEANDPROPERFRACTIONSUBTRACTION_WHOLE\\\":\\\"Convert the whole number to an equivalent fraction. Then find the difference between the like fractions.\\\",\\\"WHOLEANDPROPERFRACTIONSUBTRACTION_NUMERATOR\\\":\\\"First find the least common factor and convert them to difference between like fractions. Then subtract the numerators carefully.\\\",\\\"WHOLEANDPROPERFRACTIONSUBTRACTION_DENOMINATOR\\\":\\\"The denominator of the solution fraction remains the same as given in the problem.\\\",\\\"WHOLEANDPROPERFRACTIONSUBTRACTION_FULL\\\":\\\"When the proper fraction is subtracted from the integer becomes the mixed fraction.\\\",\\\"WHOLEANDFRACTIONMULTIPLICATION_NUMERATOR\\\":\\\"Multiply the numerator and the whole number carefully.\\\",\\\"WHOLEANDFRACTIONMULTIPLICATION_DENOMINATOR\\\":\\\"Multiply the denominators of the fractions carefully.\\\",\\\"WHOLEANDFRACTIONMULTIPLICATION_FULL\\\":\\\"Multiply the integer with the fraction.\\\",\\\"FRACTIONMULTIPLICATION_NUMERATOR\\\":\\\"Multiply the numerators of the fractions carefully.\\\",\\\"FRACTIONMULTIPLICATION_DENOMINATOR\\\":\\\"Multiply the denominators of the fractions carefully.\\\",\\\"FRACTIONMULTIPLICATION_FULL\\\":\\\"Multiply the numerators and denominators of the fractions.\\\",\\\"FRACTIONDIVISION\\\":\\\"First find the reciprocal of the divisor. Then multiply the fraction with the reciprocal of the divisor to get the solution.\\\",\\\"QTEXT\\\":\\\"Multiply the given numbers.\\\",\\\"MH_SINGLEDIGIT\\\":\\\"Check the numbers to be multiplied and recall skip counting and carefully try again.\\\",\\\"MH_SAME\\\":\\\"Please understand that product of two equal numbers is calculated exactly like product of any numbers. Try again.\\\",\\\"MH_10\\\":\\\"When multiplying with 10 or powers of 10, carefully check the number of zeroes in the product and try again.\\\",\\\"MH_SUM\\\":\\\"Please identify the symbol carefully and find the product of the given numbers.\\\",\\\"NO_HINT\\\":\\\"There is no hint for this question\\\",\\\"QUESTION_TITLE\\\":\\\"Multiplication\\\",\\\"MH_END0\\\":\\\"Please do not leave the zeros  in the product while multiplying with powers of 10.\\\",\\\"MH_MISPLACE\\\":\\\"Please go through the process of multiplication and identify the exact position where numbers must be placed after multiplying each digit.\\\",\\\"MH_0\\\":\\\"Do not ignore the zero in the given numbers. Carefully do the multiplication.\\\",\\\"MH_1\\\":\\\"When we multiply by 1, we get the number itself. This is the special property of 1.\\\",\\\"NO_ANSWER\\\":\\\"Please answer\\\",\\\"MH_POWERSOF10\\\":\\\"Multiply the given numbers and add as many zeroes as needed. Place the decimal point correctly.\\\",\\\"HINT_4\\\":\\\"Carefully find the product of the numbers by recalling the skip counting sequences.\\\",\\\"HINT_5\\\":\\\"Carefully multiply by each term and calculate the product without missing the addition of carryover digits.\\\",\\\"MH_DEFAULT\\\":\\\"Please recall the process of multiplication. When multiplying with successive digits, we need to identify the correct place value to put the next set of multiplied numbers.\\\",\\\"HINT_6DECIMAL\\\":\\\"The decimal point moves one place to the right after multiplication.\\\",\\\"HINT_1\\\":\\\"Product of a number with 1 gives the number itself.\\\",\\\"HINT_2\\\":\\\"Carefully remember counting in 2's and try again.\\\",\\\"HINT_3\\\":\\\"Carefully remember counting in 3's and try again.\\\",\\\"MH_MISSED0\\\":\\\"The product with zero must be calculated to find the final answer. Please do not leave multiplying with zero.\\\",\\\"MH_DECIMAL\\\":\\\"Multiply the given numbers. Now place the decimal point in such a way that it will have as many decimal places as the original operands combined.\\\"}},\\\"selectedConfig\\\":{\\\"enableNextButton\\\":true,\\\"Grade\\\":\\\"1\\\",\\\"Level\\\":{\\\"Level\\\":0,\\\"LevelDesc\\\":\\\"Multiplication with single digit numbers\\\",\\\"$$hashKey\\\":\\\"object:9262\\\"},\\\"SubLevel\\\":{\\\"SubLevel\\\":1,\\\"SubLevelDesc\\\":\\\"Multiply by 1\\\",\\\"$$hashKey\\\":\\\"object:9263\\\"},\\\"itemData\\\":{\\\"Type\\\":\\\"Multiplication\\\",\\\"Grade\\\":1,\\\"Level\\\":0,\\\"LevelDesc\\\":\\\"Multiplication with single digit numbers\\\",\\\"SubLevel\\\":1,\\\"SubLevelDesc\\\":\\\"Multiply by 1\\\",\\\"Expression\\\":\\\"$x = random(1 , 20)\\\\n$y = 1\\\\n$nums = [toNumber($x) , toNumber($y)]\\\",\\\"BTLO\\\":\\\"R\\\",\\\"DifficultyLevel\\\":2,\\\"Description\\\":\\\"Tests the multiplication of numbers by 1.\\\",\\\"SubLevelDesc1\\\":\\\"Give numbers between 1 and 20 to be multiplied by 1.\\\",\\\"HintID\\\":\\\"HINT_1\\\",\\\"QuestionText\\\":\\\"QTEXT\\\",\\\"QID\\\":\\\"\\\",\\\"Subject\\\":\\\"LMA\\\",\\\"ConceptCode\\\":\\\"C271, C548\\\",\\\"ESDifficultyLevel\\\":\\\"Easy\\\"},\\\"QCount\\\":3,\\\"showImmediateFeedback\\\":true,\\\"areVariablesStatic\\\":false,\\\"areMicrohintsEnabled\\\":true,\\\"enableFeedback\\\":true,\\\"enableSolution\\\":true,\\\"enableHint\\\":true,\\\"retainAnswers\\\":true,\\\"maxNoOfAtt\\\":2,\\\"contentLocale\\\":\\\"en\\\",\\\"numeralLocale\\\":\\\"en\\\"}}\"},\"config\":{\"__cdata\":\"{\\\"title\\\":\\\"Multiplication\\\",\\\"count\\\":10,\\\"locales\\\":{\\\"contentLocale\\\":\\\"en\\\",\\\"numeralLocale\\\":\\\"en\\\"},\\\"selectedConfig\\\":{\\\"enableNextButton\\\":true,\\\"Grade\\\":\\\"1\\\",\\\"Level\\\":{\\\"Level\\\":0,\\\"LevelDesc\\\":\\\"Multiplication with single digit numbers\\\",\\\"$$hashKey\\\":\\\"object:9262\\\"},\\\"SubLevel\\\":{\\\"SubLevel\\\":1,\\\"SubLevelDesc\\\":\\\"Multiply by 1\\\",\\\"$$hashKey\\\":\\\"object:9263\\\"},\\\"itemData\\\":{\\\"Type\\\":\\\"Multiplication\\\",\\\"Grade\\\":1,\\\"Level\\\":0,\\\"LevelDesc\\\":\\\"Multiplication with single digit numbers\\\",\\\"SubLevel\\\":1,\\\"SubLevelDesc\\\":\\\"Multiply by 1\\\",\\\"Expression\\\":\\\"$x = random(1 , 20)\\\\n$y = 1\\\\n$nums = [toNumber($x) , toNumber($y)]\\\",\\\"BTLO\\\":\\\"R\\\",\\\"DifficultyLevel\\\":2,\\\"Description\\\":\\\"Tests the multiplication of numbers by 1.\\\",\\\"SubLevelDesc1\\\":\\\"Give numbers between 1 and 20 to be multiplied by 1.\\\",\\\"HintID\\\":\\\"HINT_1\\\",\\\"QuestionText\\\":\\\"QTEXT\\\",\\\"QID\\\":\\\"\\\",\\\"Subject\\\":\\\"LMA\\\",\\\"ConceptCode\\\":\\\"C271, C548\\\",\\\"ESDifficultyLevel\\\":\\\"Easy\\\"},\\\"QCount\\\":3,\\\"showImmediateFeedback\\\":true,\\\"areVariablesStatic\\\":false,\\\"areMicrohintsEnabled\\\":true,\\\"enableFeedback\\\":true,\\\"enableSolution\\\":true,\\\"enableHint\\\":true,\\\"retainAnswers\\\":true,\\\"maxNoOfAtt\\\":2,\\\"contentLocale\\\":\\\"en\\\",\\\"numeralLocale\\\":\\\"en\\\"},\\\"type\\\":\\\"items\\\",\\\"var\\\":\\\"item\\\"}\"}}]}],\"manifest\":{\"media\":[{\"id\":\"3612b1da-8837-458c-ab6c-b5c1474098d4\",\"plugin\":\"org.ekstep.navigation\",\"ver\":\"1.0\",\"src\":\"/content-plugins/org.ekstep.navigation-1.0/renderer/controller/navigation_ctrl.js\",\"type\":\"js\"},{\"id\":\"5a55be01-ca2e-4e3c-a244-61530e814678\",\"plugin\":\"org.ekstep.navigation\",\"ver\":\"1.0\",\"src\":\"/content-plugins/org.ekstep.navigation-1.0/renderer/templates/navigation.html\",\"type\":\"js\"},{\"id\":\"org.ekstep.navigation\",\"plugin\":\"org.ekstep.navigation\",\"ver\":\"1.0\",\"src\":\"/content-plugins/org.ekstep.navigation-1.0/renderer/plugin.js\",\"type\":\"plugin\"},{\"id\":\"org.ekstep.navigation_manifest\",\"plugin\":\"org.ekstep.navigation\",\"ver\":\"1.0\",\"src\":\"/content-plugins/org.ekstep.navigation-1.0/manifest.json\",\"type\":\"json\"},{\"id\":\"polyglot\",\"plugin\":\"org.ekstep.plugins.i18n\",\"ver\":\"1.0\",\"src\":\"/content-plugins/org.ekstep.plugins.i18n-1.0/renderer/polyglot.js\",\"type\":\"js\"},{\"id\":\"org.ekstep.plugins.i18n\",\"plugin\":\"org.ekstep.plugins.i18n\",\"ver\":\"1.0\",\"src\":\"/content-plugins/org.ekstep.plugins.i18n-1.0/renderer/plugin.js\",\"type\":\"plugin\"},{\"id\":\"org.ekstep.plugins.i18n_manifest\",\"plugin\":\"org.ekstep.plugins.i18n\",\"ver\":\"1.0\",\"src\":\"/content-plugins/org.ekstep.plugins.i18n-1.0/manifest.json\",\"type\":\"json\"},{\"id\":\"keyboardcss\",\"plugin\":\"org.ekstep.plugins.common.keyboard\",\"ver\":\"1.0\",\"src\":\"/content-plugins/org.ekstep.plugins.common.keyboard-1.0/renderer/keyboard.css\",\"type\":\"css\"},{\"id\":\"org.ekstep.plugins.common.keyboard\",\"plugin\":\"org.ekstep.plugins.common.keyboard\",\"ver\":\"1.0\",\"src\":\"/content-plugins/org.ekstep.plugins.common.keyboard-1.0/renderer/keyboard-plugin.js\",\"type\":\"plugin\"},{\"id\":\"org.ekstep.plugins.common.keyboard_manifest\",\"plugin\":\"org.ekstep.plugins.common.keyboard\",\"ver\":\"1.0\",\"src\":\"/content-plugins/org.ekstep.plugins.common.keyboard-1.0/manifest.json\",\"type\":\"json\"},{\"id\":\"generators\",\"plugin\":\"org.ekstep.funtoot.common\",\"ver\":\"1.0\",\"src\":\"/content-plugins/org.ekstep.funtoot.common-1.0/renderer/generators.js\",\"type\":\"js\"},{\"id\":\"eraser\",\"plugin\":\"org.ekstep.funtoot.common\",\"ver\":\"1.0\",\"src\":\"/content-plugins/org.ekstep.funtoot.common-1.0/assets/eraser.png\",\"type\":\"image\"},{\"id\":\"seq\",\"plugin\":\"org.ekstep.funtoot.common\",\"ver\":\"1.0\",\"src\":\"/content-plugins/org.ekstep.funtoot.common-1.0/assets/seq.png\",\"type\":\"image\"},{\"id\":\"semitrans\",\"plugin\":\"org.ekstep.funtoot.common\",\"ver\":\"1.0\",\"src\":\"/content-plugins/org.ekstep.funtoot.common-1.0/assets/semitrans.png\",\"type\":\"image\"},{\"id\":\"zoom-in\",\"plugin\":\"org.ekstep.funtoot.common\",\"ver\":\"1.0\",\"src\":\"/content-plugins/org.ekstep.funtoot.common-1.0/assets/zoom.png\",\"type\":\"image\"},{\"id\":\"plus-white\",\"plugin\":\"org.ekstep.funtoot.common\",\"ver\":\"1.0\",\"src\":\"/content-plugins/org.ekstep.funtoot.common-1.0/assets/plus_white.png\",\"type\":\"image\"},{\"id\":\"minus-white\",\"plugin\":\"org.ekstep.funtoot.common\",\"ver\":\"1.0\",\"src\":\"/content-plugins/org.ekstep.funtoot.common-1.0/assets/minus_white.png\",\"type\":\"image\"},{\"id\":\"micro-hint\",\"plugin\":\"org.ekstep.funtoot.common\",\"ver\":\"1.0\",\"src\":\"/content-plugins/org.ekstep.funtoot.common-1.0/assets/micro-hint.png\",\"type\":\"image\"},{\"id\":\"micro-hint-mdd\",\"plugin\":\"org.ekstep.funtoot.common\",\"ver\":\"1.0\",\"src\":\"/content-plugins/org.ekstep.funtoot.common-1.0/assets/micro-hint.png\",\"type\":\"image\"},{\"id\":\"html-micro-hint\",\"plugin\":\"org.ekstep.funtoot.common\",\"ver\":\"1.0\",\"src\":\"/content-plugins/org.ekstep.funtoot.common-1.0/assets/micro-hint.png\",\"type\":\"image\"},{\"id\":\"drop-down\",\"plugin\":\"org.ekstep.funtoot.common\",\"ver\":\"1.0\",\"src\":\"/content-plugins/org.ekstep.funtoot.common-1.0/assets/drop-down-icon.png\",\"type\":\"image\"},{\"id\":\"org.ekstep.funtoot.hint-icon\",\"plugin\":\"org.ekstep.funtoot.common\",\"ver\":\"1.0\",\"src\":\"/content-plugins/org.ekstep.funtoot.common-1.0/assets/hint.png\",\"type\":\"image\"},{\"id\":\"org.ekstep.funtoot.solution-icon\",\"plugin\":\"org.ekstep.funtoot.common\",\"ver\":\"1.0\",\"src\":\"/content-plugins/org.ekstep.funtoot.common-1.0/assets/solimg.png\",\"type\":\"image\"},{\"id\":\"close\",\"plugin\":\"org.ekstep.funtoot.common\",\"ver\":\"1.0\",\"src\":\"/content-plugins/org.ekstep.funtoot.common-1.0/assets/close.png\",\"type\":\"image\"},{\"id\":\"submit\",\"plugin\":\"org.ekstep.funtoot.common\",\"ver\":\"1.0\",\"src\":\"/content-plugins/org.ekstep.funtoot.common-1.0/assets/icn_submit.png\",\"type\":\"image\"},{\"id\":\"undo\",\"plugin\":\"org.ekstep.funtoot.common\",\"ver\":\"1.0\",\"src\":\"/content-plugins/org.ekstep.funtoot.common-1.0/assets/undo.png\",\"type\":\"image\"},{\"id\":\"clearall\",\"plugin\":\"org.ekstep.funtoot.common\",\"ver\":\"1.0\",\"src\":\"/content-plugins/org.ekstep.funtoot.common-1.0/assets/clearall.png\",\"type\":\"image\"},{\"id\":\"disabledsubmit\",\"plugin\":\"org.ekstep.funtoot.common\",\"ver\":\"1.0\",\"src\":\"/content-plugins/org.ekstep.funtoot.common-1.0/assets/disabled_submit.png\",\"type\":\"image\"},{\"id\":\"org.ekstep.funtoot.asset.next\",\"plugin\":\"org.ekstep.funtoot.common\",\"ver\":\"1.0\",\"src\":\"/content-plugins/org.ekstep.funtoot.common-1.0/assets/next.png\",\"type\":\"image\"},{\"id\":\"editable\",\"plugin\":\"org.ekstep.funtoot.common\",\"ver\":\"1.0\",\"src\":\"/content-plugins/org.ekstep.funtoot.common-1.0/assets/editable.png\",\"type\":\"image\"},{\"id\":\"nonEditable\",\"plugin\":\"org.ekstep.funtoot.common\",\"ver\":\"1.0\",\"src\":\"/content-plugins/org.ekstep.funtoot.common-1.0/assets/noneditable.png\",\"type\":\"image\"},{\"id\":\"additioneval\",\"plugin\":\"org.ekstep.funtoot.common\",\"ver\":\"1.0\",\"src\":\"/content-plugins/org.ekstep.funtoot.common-1.0/renderer/additioneval.js\",\"type\":\"js\"},{\"id\":\"fractioneval\",\"plugin\":\"org.ekstep.funtoot.common\",\"ver\":\"1.0\",\"src\":\"/content-plugins/org.ekstep.funtoot.common-1.0/renderer/fractioneval.js\",\"type\":\"js\"},{\"id\":\"multiplicationeval\",\"plugin\":\"org.ekstep.funtoot.common\",\"ver\":\"1.0\",\"src\":\"/content-plugins/org.ekstep.funtoot.common-1.0/renderer/multiplicationeval.js\",\"type\":\"js\"},{\"id\":\"divisioneval\",\"plugin\":\"org.ekstep.funtoot.common\",\"ver\":\"1.0\",\"src\":\"/content-plugins/org.ekstep.funtoot.common-1.0/renderer/divisioneval.js\",\"type\":\"js\"},{\"id\":\"clockcontrol\",\"plugin\":\"org.ekstep.funtoot.common\",\"ver\":\"1.0\",\"src\":\"/content-plugins/org.ekstep.funtoot.common-1.0/renderer/clockcontrol.js\",\"type\":\"plugin\"},{\"id\":\"numberlineeval\",\"plugin\":\"org.ekstep.funtoot.common\",\"ver\":\"1.0\",\"src\":\"/content-plugins/org.ekstep.funtoot.common-1.0/renderer/numberlineeval.js\",\"type\":\"js\"},{\"id\":\"mathquill\",\"plugin\":\"org.ekstep.funtoot.common\",\"ver\":\"1.0\",\"src\":\"/content-plugins/org.ekstep.funtoot.common-1.0/renderer/mathquill.js\",\"type\":\"js\"},{\"id\":\"mathjs\",\"plugin\":\"org.ekstep.funtoot.common\",\"ver\":\"1.0\",\"src\":\"/content-plugins/org.ekstep.funtoot.common-1.0/renderer/math.min.js\",\"type\":\"js\"},{\"id\":\"mathquill-basic\",\"plugin\":\"org.ekstep.funtoot.common\",\"ver\":\"1.0\",\"src\":\"/content-plugins/org.ekstep.funtoot.common-1.0/renderer/mathquill.css\",\"type\":\"css\"},{\"id\":\"genericmdd\",\"plugin\":\"org.ekstep.funtoot.common\",\"ver\":\"1.0\",\"src\":\"/content-plugins/org.ekstep.funtoot.common-1.0/renderer/css/genericmdd.css\",\"type\":\"css\"},{\"id\":\"zoomableImageStyle\",\"plugin\":\"org.ekstep.funtoot.common\",\"ver\":\"1.0\",\"src\":\"/content-plugins/org.ekstep.funtoot.common-1.0/renderer/css/zoomableimage.css\",\"type\":\"css\"},{\"id\":\"mathtext\",\"plugin\":\"org.ekstep.funtoot.common\",\"ver\":\"1.0\",\"src\":\"/content-plugins/org.ekstep.funtoot.common-1.0/renderer/mathtext.js\",\"type\":\"plugin\"},{\"id\":\"mathedit\",\"plugin\":\"org.ekstep.funtoot.common\",\"ver\":\"1.0\",\"src\":\"/content-plugins/org.ekstep.funtoot.common-1.0/renderer/mathedit.js\",\"type\":\"plugin\"},{\"id\":\"org.ekstep.funtoot.ftPlugin\",\"plugin\":\"org.ekstep.funtoot.common\",\"ver\":\"1.0\",\"src\":\"/content-plugins/org.ekstep.funtoot.common-1.0/renderer/ftbaseplugin.js\",\"type\":\"plugin\"},{\"id\":\"nkeyboard\",\"plugin\":\"org.ekstep.funtoot.common\",\"ver\":\"1.0\",\"src\":\"/content-plugins/org.ekstep.funtoot.common-1.0/renderer/customnumkeyboard.js\",\"type\":\"plugin\"},{\"id\":\"keyboard\",\"plugin\":\"org.ekstep.funtoot.common\",\"ver\":\"1.0\",\"src\":\"/content-plugins/org.ekstep.funtoot.common-1.0/renderer/keyboard-plugin.js\",\"type\":\"plugin\"},{\"id\":\"fibblankprocessor\",\"plugin\":\"org.ekstep.funtoot.common\",\"ver\":\"1.0\",\"src\":\"/content-plugins/org.ekstep.funtoot.common-1.0/renderer/fibblankprocessor.js\",\"type\":\"plugin\"},{\"id\":\"ftbdropdownprocessor\",\"plugin\":\"org.ekstep.funtoot.common\",\"ver\":\"1.0\",\"src\":\"/content-plugins/org.ekstep.funtoot.common-1.0/renderer/ftbdropdownprocessor.js\",\"type\":\"plugin\"},{\"id\":\"org.ekstep.funtoot.zoomableImage\",\"plugin\":\"org.ekstep.funtoot.common\",\"ver\":\"1.0\",\"src\":\"/content-plugins/org.ekstep.funtoot.common-1.0/renderer/zoomableimage.js\",\"type\":\"plugin\"},{\"id\":\"defaultkeyboardadapter\",\"plugin\":\"org.ekstep.funtoot.common\",\"ver\":\"1.0\",\"src\":\"/content-plugins/org.ekstep.funtoot.common-1.0/renderer/defaultkeyboardadapter.js\",\"type\":\"plugin\"},{\"id\":\"ftFib\",\"plugin\":\"org.ekstep.funtoot.common\",\"ver\":\"1.0\",\"src\":\"/content-plugins/org.ekstep.funtoot.common-1.0/renderer/ftfib.js\",\"type\":\"plugin\"},{\"id\":\"ftPluginHelper\",\"plugin\":\"org.ekstep.funtoot.common\",\"ver\":\"1.0\",\"src\":\"/content-plugins/org.ekstep.funtoot.common-1.0/renderer/ftpluginhelper.js\",\"type\":\"plugin\"},{\"id\":\"org.ekstep.funtoot.grid\",\"plugin\":\"org.ekstep.funtoot.common\",\"ver\":\"1.0\",\"src\":\"/content-plugins/org.ekstep.funtoot.common-1.0/renderer/grid.js\",\"type\":\"plugin\"},{\"id\":\"org.ekstep.funtoot.table\",\"plugin\":\"org.ekstep.funtoot.common\",\"ver\":\"1.0\",\"src\":\"/content-plugins/org.ekstep.funtoot.common-1.0/renderer/table.js\",\"type\":\"plugin\"},{\"id\":\"keyboard_css\",\"plugin\":\"org.ekstep.funtoot.common\",\"ver\":\"1.0\",\"src\":\"/content-plugins/org.ekstep.funtoot.common-1.0/renderer/css/numerickeyboard.css\",\"type\":\"css\"},{\"id\":\"htmlpopup\",\"plugin\":\"org.ekstep.funtoot.common\",\"ver\":\"1.0\",\"src\":\"/content-plugins/org.ekstep.funtoot.common-1.0/renderer/htmlpopupplugin.js\",\"type\":\"plugin\"},{\"id\":\"htmlpopup_css\",\"plugin\":\"org.ekstep.funtoot.common\",\"ver\":\"1.0\",\"src\":\"/content-plugins/org.ekstep.funtoot.common-1.0/renderer/css/htmlpopup.css\",\"type\":\"css\"},{\"id\":\"htmlpopup_js\",\"plugin\":\"org.ekstep.funtoot.common\",\"ver\":\"1.0\",\"src\":\"/content-plugins/org.ekstep.funtoot.common-1.0/renderer/scripts/htmlpopup.js\",\"type\":\"js\"},{\"id\":\"ftMicroHint\",\"plugin\":\"org.ekstep.funtoot.common\",\"ver\":\"1.0\",\"src\":\"/content-plugins/org.ekstep.funtoot.common-1.0/renderer/ftmicrohint.js\",\"type\":\"plugin\"},{\"id\":\"ftPopup\",\"plugin\":\"org.ekstep.funtoot.common\",\"ver\":\"1.0\",\"src\":\"/content-plugins/org.ekstep.funtoot.common-1.0/renderer/ftpopup.js\",\"type\":\"plugin\"},{\"id\":\"ftAttempts\",\"plugin\":\"org.ekstep.funtoot.common\",\"ver\":\"1.0\",\"src\":\"/content-plugins/org.ekstep.funtoot.common-1.0/renderer/ftattempts.js\",\"type\":\"plugin\"},{\"id\":\"inlineFib\",\"plugin\":\"org.ekstep.funtoot.common\",\"ver\":\"1.0\",\"src\":\"/content-plugins/org.ekstep.funtoot.common-1.0/renderer/inlinefib.js\",\"type\":\"plugin\"},{\"id\":\"numberlinenumber\",\"plugin\":\"org.ekstep.funtoot.common\",\"ver\":\"1.0\",\"src\":\"/content-plugins/org.ekstep.funtoot.common-1.0/renderer/numberlinenumber.js\",\"type\":\"plugin\"},{\"id\":\"numberline\",\"plugin\":\"org.ekstep.funtoot.common\",\"ver\":\"1.0\",\"src\":\"/content-plugins/org.ekstep.funtoot.common-1.0/renderer/numberline.js\",\"type\":\"plugin\"},{\"id\":\"org.ekstep.funtoot.option\",\"plugin\":\"org.ekstep.funtoot.common\",\"ver\":\"1.0\",\"src\":\"/content-plugins/org.ekstep.funtoot.common-1.0/renderer/option.js\",\"type\":\"plugin\"},{\"id\":\"org.ekstep.funtoot.optionBuilder\",\"plugin\":\"org.ekstep.funtoot.common\",\"ver\":\"1.0\",\"src\":\"/content-plugins/org.ekstep.funtoot.common-1.0/renderer/optionbuilder.js\",\"type\":\"plugin\"},{\"id\":\"org.ekstep.funtoot.common\",\"plugin\":\"org.ekstep.funtoot.common\",\"ver\":\"1.0\",\"src\":\"/content-plugins/org.ekstep.funtoot.common-1.0/renderer/ftfibbaseplugin.js\",\"type\":\"plugin\"},{\"id\":\"org.ekstep.funtoot.common_manifest\",\"plugin\":\"org.ekstep.funtoot.common\",\"ver\":\"1.0\",\"src\":\"/content-plugins/org.ekstep.funtoot.common-1.0/manifest.json\",\"type\":\"json\"},{\"id\":\"org.ekstep.funtoot.multiplicationhorizontalbase\",\"plugin\":\"org.ekstep.funtoot.multiplicationhorizontalbase\",\"ver\":\"1.0\",\"src\":\"/content-plugins/org.ekstep.funtoot.multiplicationhorizontalbase-1.0/renderer/plugin.js\",\"type\":\"plugin\"},{\"id\":\"org.ekstep.funtoot.multiplicationhorizontalbase_manifest\",\"plugin\":\"org.ekstep.funtoot.multiplicationhorizontalbase\",\"ver\":\"1.0\",\"src\":\"/content-plugins/org.ekstep.funtoot.multiplicationhorizontalbase-1.0/manifest.json\",\"type\":\"json\"},{\"id\":\"org.ekstep.funtoot.multiplicationhorizontal\",\"plugin\":\"org.ekstep.funtoot.multiplicationhorizontal\",\"ver\":\"1.0\",\"src\":\"/content-plugins/org.ekstep.funtoot.multiplicationhorizontal-1.0/renderer/plugin.js\",\"type\":\"plugin\"},{\"id\":\"org.ekstep.funtoot.multiplicationhorizontal_manifest\",\"plugin\":\"org.ekstep.funtoot.multiplicationhorizontal\",\"ver\":\"1.0\",\"src\":\"/content-plugins/org.ekstep.funtoot.multiplicationhorizontal-1.0/manifest.json\",\"type\":\"json\"}]},\"plugin-manifest\":{\"plugin\":[{\"id\":\"org.ekstep.navigation\",\"ver\":\"1.0\",\"type\":\"plugin\",\"depends\":\"\"},{\"id\":\"org.ekstep.plugins.i18n\",\"ver\":\"1.0\",\"type\":\"plugin\",\"depends\":\"\"},{\"id\":\"org.ekstep.plugins.common.keyboard\",\"ver\":\"1.0\",\"type\":\"widget\",\"depends\":\"\"},{\"id\":\"org.ekstep.funtoot.common\",\"ver\":\"1.0\",\"type\":\"plugin\",\"depends\":\"org.ekstep.plugins.i18n,org.ekstep.plugins.common.keyboard\"},{\"id\":\"org.ekstep.funtoot.multiplicationhorizontalbase\",\"ver\":\"1.0\",\"type\":\"plugin\",\"depends\":\"org.ekstep.funtoot.common\"},{\"id\":\"org.ekstep.funtoot.multiplicationhorizontal\",\"ver\":\"1.0\",\"type\":\"plugin\",\"depends\":\"org.ekstep.funtoot.multiplicationhorizontalbase\"}]},\"compatibilityVersion\":2}}","languageCode":"en"}}}