{"id":"ekstep.content.find","ver":"3.0","ts":"2018-11-08T15:20:22ZZ","params":{"resmsgid":"d8d9eb7a-8266-48a6-a1b6-6ec3cbfa6314","msgid":null,"err":null,"status":"successful","errmsg":null},"responseCode":"OK","result":{"content":{"identifier":"do_21257273082313932818485","body":"{\"theme\":{\"id\":\"theme\",\"version\":\"1.0\",\"startStage\":\"7555527e-eabe-401b-bdb5-511c344dabae\",\"stage\":[{\"x\":0,\"y\":0,\"w\":100,\"h\":100,\"id\":\"7555527e-eabe-401b-bdb5-511c344dabae\",\"rotate\":null,\"config\":{\"__cdata\":\"{\\\"opacity\\\":100,\\\"strokeWidth\\\":1,\\\"stroke\\\":\\\"rgba(255, 255, 255, 0)\\\",\\\"autoplay\\\":false,\\\"visible\\\":true,\\\"color\\\":\\\"#FFFFFF\\\",\\\"genieControls\\\":false,\\\"instructions\\\":\\\"\\\"}\"},\"param\":[{\"name\":\"next\",\"value\":\"7a0a8ec5-73eb-4710-b5b3-d176cc8a5007\"}],\"manifest\":{\"media\":[{\"assetId\":\"do_20051275\"},{\"assetId\":\"protractor1_img\"},{\"assetId\":\"protractorButton_img\"},{\"assetId\":\"angle\"},{\"assetId\":\"QuizImage\"},{\"assetId\":\"audioIcon\"},{\"assetId\":\"zoomIcon\"}]},\"shape\":[{\"type\":\"rect\",\"x\":-0.14,\"y\":0.99,\"fill\":\"#FFFF00\",\"w\":102.78,\"h\":103.71,\"stroke\":\"rgba(255, 255, 255, 0)\",\"strokeWidth\":1,\"opacity\":1,\"rotate\":0,\"z-index\":0,\"id\":\"d685bbd6-05a2-427c-9c98-767de6196aac\",\"config\":{\"__cdata\":\"{\\\"opacity\\\":100,\\\"strokeWidth\\\":1,\\\"stroke\\\":\\\"rgba(255, 255, 255, 0)\\\",\\\"autoplay\\\":false,\\\"visible\\\":true,\\\"color\\\":\\\"#FFFF00\\\"}\"}}],\"org.ekstep.questionset\":[{\"x\":9,\"y\":6,\"w\":80,\"h\":85,\"rotate\":0,\"z-index\":1,\"id\":\"e6672012-93c3-48d8-b4ae-ad4bd407ab55\",\"data\":{\"__cdata\":\"[{\\\"template\\\":[{\\\"text\\\":{\\\"event\\\":{\\\"action\\\":[{\\\"asset_model\\\":\\\"item.question_audio\\\",\\\"sound\\\":true,\\\"type\\\":\\\"command\\\",\\\"command\\\":\\\"stop\\\"},{\\\"asset_model\\\":\\\"item.question_audio\\\",\\\"type\\\":\\\"command\\\",\\\"command\\\":\\\"play\\\"}],\\\"type\\\":\\\"click\\\"},\\\"color\\\":\\\"#4c4c4c\\\",\\\"w\\\":100,\\\"x\\\":0,\\\"fontsize\\\":\\\"3.5vw\\\",\\\"y\\\":5,\\\"lineHeight\\\":1.4,\\\"model\\\":\\\"item.title\\\",\\\"align\\\":\\\"center\\\"},\\\"angle\\\":{\\\"w\\\":60,\\\"h\\\":60,\\\"x\\\":10,\\\"y\\\":20,\\\"model\\\":\\\"item.question\\\",\\\"id\\\":\\\"angleTest\\\"},\\\"g\\\":{\\\"image\\\":{\\\"stretch\\\":false,\\\"enableDrag\\\":true,\\\"w\\\":100,\\\"x\\\":0,\\\"y\\\":0,\\\"id\\\":\\\"protractorId\\\",\\\"asset\\\":\\\"protractor1_img\\\"},\\\"w\\\":60,\\\"h\\\":50,\\\"x\\\":20,\\\"y\\\":40},\\\"image\\\":{\\\"event\\\":{\\\"action\\\":{\\\"asset\\\":\\\"protractorId\\\",\\\"type\\\":\\\"command\\\",\\\"command\\\":\\\"toggleshow\\\"},\\\"type\\\":\\\"click\\\"},\\\"stretch\\\":false,\\\"z-index\\\":1,\\\"w\\\":10,\\\"x\\\":102,\\\"y\\\":5,\\\"asset\\\":\\\"protractorButton_img\\\"},\\\"mcq\\\":{\\\"options\\\":{\\\"shape\\\":{\\\"w\\\":100,\\\"h\\\":100,\\\"x\\\":0,\\\"y\\\":0,\\\"fill\\\":\\\"#E4F1FE\\\"},\\\"text\\\":{\\\"z-index\\\":2,\\\"color\\\":\\\"#4c4c4c\\\",\\\"w\\\":100,\\\"h\\\":80,\\\"x\\\":0,\\\"fontsize\\\":\\\"3.5vw\\\",\\\"y\\\":20,\\\"model\\\":\\\"option.value.text\\\",\\\"valign\\\":\\\"middle\\\",\\\"align\\\":\\\"center\\\"},\\\"layout\\\":\\\"table\\\",\\\"w\\\":100,\\\"h\\\":10,\\\"options\\\":\\\"options\\\",\\\"x\\\":0,\\\"y\\\":87,\\\"cols\\\":5,\\\"marginX\\\":2,\\\"marginY\\\":1},\\\"multi_select\\\":false,\\\"density\\\":10,\\\"shadow\\\":\\\"#666666\\\",\\\"model\\\":\\\"item\\\"},\\\"id\\\":\\\"protractor_template\\\"}],\\\"itemType\\\":\\\"UNIT\\\",\\\"code\\\":\\\"org.ekstep.assessmentitem.literacy_5aa651e686d47\\\",\\\"subject\\\":\\\"domain\\\",\\\"qlevel\\\":\\\"EASY\\\",\\\"channel\\\":\\\"in.ekstep\\\",\\\"description\\\":\\\"test v1 question\\\",\\\"language\\\":[\\\"English\\\"],\\\"medium\\\":\\\"English\\\",\\\"media\\\":[{\\\"id\\\":\\\"do_20051275\\\",\\\"type\\\":\\\"image\\\",\\\"src\\\":\\\"https://ekstep-public-qa.s3-ap-south-1.amazonaws.com/content/logo_371_1476701760_1476701966868.jpg\\\",\\\"asset_id\\\":\\\"do_20051275\\\"}],\\\"title\\\":\\\"Copy of Measure Angels\\\",\\\"type\\\":\\\"mcq\\\",\\\"createdOn\\\":\\\"2018-03-12T10:09:42.581+0000\\\",\\\"gradeLevel\\\":[\\\"Class 1\\\"],\\\"appId\\\":\\\"ekstep_portal\\\",\\\"options\\\":[{\\\"value\\\":{\\\"type\\\":\\\"mixed\\\",\\\"text\\\":\\\"45\\\",\\\"count\\\":\\\"\\\",\\\"image\\\":null,\\\"audio\\\":null,\\\"resvalue\\\":\\\"45\\\",\\\"resindex\\\":0}},{\\\"value\\\":{\\\"type\\\":\\\"mixed\\\",\\\"text\\\":\\\"40\\\",\\\"count\\\":\\\"\\\",\\\"image\\\":null,\\\"audio\\\":null,\\\"resvalue\\\":\\\"40\\\",\\\"resindex\\\":1}},{\\\"value\\\":{\\\"type\\\":\\\"mixed\\\",\\\"text\\\":\\\"120\\\",\\\"count\\\":\\\"\\\",\\\"image\\\":null,\\\"audio\\\":null,\\\"resvalue\\\":\\\"120\\\",\\\"resindex\\\":2}},{\\\"value\\\":{\\\"type\\\":\\\"mixed\\\",\\\"text\\\":\\\"90\\\",\\\"count\\\":\\\"\\\",\\\"image\\\":null,\\\"audio\\\":null,\\\"resvalue\\\":\\\"90\\\",\\\"resindex\\\":3},\\\"score\\\":1,\\\"answer\\\":true}],\\\"question_image\\\":\\\"do_20051275\\\",\\\"lastUpdatedOn\\\":\\\"2018-03-12T10:09:42.581+0000\\\",\\\"used_for\\\":\\\"worksheet\\\",\\\"lastUpdatedBy\\\":\\\"769\\\",\\\"identifier\\\":\\\"do_21245879814211174411679\\\",\\\"question\\\":\\\"Tell the Angels of image\\\",\\\"consumerId\\\":\\\"2c43f136-c02f-4494-9fb9-fd228e2c77e6\\\",\\\"version\\\":1,\\\"versionKey\\\":\\\"1520849382581\\\",\\\"framework\\\":\\\"NCF\\\",\\\"concepts\\\":[{\\\"identifier\\\":\\\"LO39\\\",\\\"name\\\":\\\"Akshara Recognition\\\",\\\"objectType\\\":\\\"Concept\\\",\\\"relation\\\":\\\"associatedTo\\\",\\\"description\\\":null,\\\"index\\\":null,\\\"status\\\":null,\\\"depth\\\":null,\\\"mimeType\\\":null,\\\"visibility\\\":null,\\\"compatibilityLevel\\\":null}],\\\"createdBy\\\":\\\"769\\\",\\\"max_score\\\":1,\\\"domain\\\":[\\\"literacy\\\"],\\\"name\\\":\\\"Copy of Measure Angels\\\",\\\"template_id\\\":\\\"do_20051274\\\",\\\"category\\\":\\\"MCQ\\\",\\\"status\\\":\\\"Live\\\",\\\"isSelected\\\":true,\\\"$$hashKey\\\":\\\"object:1636\\\",\\\"mediamanifest\\\":{\\\"media\\\":[{\\\"id\\\":\\\"do_20051275\\\",\\\"type\\\":\\\"image\\\",\\\"src\\\":\\\"https://ekstep-public-qa.s3-ap-south-1.amazonaws.com/content/logo_371_1476701760_1476701966868.jpg\\\",\\\"asset_id\\\":\\\"do_20051275\\\"},{\\\"src\\\":\\\"https://ekstep-public-qa.s3-ap-south-1.amazonaws.com/content/do_20051274/protractor1.png\\\",\\\"id\\\":\\\"protractor1_img\\\",\\\"type\\\":\\\"image\\\"},{\\\"src\\\":\\\"https://ekstep-public-qa.s3-ap-south-1.amazonaws.com/content/do_20051274/protractorbutton.png\\\",\\\"id\\\":\\\"protractorButton_img\\\",\\\"type\\\":\\\"image\\\"},{\\\"src\\\":\\\"https://ekstep-public-qa.s3-ap-south-1.amazonaws.com/content/do_20051274/js/angleplugin.js\\\",\\\"id\\\":\\\"angle\\\",\\\"type\\\":\\\"plugin\\\",\\\"plugin\\\":\\\"org.ekstep.questionset\\\",\\\"ver\\\":\\\"1.0\\\"}]}}]\"},\"config\":{\"__cdata\":\"{\\\"title\\\":\\\"qs\\\",\\\"max_score\\\":1,\\\"allow_skip\\\":true,\\\"show_feedback\\\":true,\\\"shuffle_questions\\\":false,\\\"shuffle_options\\\":false,\\\"total_items\\\":1,\\\"btn_edit\\\":\\\"Edit\\\"}\"},\"org.ekstep.question\":[{\"id\":\"ee21c44b-51cc-432c-8091-ed52ec4889dd\",\"type\":\"mcq\",\"pluginId\":\"org.ekstep.questionset.quiz\",\"pluginVer\":\"1.0\",\"templateId\":\"horizontalMCQ\",\"data\":{\"__cdata\":\"{\\\"questionnaire\\\":{\\\"items\\\":{\\\"do_21245879814211174411679\\\":[{\\\"itemType\\\":\\\"UNIT\\\",\\\"code\\\":\\\"org.ekstep.assessmentitem.literacy_5aa651e686d47\\\",\\\"subject\\\":\\\"domain\\\",\\\"qlevel\\\":\\\"EASY\\\",\\\"channel\\\":\\\"in.ekstep\\\",\\\"description\\\":\\\"test v1 question\\\",\\\"language\\\":[\\\"English\\\"],\\\"medium\\\":\\\"English\\\",\\\"media\\\":[{\\\"id\\\":\\\"do_20051275\\\",\\\"type\\\":\\\"image\\\",\\\"src\\\":\\\"https://ekstep-public-qa.s3-ap-south-1.amazonaws.com/content/logo_371_1476701760_1476701966868.jpg\\\",\\\"asset_id\\\":\\\"do_20051275\\\"}],\\\"title\\\":\\\"Copy of Measure Angels\\\",\\\"type\\\":\\\"mcq\\\",\\\"createdOn\\\":\\\"2018-03-12T10:09:42.581+0000\\\",\\\"gradeLevel\\\":[\\\"Class 1\\\"],\\\"appId\\\":\\\"ekstep_portal\\\",\\\"options\\\":[{\\\"value\\\":{\\\"type\\\":\\\"mixed\\\",\\\"text\\\":\\\"45\\\",\\\"count\\\":\\\"\\\",\\\"image\\\":null,\\\"audio\\\":null,\\\"resvalue\\\":\\\"45\\\",\\\"resindex\\\":0}},{\\\"value\\\":{\\\"type\\\":\\\"mixed\\\",\\\"text\\\":\\\"40\\\",\\\"count\\\":\\\"\\\",\\\"image\\\":null,\\\"audio\\\":null,\\\"resvalue\\\":\\\"40\\\",\\\"resindex\\\":1}},{\\\"value\\\":{\\\"type\\\":\\\"mixed\\\",\\\"text\\\":\\\"120\\\",\\\"count\\\":\\\"\\\",\\\"image\\\":null,\\\"audio\\\":null,\\\"resvalue\\\":\\\"120\\\",\\\"resindex\\\":2}},{\\\"value\\\":{\\\"type\\\":\\\"mixed\\\",\\\"text\\\":\\\"90\\\",\\\"count\\\":\\\"\\\",\\\"image\\\":null,\\\"audio\\\":null,\\\"resvalue\\\":\\\"90\\\",\\\"resindex\\\":3},\\\"score\\\":1,\\\"answer\\\":true}],\\\"question_image\\\":\\\"do_20051275\\\",\\\"lastUpdatedOn\\\":\\\"2018-03-12T10:09:42.581+0000\\\",\\\"used_for\\\":\\\"worksheet\\\",\\\"lastUpdatedBy\\\":\\\"769\\\",\\\"identifier\\\":\\\"do_21245879814211174411679\\\",\\\"question\\\":\\\"Tell the Angels of image\\\",\\\"consumerId\\\":\\\"2c43f136-c02f-4494-9fb9-fd228e2c77e6\\\",\\\"version\\\":1,\\\"versionKey\\\":\\\"1520849382581\\\",\\\"framework\\\":\\\"NCF\\\",\\\"concepts\\\":[{\\\"identifier\\\":\\\"LO39\\\",\\\"name\\\":\\\"Akshara Recognition\\\",\\\"objectType\\\":\\\"Concept\\\",\\\"relation\\\":\\\"associatedTo\\\",\\\"description\\\":null,\\\"index\\\":null,\\\"status\\\":null,\\\"depth\\\":null,\\\"mimeType\\\":null,\\\"visibility\\\":null,\\\"compatibilityLevel\\\":null}],\\\"createdBy\\\":\\\"769\\\",\\\"max_score\\\":1,\\\"domain\\\":[\\\"literacy\\\"],\\\"name\\\":\\\"Copy of Measure Angels\\\",\\\"template_id\\\":\\\"do_20051274\\\",\\\"category\\\":\\\"MCQ\\\",\\\"status\\\":\\\"Live\\\",\\\"isSelected\\\":true,\\\"$$hashKey\\\":\\\"object:1636\\\",\\\"template\\\":\\\"protractor_template\\\"}]},\\\"item_sets\\\":[{\\\"count\\\":1,\\\"id\\\":\\\"do_21245879814211174411679\\\"}],\\\"title\\\":\\\"qs\\\",\\\"max_score\\\":1,\\\"allow_skip\\\":true,\\\"show_feedback\\\":true,\\\"shuffle_questions\\\":false,\\\"shuffle_options\\\":false,\\\"total_items\\\":1,\\\"btn_edit\\\":\\\"Edit\\\"},\\\"template\\\":[{\\\"text\\\":{\\\"event\\\":{\\\"action\\\":[{\\\"asset_model\\\":\\\"item.question_audio\\\",\\\"sound\\\":true,\\\"type\\\":\\\"command\\\",\\\"command\\\":\\\"stop\\\"},{\\\"asset_model\\\":\\\"item.question_audio\\\",\\\"type\\\":\\\"command\\\",\\\"command\\\":\\\"play\\\"}],\\\"type\\\":\\\"click\\\"},\\\"color\\\":\\\"#4c4c4c\\\",\\\"w\\\":100,\\\"x\\\":0,\\\"fontsize\\\":\\\"3.5vw\\\",\\\"y\\\":5,\\\"lineHeight\\\":1.4,\\\"model\\\":\\\"item.title\\\",\\\"align\\\":\\\"center\\\"},\\\"angle\\\":{\\\"w\\\":60,\\\"h\\\":60,\\\"x\\\":10,\\\"y\\\":20,\\\"model\\\":\\\"item.question\\\",\\\"id\\\":\\\"angleTest\\\"},\\\"g\\\":{\\\"image\\\":{\\\"stretch\\\":false,\\\"enableDrag\\\":true,\\\"w\\\":100,\\\"x\\\":0,\\\"y\\\":0,\\\"id\\\":\\\"protractorId\\\",\\\"asset\\\":\\\"protractor1_img\\\"},\\\"w\\\":60,\\\"h\\\":50,\\\"x\\\":20,\\\"y\\\":40},\\\"image\\\":{\\\"event\\\":{\\\"action\\\":{\\\"asset\\\":\\\"protractorId\\\",\\\"type\\\":\\\"command\\\",\\\"command\\\":\\\"toggleshow\\\"},\\\"type\\\":\\\"click\\\"},\\\"stretch\\\":false,\\\"z-index\\\":1,\\\"w\\\":10,\\\"x\\\":102,\\\"y\\\":5,\\\"asset\\\":\\\"protractorButton_img\\\"},\\\"mcq\\\":{\\\"options\\\":{\\\"shape\\\":{\\\"w\\\":100,\\\"h\\\":100,\\\"x\\\":0,\\\"y\\\":0,\\\"fill\\\":\\\"#E4F1FE\\\"},\\\"text\\\":{\\\"z-index\\\":2,\\\"color\\\":\\\"#4c4c4c\\\",\\\"w\\\":100,\\\"h\\\":80,\\\"x\\\":0,\\\"fontsize\\\":\\\"3.5vw\\\",\\\"y\\\":20,\\\"model\\\":\\\"option.value.text\\\",\\\"valign\\\":\\\"middle\\\",\\\"align\\\":\\\"center\\\"},\\\"layout\\\":\\\"table\\\",\\\"w\\\":100,\\\"h\\\":10,\\\"options\\\":\\\"options\\\",\\\"x\\\":0,\\\"y\\\":87,\\\"cols\\\":5,\\\"marginX\\\":2,\\\"marginY\\\":1},\\\"multi_select\\\":false,\\\"density\\\":10,\\\"shadow\\\":\\\"#666666\\\",\\\"model\\\":\\\"item\\\"},\\\"id\\\":\\\"protractor_template\\\"}]}\"},\"config\":{\"__cdata\":\"{\\\"type\\\":\\\"items\\\",\\\"var\\\":\\\"item\\\"}\"},\"w\":80,\"h\":85,\"x\":9,\"y\":6}]}]},{\"x\":0,\"y\":0,\"w\":100,\"h\":100,\"id\":\"7a0a8ec5-73eb-4710-b5b3-d176cc8a5007\",\"rotate\":null,\"config\":{\"__cdata\":\"{\\\"opacity\\\":100,\\\"strokeWidth\\\":1,\\\"stroke\\\":\\\"rgba(255, 255, 255, 0)\\\",\\\"autoplay\\\":false,\\\"visible\\\":true,\\\"color\\\":\\\"#FFFFFF\\\",\\\"genieControls\\\":false,\\\"instructions\\\":\\\"\\\"}\"},\"param\":[{\"name\":\"previous\",\"value\":\"7555527e-eabe-401b-bdb5-511c344dabae\"}],\"manifest\":{\"media\":[{\"assetId\":\"do_2124558710313533441346\"},{\"assetId\":\"uth\"},{\"assetId\":\"tenth\"},{\"assetId\":\"one\"},{\"assetId\":\"QuizImage\"},{\"assetId\":\"audioIcon\"},{\"assetId\":\"zoomIcon\"}]},\"org.ekstep.questionset\":[{\"x\":9,\"y\":6,\"w\":80,\"h\":85,\"rotate\":0,\"z-index\":0,\"id\":\"1c8403b2-3eb4-47a8-b8c9-66dc28c79837\",\"data\":{\"__cdata\":\"[{\\\"template\\\":[{\\\"text\\\":[{\\\"color\\\":\\\"#191919\\\",\\\"w\\\":100,\\\"h\\\":20,\\\"x\\\":0,\\\"fontsize\\\":\\\"1.8em\\\",\\\"y\\\":5,\\\"lineHeight\\\":2,\\\"model\\\":\\\"item.question\\\",\\\"align\\\":\\\"center\\\"},{\\\"color\\\":\\\"#000\\\",\\\"w\\\":30,\\\"h\\\":10,\\\"x\\\":62,\\\"fontsize\\\":\\\"2em\\\",\\\"y\\\":90,\\\"model\\\":\\\"item.text_after_box\\\",\\\"valign\\\":\\\"middle\\\",\\\"align\\\":\\\"left\\\"}],\\\"g\\\":{\\\"image\\\":{\\\"event\\\":{\\\"action\\\":[{\\\"asset_model\\\":\\\"item.question_audio\\\",\\\"sound\\\":true,\\\"type\\\":\\\"command\\\",\\\"command\\\":\\\"stop\\\"},{\\\"asset_model\\\":\\\"item.question_audio\\\",\\\"type\\\":\\\"command\\\",\\\"command\\\":\\\"play\\\"}],\\\"type\\\":\\\"click\\\"},\\\"stretch\\\":false,\\\"w\\\":100,\\\"x\\\":0,\\\"y\\\":0,\\\"model\\\":\\\"item.question_image\\\",\\\"align\\\":\\\"center\\\"},\\\"w\\\":70,\\\"h\\\":50,\\\"x\\\":15,\\\"y\\\":35},\\\"input\\\":{\\\"w\\\":20,\\\"h\\\":10,\\\"x\\\":40,\\\"y\\\":90,\\\"model\\\":\\\"item.ans1\\\",\\\"id\\\":\\\"text1\\\",\\\"align\\\":\\\"center\\\",\\\"fill\\\":\\\"#FFFFA5\\\",\\\"type\\\":\\\"text\\\",\\\"class\\\":\\\"inputText\\\"},\\\"id\\\":\\\"txt_img_type_text_template\\\"}],\\\"itemType\\\":\\\"UNIT\\\",\\\"code\\\":\\\"org.ekstep.assessmentitem.literacy_5aa65d90a1dc3\\\",\\\"subject\\\":\\\"domain\\\",\\\"qlevel\\\":\\\"EASY\\\",\\\"channel\\\":\\\"in.ekstep\\\",\\\"description\\\":\\\"\\\",\\\"language\\\":[\\\"English\\\"],\\\"medium\\\":\\\"English\\\",\\\"media\\\":[{\\\"id\\\":\\\"do_2124558710313533441346\\\",\\\"type\\\":\\\"image\\\",\\\"src\\\":\\\"https://ekstep-public-qa.s3-ap-south-1.amazonaws.com/content/do_2124558710313533441346/artifact/ee9e245e93d1bee3ebe8778c914fab8b_1520492069362.jpeg\\\",\\\"asset_id\\\":\\\"do_2124558710313533441346\\\"}],\\\"title\\\":\\\"v1 - Fill in the blanks (with image) - word answer\\\",\\\"type\\\":\\\"ftb\\\",\\\"createdOn\\\":\\\"2018-03-12T10:59:28.685+0000\\\",\\\"gradeLevel\\\":[\\\"KG\\\"],\\\"appId\\\":\\\"ekstep_portal\\\",\\\"question_image\\\":\\\"do_2124558710313533441346\\\",\\\"lastUpdatedOn\\\":\\\"2018-03-12T10:59:28.685+0000\\\",\\\"used_for\\\":\\\"worksheet\\\",\\\"lastUpdatedBy\\\":\\\"785\\\",\\\"identifier\\\":\\\"do_21245882260426752011843\\\",\\\"question\\\":\\\"Name the image\\\",\\\"consumerId\\\":\\\"2c43f136-c02f-4494-9fb9-fd228e2c77e6\\\",\\\"version\\\":1,\\\"versionKey\\\":\\\"1520852368685\\\",\\\"framework\\\":\\\"NCF\\\",\\\"answer\\\":{\\\"ans1\\\":{\\\"value\\\":\\\"Cauliflower\\\",\\\"score\\\":1}},\\\"concepts\\\":[{\\\"identifier\\\":\\\"LO39\\\",\\\"name\\\":\\\"Akshara Recognition\\\",\\\"objectType\\\":\\\"Concept\\\",\\\"relation\\\":\\\"associatedTo\\\",\\\"description\\\":null,\\\"index\\\":null,\\\"status\\\":null,\\\"depth\\\":null,\\\"mimeType\\\":null,\\\"visibility\\\":null,\\\"compatibilityLevel\\\":null}],\\\"createdBy\\\":\\\"785\\\",\\\"domain\\\":[\\\"literacy\\\"],\\\"max_score\\\":1,\\\"name\\\":\\\"v1 - Fill in the blanks (with image) - word answer\\\",\\\"template_id\\\":\\\"do_2124360781602734081436\\\",\\\"category\\\":\\\"MCQ\\\",\\\"status\\\":\\\"Live\\\",\\\"isSelected\\\":true,\\\"$$hashKey\\\":\\\"object:3386\\\",\\\"mediamanifest\\\":{\\\"media\\\":[{\\\"id\\\":\\\"do_2124558710313533441346\\\",\\\"type\\\":\\\"image\\\",\\\"src\\\":\\\"https://ekstep-public-qa.s3-ap-south-1.amazonaws.com/content/do_2124558710313533441346/artifact/ee9e245e93d1bee3ebe8778c914fab8b_1520492069362.jpeg\\\",\\\"asset_id\\\":\\\"do_2124558710313533441346\\\"}]}},{\\\"template\\\":[{\\\"image\\\":[{\\\"stretch\\\":false,\\\"visible\\\":false,\\\"w\\\":100,\\\"h\\\":100,\\\"x\\\":0,\\\"y\\\":0,\\\"asset\\\":\\\"tenth\\\"},{\\\"stretch\\\":false,\\\"visible\\\":false,\\\"w\\\":100,\\\"h\\\":100,\\\"x\\\":0,\\\"y\\\":0,\\\"asset\\\":\\\"one\\\"}],\\\"text\\\":{\\\"color\\\":\\\"#4c4c4c\\\",\\\"w\\\":100,\\\"h\\\":15,\\\"x\\\":0,\\\"fontsize\\\":\\\"3vw\\\",\\\"y\\\":10,\\\"lineHeight\\\":1.4,\\\"model\\\":\\\"item.question\\\",\\\"valign\\\":\\\"top\\\",\\\"align\\\":\\\"center\\\"},\\\"g\\\":{\\\"shape\\\":[{\\\"w\\\":15,\\\"h\\\":50,\\\"x\\\":20,\\\"y\\\":0,\\\"type\\\":\\\"rect\\\",\\\"stroke\\\":\\\"black\\\"},{\\\"w\\\":52,\\\"h\\\":50,\\\"x\\\":35,\\\"y\\\":0,\\\"type\\\":\\\"rect\\\",\\\"stroke\\\":\\\"black\\\"},{\\\"w\\\":15,\\\"h\\\":50,\\\"x\\\":20,\\\"y\\\":50,\\\"type\\\":\\\"rect\\\",\\\"stroke\\\":\\\"black\\\"},{\\\"w\\\":52,\\\"h\\\":50,\\\"x\\\":35,\\\"y\\\":50,\\\"type\\\":\\\"rect\\\",\\\"stroke\\\":\\\"black\\\"}],\\\"text\\\":[{\\\"color\\\":\\\"#4c4c4c\\\",\\\"w\\\":15,\\\"h\\\":50,\\\"x\\\":20,\\\"fontsize\\\":\\\"3vw\\\",\\\"y\\\":0,\\\"model\\\":\\\"item.num1\\\",\\\"valign\\\":\\\"middle\\\",\\\"align\\\":\\\"center\\\"},{\\\"color\\\":\\\"#4c4c4c\\\",\\\"w\\\":15,\\\"h\\\":50,\\\"x\\\":20,\\\"fontsize\\\":\\\"3vw\\\",\\\"y\\\":50,\\\"model\\\":\\\"item.num2\\\",\\\"valign\\\":\\\"middle\\\",\\\"align\\\":\\\"center\\\"},{\\\"w\\\":5,\\\"h\\\":20,\\\"x\\\":10,\\\"fontsize\\\":\\\"6vw\\\",\\\"y\\\":63,\\\"model\\\":\\\"item.operator\\\",\\\"align\\\":\\\"center\\\"}],\\\"uth\\\":[{\\\"inputdata\\\":\\\"item.num1\\\",\\\"w\\\":40,\\\"h\\\":35,\\\"x\\\":27,\\\"y\\\":2,\\\"id\\\":\\\"uth\\\"},{\\\"inputdata\\\":\\\"item.num2\\\",\\\"w\\\":40,\\\"h\\\":35,\\\"x\\\":27,\\\"y\\\":39,\\\"id\\\":\\\"uth\\\"}],\\\"w\\\":100,\\\"h\\\":45,\\\"x\\\":0,\\\"y\\\":33,\\\"id\\\":\\\"qImage\\\"},\\\"mcq\\\":{\\\"options\\\":{\\\"shape\\\":{\\\"w\\\":100,\\\"h\\\":100,\\\"x\\\":0,\\\"y\\\":0,\\\"fill\\\":\\\"#F3F3F3\\\",\\\"type\\\":\\\"roundrect\\\",\\\"stroke\\\":\\\"#B7B7B7\\\"},\\\"text\\\":{\\\"color\\\":\\\"#4c4c4c\\\",\\\"w\\\":100,\\\"h\\\":100,\\\"x\\\":0,\\\"fontsize\\\":\\\"3vw\\\",\\\"y\\\":0,\\\"model\\\":\\\"option.value.text\\\",\\\"valign\\\":\\\"middle\\\",\\\"align\\\":\\\"center\\\"},\\\"layout\\\":\\\"table\\\",\\\"heighlight\\\":\\\"yellow\\\",\\\"w\\\":100,\\\"h\\\":26,\\\"options\\\":\\\"options\\\",\\\"x\\\":0,\\\"y\\\":82,\\\"cols\\\":4,\\\"marginX\\\":3,\\\"marginY\\\":4},\\\"multi_select\\\":false,\\\"model\\\":\\\"item\\\"},\\\"id\\\":\\\"org.ekstep.mcq.uth.vertical\\\"}],\\\"itemType\\\":\\\"UNIT\\\",\\\"code\\\":\\\"org.ekstep.assessmentitem.literacy_5aaba7fd6c8c1\\\",\\\"subject\\\":\\\"domain\\\",\\\"qlevel\\\":\\\"EASY\\\",\\\"channel\\\":\\\"in.ekstep\\\",\\\"description\\\":\\\"\\\",\\\"language\\\":[\\\"English\\\"],\\\"medium\\\":\\\"English\\\",\\\"title\\\":\\\"v1 -  VERTICAL OPERATIONS WITH PLACE VALUE MODELS\\\",\\\"type\\\":\\\"mcq\\\",\\\"createdOn\\\":\\\"2018-03-16T11:18:21.475+0000\\\",\\\"gradeLevel\\\":[\\\"KG\\\"],\\\"appId\\\":\\\"ekstep_portal\\\",\\\"options\\\":[{\\\"value\\\":{\\\"type\\\":\\\"mixed\\\",\\\"text\\\":\\\"47\\\",\\\"count\\\":\\\"\\\",\\\"image\\\":null,\\\"audio\\\":null,\\\"resvalue\\\":\\\"47\\\",\\\"resindex\\\":0},\\\"score\\\":1,\\\"answer\\\":true},{\\\"value\\\":{\\\"type\\\":\\\"mixed\\\",\\\"text\\\":\\\"57\\\",\\\"count\\\":\\\"\\\",\\\"image\\\":null,\\\"audio\\\":null,\\\"resvalue\\\":\\\"57\\\",\\\"resindex\\\":1}},{\\\"value\\\":{\\\"type\\\":\\\"mixed\\\",\\\"text\\\":\\\"67\\\",\\\"count\\\":\\\"\\\",\\\"image\\\":null,\\\"audio\\\":null,\\\"resvalue\\\":\\\"67\\\",\\\"resindex\\\":2}},{\\\"value\\\":{\\\"type\\\":\\\"mixed\\\",\\\"text\\\":\\\"87\\\",\\\"count\\\":\\\"\\\",\\\"image\\\":null,\\\"audio\\\":null,\\\"resvalue\\\":\\\"87\\\",\\\"resindex\\\":3}}],\\\"lastUpdatedOn\\\":\\\"2018-03-16T11:18:21.475+0000\\\",\\\"used_for\\\":\\\"worksheet\\\",\\\"model\\\":{\\\"num1\\\":\\\"2\\\",\\\"operator\\\":\\\"+\\\",\\\"num2\\\":\\\"45\\\"},\\\"lastUpdatedBy\\\":\\\"785\\\",\\\"identifier\\\":\\\"do_2124616630392913921497\\\",\\\"question\\\":\\\"v1 -  VERTICAL OPERATIONS WITH PLACE VALUE MODELS\\\",\\\"consumerId\\\":\\\"2c43f136-c02f-4494-9fb9-fd228e2c77e6\\\",\\\"version\\\":1,\\\"versionKey\\\":\\\"1521199101475\\\",\\\"framework\\\":\\\"NCF\\\",\\\"concepts\\\":[{\\\"identifier\\\":\\\"LO39\\\",\\\"name\\\":\\\"Akshara Recognition\\\",\\\"objectType\\\":\\\"Concept\\\",\\\"relation\\\":\\\"associatedTo\\\",\\\"description\\\":null,\\\"index\\\":null,\\\"status\\\":null,\\\"depth\\\":null,\\\"mimeType\\\":null,\\\"visibility\\\":null,\\\"compatibilityLevel\\\":null}],\\\"createdBy\\\":\\\"785\\\",\\\"max_score\\\":1,\\\"domain\\\":[\\\"literacy\\\"],\\\"name\\\":\\\"v1 -  VERTICAL OPERATIONS WITH PLACE VALUE MODELS\\\",\\\"template_id\\\":\\\"do_2124360697275023361432\\\",\\\"category\\\":\\\"MCQ\\\",\\\"status\\\":\\\"Live\\\",\\\"isSelected\\\":true,\\\"$$hashKey\\\":\\\"object:3391\\\",\\\"mediamanifest\\\":{\\\"media\\\":[{\\\"src\\\":\\\"https://ekstep-public-qa.s3-ap-south-1.amazonaws.com/content/do_2124360697275023361432/assets/1518074918499/uthplugin.js\\\",\\\"id\\\":\\\"uth\\\",\\\"type\\\":\\\"plugin\\\",\\\"plugin\\\":\\\"org.ekstep.questionset\\\",\\\"ver\\\":\\\"1.0\\\"},{\\\"src\\\":\\\"https://ekstep-public-qa.s3-ap-south-1.amazonaws.com/content/do_2124360697275023361432/assets/1518074918502/tens.png\\\",\\\"id\\\":\\\"tenth\\\",\\\"type\\\":\\\"image\\\"},{\\\"src\\\":\\\"https://ekstep-public-qa.s3-ap-south-1.amazonaws.com/content/do_2124360697275023361432/assets/1518074918508/ones.png\\\",\\\"id\\\":\\\"one\\\",\\\"type\\\":\\\"image\\\"}]}},{\\\"template\\\":[{\\\"text\\\":{\\\"event\\\":{\\\"action\\\":[{\\\"asset_model\\\":\\\"item.question_audio\\\",\\\"sound\\\":true,\\\"type\\\":\\\"command\\\",\\\"command\\\":\\\"stop\\\"},{\\\"asset_model\\\":\\\"item.question_audio\\\",\\\"type\\\":\\\"command\\\",\\\"command\\\":\\\"play\\\"}],\\\"type\\\":\\\"click\\\"},\\\"color\\\":\\\"#4c4c4c\\\",\\\"w\\\":100,\\\"h\\\":15,\\\"x\\\":0,\\\"fontsize\\\":\\\"3vw\\\",\\\"y\\\":10,\\\"lineHeight\\\":1.4,\\\"model\\\":\\\"item.question\\\",\\\"valign\\\":\\\"top\\\",\\\"align\\\":\\\"center\\\"},\\\"mcq\\\":{\\\"options\\\":{\\\"shape\\\":{\\\"w\\\":100,\\\"h\\\":100,\\\"x\\\":0,\\\"y\\\":0,\\\"fill\\\":\\\"#F3F3F3\\\",\\\"type\\\":\\\"roundrect\\\",\\\"stroke\\\":\\\"B7B7B7\\\"},\\\"text\\\":{\\\"color\\\":\\\"#4c4c4c\\\",\\\"w\\\":96,\\\"h\\\":94,\\\"x\\\":2,\\\"fontsize\\\":\\\"3vw\\\",\\\"y\\\":3,\\\"lineHeight\\\":1.4,\\\"model\\\":\\\"option.value.text\\\",\\\"valign\\\":\\\"middle\\\",\\\"align\\\":\\\"center\\\"},\\\"event\\\":{\\\"action\\\":[{\\\"asset_model\\\":\\\"option.value.audio\\\",\\\"sound\\\":true,\\\"type\\\":\\\"command\\\",\\\"command\\\":\\\"stop\\\"},{\\\"asset_model\\\":\\\"option.value.audio\\\",\\\"type\\\":\\\"command\\\",\\\"command\\\":\\\"play\\\"}],\\\"type\\\":\\\"click\\\"},\\\"layout\\\":\\\"table\\\",\\\"highlight\\\":\\\"yellow\\\",\\\"w\\\":100,\\\"h\\\":69,\\\"options\\\":\\\"options\\\",\\\"x\\\":0,\\\"y\\\":33,\\\"cols\\\":1,\\\"marginX\\\":3,\\\"marginY\\\":4},\\\"multi_select\\\":false,\\\"shadow\\\":\\\"#56B1F7\\\",\\\"model\\\":\\\"item\\\"},\\\"id\\\":\\\"org.ekstep.mcq.ta.vertical\\\"}],\\\"itemType\\\":\\\"UNIT\\\",\\\"code\\\":\\\"org.ekstep.assessmentitem.numeracy_5aa672272493a\\\",\\\"subject\\\":\\\"domain\\\",\\\"qlevel\\\":\\\"EASY\\\",\\\"channel\\\":\\\"in.ekstep\\\",\\\"description\\\":\\\"\\\",\\\"language\\\":[\\\"English\\\"],\\\"medium\\\":\\\"English\\\",\\\"title\\\":\\\"v1 text question text option vertical\\\",\\\"type\\\":\\\"mcq\\\",\\\"createdOn\\\":\\\"2018-03-12T12:27:19.166+0000\\\",\\\"gradeLevel\\\":[\\\"Class 1\\\"],\\\"appId\\\":\\\"ekstep_portal\\\",\\\"options\\\":[{\\\"value\\\":{\\\"type\\\":\\\"mixed\\\",\\\"text\\\":\\\"apple\\\",\\\"count\\\":\\\"\\\",\\\"image\\\":null,\\\"audio\\\":null,\\\"resvalue\\\":\\\"apple\\\",\\\"resindex\\\":0},\\\"score\\\":1,\\\"answer\\\":true},{\\\"value\\\":{\\\"type\\\":\\\"mixed\\\",\\\"text\\\":\\\"cat\\\",\\\"count\\\":\\\"\\\",\\\"image\\\":null,\\\"audio\\\":null,\\\"resvalue\\\":\\\"cat\\\",\\\"resindex\\\":1}},{\\\"value\\\":{\\\"type\\\":\\\"mixed\\\",\\\"text\\\":\\\"dog\\\",\\\"count\\\":\\\"\\\",\\\"image\\\":null,\\\"audio\\\":null,\\\"resvalue\\\":\\\"dog\\\",\\\"resindex\\\":2}}],\\\"lastUpdatedOn\\\":\\\"2018-03-12T12:27:19.166+0000\\\",\\\"used_for\\\":\\\"worksheet\\\",\\\"lastUpdatedBy\\\":\\\"769\\\",\\\"identifier\\\":\\\"do_21245886578005606411875\\\",\\\"question\\\":\\\"Select the fruit name in the following\\\",\\\"consumerId\\\":\\\"2c43f136-c02f-4494-9fb9-fd228e2c77e6\\\",\\\"version\\\":1,\\\"versionKey\\\":\\\"1520857639166\\\",\\\"framework\\\":\\\"NCF\\\",\\\"concepts\\\":[{\\\"identifier\\\":\\\"C26\\\",\\\"name\\\":\\\"Introduction to Data Handling\\\",\\\"objectType\\\":\\\"Concept\\\",\\\"relation\\\":\\\"associatedTo\\\",\\\"description\\\":null,\\\"index\\\":null,\\\"status\\\":null,\\\"depth\\\":null,\\\"mimeType\\\":null,\\\"visibility\\\":null,\\\"compatibilityLevel\\\":null}],\\\"createdBy\\\":\\\"769\\\",\\\"max_score\\\":1,\\\"domain\\\":[\\\"numeracy\\\"],\\\"name\\\":\\\"v1 text question text option vertical\\\",\\\"template_id\\\":\\\"do_20051293\\\",\\\"category\\\":\\\"MCQ\\\",\\\"status\\\":\\\"Live\\\",\\\"isSelected\\\":true,\\\"$$hashKey\\\":\\\"object:3396\\\",\\\"mediamanifest\\\":{\\\"media\\\":[]}}]\"},\"config\":{\"__cdata\":\"{\\\"title\\\":\\\"qwe\\\",\\\"max_score\\\":3,\\\"allow_skip\\\":true,\\\"show_feedback\\\":true,\\\"shuffle_questions\\\":false,\\\"shuffle_options\\\":false,\\\"total_items\\\":3,\\\"btn_edit\\\":\\\"Edit\\\"}\"},\"org.ekstep.question\":[{\"id\":\"6897d541-c7d1-4d25-a5cd-e870eb550d5a\",\"type\":\"ftb\",\"pluginId\":\"org.ekstep.questionset.quiz\",\"pluginVer\":\"1.0\",\"templateId\":\"horizontalMCQ\",\"data\":{\"__cdata\":\"{\\\"questionnaire\\\":{\\\"items\\\":{\\\"do_21245882260426752011843\\\":[{\\\"itemType\\\":\\\"UNIT\\\",\\\"code\\\":\\\"org.ekstep.assessmentitem.literacy_5aa65d90a1dc3\\\",\\\"subject\\\":\\\"domain\\\",\\\"qlevel\\\":\\\"EASY\\\",\\\"channel\\\":\\\"in.ekstep\\\",\\\"description\\\":\\\"\\\",\\\"language\\\":[\\\"English\\\"],\\\"medium\\\":\\\"English\\\",\\\"media\\\":[{\\\"id\\\":\\\"do_2124558710313533441346\\\",\\\"type\\\":\\\"image\\\",\\\"src\\\":\\\"https://ekstep-public-qa.s3-ap-south-1.amazonaws.com/content/do_2124558710313533441346/artifact/ee9e245e93d1bee3ebe8778c914fab8b_1520492069362.jpeg\\\",\\\"asset_id\\\":\\\"do_2124558710313533441346\\\"}],\\\"title\\\":\\\"v1 - Fill in the blanks (with image) - word answer\\\",\\\"type\\\":\\\"ftb\\\",\\\"createdOn\\\":\\\"2018-03-12T10:59:28.685+0000\\\",\\\"gradeLevel\\\":[\\\"KG\\\"],\\\"appId\\\":\\\"ekstep_portal\\\",\\\"question_image\\\":\\\"do_2124558710313533441346\\\",\\\"lastUpdatedOn\\\":\\\"2018-03-12T10:59:28.685+0000\\\",\\\"used_for\\\":\\\"worksheet\\\",\\\"lastUpdatedBy\\\":\\\"785\\\",\\\"identifier\\\":\\\"do_21245882260426752011843\\\",\\\"question\\\":\\\"Name the image\\\",\\\"consumerId\\\":\\\"2c43f136-c02f-4494-9fb9-fd228e2c77e6\\\",\\\"version\\\":1,\\\"versionKey\\\":\\\"1520852368685\\\",\\\"framework\\\":\\\"NCF\\\",\\\"answer\\\":{\\\"ans1\\\":{\\\"value\\\":\\\"Cauliflower\\\",\\\"score\\\":1}},\\\"concepts\\\":[{\\\"identifier\\\":\\\"LO39\\\",\\\"name\\\":\\\"Akshara Recognition\\\",\\\"objectType\\\":\\\"Concept\\\",\\\"relation\\\":\\\"associatedTo\\\",\\\"description\\\":null,\\\"index\\\":null,\\\"status\\\":null,\\\"depth\\\":null,\\\"mimeType\\\":null,\\\"visibility\\\":null,\\\"compatibilityLevel\\\":null}],\\\"createdBy\\\":\\\"785\\\",\\\"domain\\\":[\\\"literacy\\\"],\\\"max_score\\\":1,\\\"name\\\":\\\"v1 - Fill in the blanks (with image) - word answer\\\",\\\"template_id\\\":\\\"do_2124360781602734081436\\\",\\\"category\\\":\\\"MCQ\\\",\\\"status\\\":\\\"Live\\\",\\\"isSelected\\\":true,\\\"$$hashKey\\\":\\\"object:3386\\\",\\\"template\\\":\\\"txt_img_type_text_template\\\"}]},\\\"item_sets\\\":[{\\\"count\\\":3,\\\"id\\\":\\\"do_21245882260426752011843\\\"}],\\\"title\\\":\\\"qwe\\\",\\\"max_score\\\":3,\\\"allow_skip\\\":true,\\\"show_feedback\\\":true,\\\"shuffle_questions\\\":false,\\\"shuffle_options\\\":false,\\\"total_items\\\":3,\\\"btn_edit\\\":\\\"Edit\\\"},\\\"template\\\":[{\\\"text\\\":[{\\\"color\\\":\\\"#191919\\\",\\\"w\\\":100,\\\"h\\\":20,\\\"x\\\":0,\\\"fontsize\\\":\\\"1.8em\\\",\\\"y\\\":5,\\\"lineHeight\\\":2,\\\"model\\\":\\\"item.question\\\",\\\"align\\\":\\\"center\\\"},{\\\"color\\\":\\\"#000\\\",\\\"w\\\":30,\\\"h\\\":10,\\\"x\\\":62,\\\"fontsize\\\":\\\"2em\\\",\\\"y\\\":90,\\\"model\\\":\\\"item.text_after_box\\\",\\\"valign\\\":\\\"middle\\\",\\\"align\\\":\\\"left\\\"}],\\\"g\\\":{\\\"image\\\":{\\\"event\\\":{\\\"action\\\":[{\\\"asset_model\\\":\\\"item.question_audio\\\",\\\"sound\\\":true,\\\"type\\\":\\\"command\\\",\\\"command\\\":\\\"stop\\\"},{\\\"asset_model\\\":\\\"item.question_audio\\\",\\\"type\\\":\\\"command\\\",\\\"command\\\":\\\"play\\\"}],\\\"type\\\":\\\"click\\\"},\\\"stretch\\\":false,\\\"w\\\":100,\\\"x\\\":0,\\\"y\\\":0,\\\"model\\\":\\\"item.question_image\\\",\\\"align\\\":\\\"center\\\"},\\\"w\\\":70,\\\"h\\\":50,\\\"x\\\":15,\\\"y\\\":35},\\\"input\\\":{\\\"w\\\":20,\\\"h\\\":10,\\\"x\\\":40,\\\"y\\\":90,\\\"model\\\":\\\"item.ans1\\\",\\\"id\\\":\\\"text1\\\",\\\"align\\\":\\\"center\\\",\\\"fill\\\":\\\"#FFFFA5\\\",\\\"type\\\":\\\"text\\\",\\\"class\\\":\\\"inputText\\\"},\\\"id\\\":\\\"txt_img_type_text_template\\\"}]}\"},\"config\":{\"__cdata\":\"{\\\"type\\\":\\\"items\\\",\\\"var\\\":\\\"item\\\"}\"},\"w\":80,\"h\":85,\"x\":9,\"y\":6},{\"id\":\"e9e0c738-7991-434d-b146-1590b9371cce\",\"type\":\"mcq\",\"pluginId\":\"org.ekstep.questionset.quiz\",\"pluginVer\":\"1.0\",\"templateId\":\"horizontalMCQ\",\"data\":{\"__cdata\":\"{\\\"questionnaire\\\":{\\\"items\\\":{\\\"do_2124616630392913921497\\\":[{\\\"itemType\\\":\\\"UNIT\\\",\\\"code\\\":\\\"org.ekstep.assessmentitem.literacy_5aaba7fd6c8c1\\\",\\\"subject\\\":\\\"domain\\\",\\\"qlevel\\\":\\\"EASY\\\",\\\"channel\\\":\\\"in.ekstep\\\",\\\"description\\\":\\\"\\\",\\\"language\\\":[\\\"English\\\"],\\\"medium\\\":\\\"English\\\",\\\"title\\\":\\\"v1 -  VERTICAL OPERATIONS WITH PLACE VALUE MODELS\\\",\\\"type\\\":\\\"mcq\\\",\\\"createdOn\\\":\\\"2018-03-16T11:18:21.475+0000\\\",\\\"gradeLevel\\\":[\\\"KG\\\"],\\\"appId\\\":\\\"ekstep_portal\\\",\\\"options\\\":[{\\\"value\\\":{\\\"type\\\":\\\"mixed\\\",\\\"text\\\":\\\"47\\\",\\\"count\\\":\\\"\\\",\\\"image\\\":null,\\\"audio\\\":null,\\\"resvalue\\\":\\\"47\\\",\\\"resindex\\\":0},\\\"score\\\":1,\\\"answer\\\":true},{\\\"value\\\":{\\\"type\\\":\\\"mixed\\\",\\\"text\\\":\\\"57\\\",\\\"count\\\":\\\"\\\",\\\"image\\\":null,\\\"audio\\\":null,\\\"resvalue\\\":\\\"57\\\",\\\"resindex\\\":1}},{\\\"value\\\":{\\\"type\\\":\\\"mixed\\\",\\\"text\\\":\\\"67\\\",\\\"count\\\":\\\"\\\",\\\"image\\\":null,\\\"audio\\\":null,\\\"resvalue\\\":\\\"67\\\",\\\"resindex\\\":2}},{\\\"value\\\":{\\\"type\\\":\\\"mixed\\\",\\\"text\\\":\\\"87\\\",\\\"count\\\":\\\"\\\",\\\"image\\\":null,\\\"audio\\\":null,\\\"resvalue\\\":\\\"87\\\",\\\"resindex\\\":3}}],\\\"lastUpdatedOn\\\":\\\"2018-03-16T11:18:21.475+0000\\\",\\\"used_for\\\":\\\"worksheet\\\",\\\"model\\\":{\\\"num1\\\":\\\"2\\\",\\\"operator\\\":\\\"+\\\",\\\"num2\\\":\\\"45\\\"},\\\"lastUpdatedBy\\\":\\\"785\\\",\\\"identifier\\\":\\\"do_2124616630392913921497\\\",\\\"question\\\":\\\"v1 -  VERTICAL OPERATIONS WITH PLACE VALUE MODELS\\\",\\\"consumerId\\\":\\\"2c43f136-c02f-4494-9fb9-fd228e2c77e6\\\",\\\"version\\\":1,\\\"versionKey\\\":\\\"1521199101475\\\",\\\"framework\\\":\\\"NCF\\\",\\\"concepts\\\":[{\\\"identifier\\\":\\\"LO39\\\",\\\"name\\\":\\\"Akshara Recognition\\\",\\\"objectType\\\":\\\"Concept\\\",\\\"relation\\\":\\\"associatedTo\\\",\\\"description\\\":null,\\\"index\\\":null,\\\"status\\\":null,\\\"depth\\\":null,\\\"mimeType\\\":null,\\\"visibility\\\":null,\\\"compatibilityLevel\\\":null}],\\\"createdBy\\\":\\\"785\\\",\\\"max_score\\\":1,\\\"domain\\\":[\\\"literacy\\\"],\\\"name\\\":\\\"v1 -  VERTICAL OPERATIONS WITH PLACE VALUE MODELS\\\",\\\"template_id\\\":\\\"do_2124360697275023361432\\\",\\\"category\\\":\\\"MCQ\\\",\\\"status\\\":\\\"Live\\\",\\\"isSelected\\\":true,\\\"$$hashKey\\\":\\\"object:3391\\\",\\\"template\\\":\\\"org.ekstep.mcq.uth.vertical\\\"}]},\\\"item_sets\\\":[{\\\"count\\\":3,\\\"id\\\":\\\"do_2124616630392913921497\\\"}],\\\"title\\\":\\\"qwe\\\",\\\"max_score\\\":3,\\\"allow_skip\\\":true,\\\"show_feedback\\\":true,\\\"shuffle_questions\\\":false,\\\"shuffle_options\\\":false,\\\"total_items\\\":3,\\\"btn_edit\\\":\\\"Edit\\\"},\\\"template\\\":[{\\\"image\\\":[{\\\"stretch\\\":false,\\\"visible\\\":false,\\\"w\\\":100,\\\"h\\\":100,\\\"x\\\":0,\\\"y\\\":0,\\\"asset\\\":\\\"tenth\\\"},{\\\"stretch\\\":false,\\\"visible\\\":false,\\\"w\\\":100,\\\"h\\\":100,\\\"x\\\":0,\\\"y\\\":0,\\\"asset\\\":\\\"one\\\"}],\\\"text\\\":{\\\"color\\\":\\\"#4c4c4c\\\",\\\"w\\\":100,\\\"h\\\":15,\\\"x\\\":0,\\\"fontsize\\\":\\\"3vw\\\",\\\"y\\\":10,\\\"lineHeight\\\":1.4,\\\"model\\\":\\\"item.question\\\",\\\"valign\\\":\\\"top\\\",\\\"align\\\":\\\"center\\\"},\\\"g\\\":{\\\"shape\\\":[{\\\"w\\\":15,\\\"h\\\":50,\\\"x\\\":20,\\\"y\\\":0,\\\"type\\\":\\\"rect\\\",\\\"stroke\\\":\\\"black\\\"},{\\\"w\\\":52,\\\"h\\\":50,\\\"x\\\":35,\\\"y\\\":0,\\\"type\\\":\\\"rect\\\",\\\"stroke\\\":\\\"black\\\"},{\\\"w\\\":15,\\\"h\\\":50,\\\"x\\\":20,\\\"y\\\":50,\\\"type\\\":\\\"rect\\\",\\\"stroke\\\":\\\"black\\\"},{\\\"w\\\":52,\\\"h\\\":50,\\\"x\\\":35,\\\"y\\\":50,\\\"type\\\":\\\"rect\\\",\\\"stroke\\\":\\\"black\\\"}],\\\"text\\\":[{\\\"color\\\":\\\"#4c4c4c\\\",\\\"w\\\":15,\\\"h\\\":50,\\\"x\\\":20,\\\"fontsize\\\":\\\"3vw\\\",\\\"y\\\":0,\\\"model\\\":\\\"item.num1\\\",\\\"valign\\\":\\\"middle\\\",\\\"align\\\":\\\"center\\\"},{\\\"color\\\":\\\"#4c4c4c\\\",\\\"w\\\":15,\\\"h\\\":50,\\\"x\\\":20,\\\"fontsize\\\":\\\"3vw\\\",\\\"y\\\":50,\\\"model\\\":\\\"item.num2\\\",\\\"valign\\\":\\\"middle\\\",\\\"align\\\":\\\"center\\\"},{\\\"w\\\":5,\\\"h\\\":20,\\\"x\\\":10,\\\"fontsize\\\":\\\"6vw\\\",\\\"y\\\":63,\\\"model\\\":\\\"item.operator\\\",\\\"align\\\":\\\"center\\\"}],\\\"uth\\\":[{\\\"inputdata\\\":\\\"item.num1\\\",\\\"w\\\":40,\\\"h\\\":35,\\\"x\\\":27,\\\"y\\\":2,\\\"id\\\":\\\"uth\\\"},{\\\"inputdata\\\":\\\"item.num2\\\",\\\"w\\\":40,\\\"h\\\":35,\\\"x\\\":27,\\\"y\\\":39,\\\"id\\\":\\\"uth\\\"}],\\\"w\\\":100,\\\"h\\\":45,\\\"x\\\":0,\\\"y\\\":33,\\\"id\\\":\\\"qImage\\\"},\\\"mcq\\\":{\\\"options\\\":{\\\"shape\\\":{\\\"w\\\":100,\\\"h\\\":100,\\\"x\\\":0,\\\"y\\\":0,\\\"fill\\\":\\\"#F3F3F3\\\",\\\"type\\\":\\\"roundrect\\\",\\\"stroke\\\":\\\"#B7B7B7\\\"},\\\"text\\\":{\\\"color\\\":\\\"#4c4c4c\\\",\\\"w\\\":100,\\\"h\\\":100,\\\"x\\\":0,\\\"fontsize\\\":\\\"3vw\\\",\\\"y\\\":0,\\\"model\\\":\\\"option.value.text\\\",\\\"valign\\\":\\\"middle\\\",\\\"align\\\":\\\"center\\\"},\\\"layout\\\":\\\"table\\\",\\\"heighlight\\\":\\\"yellow\\\",\\\"w\\\":100,\\\"h\\\":26,\\\"options\\\":\\\"options\\\",\\\"x\\\":0,\\\"y\\\":82,\\\"cols\\\":4,\\\"marginX\\\":3,\\\"marginY\\\":4},\\\"multi_select\\\":false,\\\"model\\\":\\\"item\\\"},\\\"id\\\":\\\"org.ekstep.mcq.uth.vertical\\\"}]}\"},\"config\":{\"__cdata\":\"{\\\"type\\\":\\\"items\\\",\\\"var\\\":\\\"item\\\"}\"},\"w\":80,\"h\":85,\"x\":9,\"y\":6},{\"id\":\"a5315753-848b-4582-bc6c-9c42d2ab9797\",\"type\":\"mcq\",\"pluginId\":\"org.ekstep.questionset.quiz\",\"pluginVer\":\"1.0\",\"templateId\":\"horizontalMCQ\",\"data\":{\"__cdata\":\"{\\\"questionnaire\\\":{\\\"items\\\":{\\\"do_21245886578005606411875\\\":[{\\\"itemType\\\":\\\"UNIT\\\",\\\"code\\\":\\\"org.ekstep.assessmentitem.numeracy_5aa672272493a\\\",\\\"subject\\\":\\\"domain\\\",\\\"qlevel\\\":\\\"EASY\\\",\\\"channel\\\":\\\"in.ekstep\\\",\\\"description\\\":\\\"\\\",\\\"language\\\":[\\\"English\\\"],\\\"medium\\\":\\\"English\\\",\\\"title\\\":\\\"v1 text question text option vertical\\\",\\\"type\\\":\\\"mcq\\\",\\\"createdOn\\\":\\\"2018-03-12T12:27:19.166+0000\\\",\\\"gradeLevel\\\":[\\\"Class 1\\\"],\\\"appId\\\":\\\"ekstep_portal\\\",\\\"options\\\":[{\\\"value\\\":{\\\"type\\\":\\\"mixed\\\",\\\"text\\\":\\\"apple\\\",\\\"count\\\":\\\"\\\",\\\"image\\\":null,\\\"audio\\\":null,\\\"resvalue\\\":\\\"apple\\\",\\\"resindex\\\":0},\\\"score\\\":1,\\\"answer\\\":true},{\\\"value\\\":{\\\"type\\\":\\\"mixed\\\",\\\"text\\\":\\\"cat\\\",\\\"count\\\":\\\"\\\",\\\"image\\\":null,\\\"audio\\\":null,\\\"resvalue\\\":\\\"cat\\\",\\\"resindex\\\":1}},{\\\"value\\\":{\\\"type\\\":\\\"mixed\\\",\\\"text\\\":\\\"dog\\\",\\\"count\\\":\\\"\\\",\\\"image\\\":null,\\\"audio\\\":null,\\\"resvalue\\\":\\\"dog\\\",\\\"resindex\\\":2}}],\\\"lastUpdatedOn\\\":\\\"2018-03-12T12:27:19.166+0000\\\",\\\"used_for\\\":\\\"worksheet\\\",\\\"lastUpdatedBy\\\":\\\"769\\\",\\\"identifier\\\":\\\"do_21245886578005606411875\\\",\\\"question\\\":\\\"Select the fruit name in the following\\\",\\\"consumerId\\\":\\\"2c43f136-c02f-4494-9fb9-fd228e2c77e6\\\",\\\"version\\\":1,\\\"versionKey\\\":\\\"1520857639166\\\",\\\"framework\\\":\\\"NCF\\\",\\\"concepts\\\":[{\\\"identifier\\\":\\\"C26\\\",\\\"name\\\":\\\"Introduction to Data Handling\\\",\\\"objectType\\\":\\\"Concept\\\",\\\"relation\\\":\\\"associatedTo\\\",\\\"description\\\":null,\\\"index\\\":null,\\\"status\\\":null,\\\"depth\\\":null,\\\"mimeType\\\":null,\\\"visibility\\\":null,\\\"compatibilityLevel\\\":null}],\\\"createdBy\\\":\\\"769\\\",\\\"max_score\\\":1,\\\"domain\\\":[\\\"numeracy\\\"],\\\"name\\\":\\\"v1 text question text option vertical\\\",\\\"template_id\\\":\\\"do_20051293\\\",\\\"category\\\":\\\"MCQ\\\",\\\"status\\\":\\\"Live\\\",\\\"isSelected\\\":true,\\\"$$hashKey\\\":\\\"object:3396\\\",\\\"template\\\":\\\"org.ekstep.mcq.ta.vertical\\\"}]},\\\"item_sets\\\":[{\\\"count\\\":3,\\\"id\\\":\\\"do_21245886578005606411875\\\"}],\\\"title\\\":\\\"qwe\\\",\\\"max_score\\\":3,\\\"allow_skip\\\":true,\\\"show_feedback\\\":true,\\\"shuffle_questions\\\":false,\\\"shuffle_options\\\":false,\\\"total_items\\\":3,\\\"btn_edit\\\":\\\"Edit\\\"},\\\"template\\\":[{\\\"text\\\":{\\\"event\\\":{\\\"action\\\":[{\\\"asset_model\\\":\\\"item.question_audio\\\",\\\"sound\\\":true,\\\"type\\\":\\\"command\\\",\\\"command\\\":\\\"stop\\\"},{\\\"asset_model\\\":\\\"item.question_audio\\\",\\\"type\\\":\\\"command\\\",\\\"command\\\":\\\"play\\\"}],\\\"type\\\":\\\"click\\\"},\\\"color\\\":\\\"#4c4c4c\\\",\\\"w\\\":100,\\\"h\\\":15,\\\"x\\\":0,\\\"fontsize\\\":\\\"3vw\\\",\\\"y\\\":10,\\\"lineHeight\\\":1.4,\\\"model\\\":\\\"item.question\\\",\\\"valign\\\":\\\"top\\\",\\\"align\\\":\\\"center\\\"},\\\"mcq\\\":{\\\"options\\\":{\\\"shape\\\":{\\\"w\\\":100,\\\"h\\\":100,\\\"x\\\":0,\\\"y\\\":0,\\\"fill\\\":\\\"#F3F3F3\\\",\\\"type\\\":\\\"roundrect\\\",\\\"stroke\\\":\\\"B7B7B7\\\"},\\\"text\\\":{\\\"color\\\":\\\"#4c4c4c\\\",\\\"w\\\":96,\\\"h\\\":94,\\\"x\\\":2,\\\"fontsize\\\":\\\"3vw\\\",\\\"y\\\":3,\\\"lineHeight\\\":1.4,\\\"model\\\":\\\"option.value.text\\\",\\\"valign\\\":\\\"middle\\\",\\\"align\\\":\\\"center\\\"},\\\"event\\\":{\\\"action\\\":[{\\\"asset_model\\\":\\\"option.value.audio\\\",\\\"sound\\\":true,\\\"type\\\":\\\"command\\\",\\\"command\\\":\\\"stop\\\"},{\\\"asset_model\\\":\\\"option.value.audio\\\",\\\"type\\\":\\\"command\\\",\\\"command\\\":\\\"play\\\"}],\\\"type\\\":\\\"click\\\"},\\\"layout\\\":\\\"table\\\",\\\"highlight\\\":\\\"yellow\\\",\\\"w\\\":100,\\\"h\\\":69,\\\"options\\\":\\\"options\\\",\\\"x\\\":0,\\\"y\\\":33,\\\"cols\\\":1,\\\"marginX\\\":3,\\\"marginY\\\":4},\\\"multi_select\\\":false,\\\"shadow\\\":\\\"#56B1F7\\\",\\\"model\\\":\\\"item\\\"},\\\"id\\\":\\\"org.ekstep.mcq.ta.vertical\\\"}]}\"},\"config\":{\"__cdata\":\"{\\\"type\\\":\\\"items\\\",\\\"var\\\":\\\"item\\\"}\"},\"w\":80,\"h\":85,\"x\":9,\"y\":6}]}]}],\"manifest\":{\"media\":[{\"id\":\"be861e99-521d-4c5c-bade-7ed850819727\",\"plugin\":\"org.ekstep.navigation\",\"ver\":\"1.0\",\"src\":\"/plugins/org.ekstep.navigation-1.0/renderer/controller/navigation_ctrl.js\",\"type\":\"js\"},{\"id\":\"be23d525-64d8-4a2b-b5ed-611393725ee0\",\"plugin\":\"org.ekstep.navigation\",\"ver\":\"1.0\",\"src\":\"/plugins/org.ekstep.navigation-1.0/renderer/templates/navigation.html\",\"type\":\"js\"},{\"id\":\"org.ekstep.navigation\",\"plugin\":\"org.ekstep.navigation\",\"ver\":\"1.0\",\"src\":\"/plugins/org.ekstep.navigation-1.0/renderer/plugin.js\",\"type\":\"plugin\"},{\"id\":\"org.ekstep.navigation_manifest\",\"plugin\":\"org.ekstep.navigation\",\"ver\":\"1.0\",\"src\":\"/plugins/org.ekstep.navigation-1.0/manifest.json\",\"type\":\"json\"},{\"id\":\"org.ekstep.questionset.quiz\",\"plugin\":\"org.ekstep.questionset.quiz\",\"ver\":\"1.0\",\"src\":\"/plugins/org.ekstep.questionset.quiz-1.0/renderer/plugin.js\",\"type\":\"plugin\"},{\"id\":\"org.ekstep.questionset.quiz_manifest\",\"plugin\":\"org.ekstep.questionset.quiz\",\"ver\":\"1.0\",\"src\":\"/plugins/org.ekstep.questionset.quiz-1.0/manifest.json\",\"type\":\"json\"},{\"id\":\"org.ekstep.iterator\",\"plugin\":\"org.ekstep.iterator\",\"ver\":\"1.0\",\"src\":\"/plugins/org.ekstep.iterator-1.0/renderer/plugin.js\",\"type\":\"plugin\"},{\"id\":\"org.ekstep.iterator_manifest\",\"plugin\":\"org.ekstep.iterator\",\"ver\":\"1.0\",\"src\":\"/plugins/org.ekstep.iterator-1.0/manifest.json\",\"type\":\"json\"},{\"id\":\"47aed3b4-d2e9-4a42-9de3-db779a8ec09a\",\"plugin\":\"org.ekstep.questionset\",\"ver\":\"1.0\",\"src\":\"/plugins/org.ekstep.questionset-1.0/renderer/utils/telemetry_logger.js\",\"type\":\"js\"},{\"id\":\"580316aa-8d9a-440e-bbe7-844d78677be3\",\"plugin\":\"org.ekstep.questionset\",\"ver\":\"1.0\",\"src\":\"/plugins/org.ekstep.questionset-1.0/renderer/utils/html_audio_plugin.js\",\"type\":\"js\"},{\"id\":\"8d996c18-9c33-48e0-aca1-b2b3e3529e57\",\"plugin\":\"org.ekstep.questionset\",\"ver\":\"1.0\",\"src\":\"/plugins/org.ekstep.questionset-1.0/renderer/utils/qs_feedback_popup.js\",\"type\":\"js\"},{\"id\":\"org.ekstep.questionset\",\"plugin\":\"org.ekstep.questionset\",\"ver\":\"1.0\",\"src\":\"/plugins/org.ekstep.questionset-1.0/renderer/plugin.js\",\"type\":\"plugin\"},{\"id\":\"org.ekstep.questionset_manifest\",\"plugin\":\"org.ekstep.questionset\",\"ver\":\"1.0\",\"src\":\"/plugins/org.ekstep.questionset-1.0/manifest.json\",\"type\":\"json\"},{\"id\":\"do_20051275\",\"type\":\"image\",\"src\":\"https://ekstep-public-qa.s3-ap-south-1.amazonaws.com/content/logo_371_1476701760_1476701966868.jpg\",\"asset_id\":\"do_20051275\"},{\"src\":\"https://ekstep-public-qa.s3-ap-south-1.amazonaws.com/content/do_20051274/protractor1.png\",\"id\":\"protractor1_img\",\"type\":\"image\"},{\"src\":\"https://ekstep-public-qa.s3-ap-south-1.amazonaws.com/content/do_20051274/protractorbutton.png\",\"id\":\"protractorButton_img\",\"type\":\"image\"},{\"src\":\"https://ekstep-public-qa.s3-ap-south-1.amazonaws.com/content/do_20051274/js/angleplugin.js\",\"id\":\"angle\",\"type\":\"plugin\",\"plugin\":\"org.ekstep.questionset\",\"ver\":\"1.0\"},{\"id\":\"QuizImage\",\"src\":\"/plugins/org.ekstep.questionset-1.0/editor/assets/quizimage.png\",\"assetId\":\"QuizImage\",\"type\":\"image\",\"preload\":true},{\"id\":\"audioIcon\",\"src\":\"/plugins/org.ekstep.questionunit.mcq-1.0/renderer/assets/audio-icon.png\",\"assetId\":\"audioIcon\",\"type\":\"image\",\"preload\":true},{\"id\":\"zoomIcon\",\"src\":\"/plugins/org.ekstep.questionunit.mcq-1.0/renderer/assets/expand-icon.png\",\"assetId\":\"zoomIcon\",\"type\":\"image\",\"preload\":true},{\"id\":\"do_2124558710313533441346\",\"type\":\"image\",\"src\":\"https://ekstep-public-qa.s3-ap-south-1.amazonaws.com/content/do_2124558710313533441346/artifact/ee9e245e93d1bee3ebe8778c914fab8b_1520492069362.jpeg\",\"asset_id\":\"do_2124558710313533441346\"},{\"src\":\"https://ekstep-public-qa.s3-ap-south-1.amazonaws.com/content/do_2124360697275023361432/assets/1518074918499/uthplugin.js\",\"id\":\"uth\",\"type\":\"plugin\",\"plugin\":\"org.ekstep.questionset\",\"ver\":\"1.0\"},{\"src\":\"https://ekstep-public-qa.s3-ap-south-1.amazonaws.com/content/do_2124360697275023361432/assets/1518074918502/tens.png\",\"id\":\"tenth\",\"type\":\"image\"},{\"src\":\"https://ekstep-public-qa.s3-ap-south-1.amazonaws.com/content/do_2124360697275023361432/assets/1518074918508/ones.png\",\"id\":\"one\",\"type\":\"image\"}]},\"plugin-manifest\":{\"plugin\":[{\"id\":\"org.ekstep.navigation\",\"ver\":\"1.0\",\"type\":\"plugin\",\"depends\":\"\"},{\"id\":\"org.ekstep.questionset.quiz\",\"ver\":\"1.0\",\"type\":\"plugin\",\"depends\":\"\"},{\"id\":\"org.ekstep.iterator\",\"ver\":\"1.0\",\"type\":\"plugin\",\"depends\":\"\"},{\"id\":\"org.ekstep.questionset\",\"ver\":\"1.0\",\"type\":\"plugin\",\"depends\":\"org.ekstep.questionset.quiz,org.ekstep.iterator\"}]},\"compatibilityVersion\":2}}","languageCode":"en"}}}